Workbook

Sheet Start Here
A1: RESEARCH HOME · R17 | B1: Purpose / rule | C1: Open / exact range | D1: Status | E1: Scope | F1: Owner / updater | G1: Updated UTC | H1: Notes
A2: Entry | B2: Use this compact view; full policy only when needed | C2: https://drive.google.com/file/d/1hBph5Fpxd5dVrolNkvzU8nb7xpxUiUdc/view | D2: ACTIVE | E2: Operations | F2: Any worker | G2: 2026-09-17T16:25:48.473074Z | H2: R17 supersedes R16 entry overhead; exact scientific gates retained
A3: Review work | B3: Pick oldest eligible nonauthor review; reconcile prior verdicts first | C3: https://docs.google.com/spreadsheets/d/1O6x8ivmaVUxYqKmCOXmToIHpMXqDI362ibqBl8HY8no/edit#gid=2026091702 | D3: LIVE QUEUE | E3: MATH / COMPUTE / OPS | F3: Claimed reviewer | G3: 2026-09-17T16:25:48.473074Z | H3: Same-provider technical review allowed; org independence remains separate
A4: Find a file | B4: Search title or ID, then read exact source | C4: https://docs.google.com/spreadsheets/d/1O6x8ivmaVUxYqKmCOXmToIHpMXqDI362ibqBl8HY8no/edit#gid=2026091703 | D4: METADATA SNAPSHOT | E4: Active-tree baseline + bounded updates | F4: Maintenance | G4: 2026-09-17T16:25:48.473074Z | H4: Catalog presence or omission does not prove mathematical truth or global completeness
A5: Quarantine | B5: Check exclusions and restoration tests before consumption | C5: https://docs.google.com/spreadsheets/d/1O6x8ivmaVUxYqKmCOXmToIHpMXqDI362ibqBl8HY8no/edit#gid=2026091704 | D5: ACTIVE | E5: Duplicates / defective scopes / unverified | F5: Any worker | G5: 2026-09-17T16:25:48.473074Z | H5: Frozen members are excluded by carrier+path+hash; keep bytes intact
A6: Claims and handoff | B6: Append unique event; read contenders; verify source/head before commit | C6: https://docs.google.com/spreadsheets/d/1O6x8ivmaVUxYqKmCOXmToIHpMXqDI362ibqBl8HY8no/edit#gid=2026091705 | D6: COOPERATIVE | E6: One exact target per claim | F6: Each session | G6: 2026-09-17T16:25:48.473074Z | H6: Not compare-and-swap; conflicting publication heads require reconciliation
A7: Claim expiry | B7: 120 minutes after valid heartbeat | C7: Work Events; legacy Active Work Claims | D7: ACTIVE | E7: Exact object + role | F7: Each session | G7: 2026-09-17T16:25:48.473074Z | H7: No resurrection by late heartbeat; use a new claim
A8: Cold entry | B8: This view plus needed queue/events in one multi-range read | C8: Read the allocated compact Start Here view after checking grid metadata (currently A1:H100, 100 rows). Resolve required stable keys; treat truncation as incomplete. Review Queue and Work Events use current target keys and relevant latest events, not assumed fixed prefixes. | D8: BOUND READ | E8: Control/navigation only | F8: Incoming worker | G8: 2026-09-17T16:25:48.473074Z | H8: Expand these bounded ranges when the queue/events grow; source reads, publication and verification are additional calls
A9: Cached continuation | B9: Check live policy, claim, source identity and output head | C9: https://drive.google.com/file/d/1fRS3BP82tCJC_K-hFCSm26Lbfv3EFoxq/view | D9: SCOPED REVALIDATION | E9: Changed dependencies only | F9: Incoming worker | G9: 2026-09-17T16:25:48.473074Z | H9: Bad/missing/stale handoff expands scoped reads; no automatic whole-Drive crawl
A10: Review ladder | B10: 7 days prioritize; 14 decompose; 30 escalate | C10: Review Queue age/action columns | D10: ACTIVE | E10: Age is prioritization, never approval | F10: Daily pickup + session entry | G10: 2026-09-17T16:25:48.473074Z | H10: Old date basis is explicit; metadata refresh does not reset substantive age
A11: Review credit | B11: Nonauthor same-provider technical pass is permitted | C11: PASS_TECHNICAL and independence are separate | D11: ACTIVE | E11: Author/coauthor checks are internal | F11: Reviewer | G11: 2026-09-17T16:25:48.473074Z | H11: Different provider can still be dependent; disclose exposure and coauthorship
A12: Publish states | B12: DRAFT → CANDIDATE_VERIFIED → READY_FOR_REVIEW → REVIEWED/AMEND | C12: One delivery manifest; immutable candidates | D12: ACTIVE | E12: Task completion is scoped | F12: Publisher | G12: 2026-09-17T16:25:48.473074Z | H12: Do not mark theorem complete merely because registration succeeded
... A23: Operator precedence | B23: Current direct user instruction controls operations | C23: Research Home / R17 policy | D23: ACTIVE | E23: No legacy budget or provider deadlock | F23: Owner | G23: 2026-09-17T16:25:48.473074Z | H23: No fabricated review or mathematical closure
A24: Audit coverage | B24: =COUNTA('File Catalog'!A2:A3500)&" catalog entries; "&COUNTA('Review Queue'!A2:A500)&" review routes; "&COUNTA('Quarantine Index'!A2:A300)&" exclusions/containers" -> 2952 catalog entries; 40 review routes; 22 exclusions/containers | C24: https://drive.google.com/file/d/1g5UP_KYlvPmx7LFwjGk6qK5QZLnL1hLj/view | D24: BOUNDED AUDIT | E24: No global proof closure; current release and verified deltas | F24: ROUND5 | G24: 2026-09-17T17:19:16.450Z | H24: RN5 adds five scoped exclusions and LM004 author-line erratum; frozen science retained
A25: Format accessibility | B25: Source map and 392 published reading copies | C25: https://docs.google.com/spreadsheets/d/1hO3MPQwtAiEjCGdOjZJTbB8fKIvt_3GU6KgxPGTPiLg/edit?usp=drivesdk | D25: PUBLISHED / VERIFIED | E25: Read Exceptions and copy verification scope | F25: ACCESS-20260917-4121 | G25: 2026-09-17T23:57:33.664Z | H25: 4,456 inventory items; 77 archives; 6,034 reading links. Report: https://drive.google.com/file/d/1sORvjt806v3z1rPAlH8I7CflxEZDUx8X/view?usp=drivesdk
A26: Folder structure | B26: Folder Directory, Folder Rules and Path Changes | C26: https://docs.google.com/spreadsheets/d/1hO3MPQwtAiEjCGdOjZJTbB8fKIvt_3GU6KgxPGTPiLg/edit?usp=drivesdk | D26: VERIFIED TARGETED UPDATE | E26: 755 folder rows; 238 mapped path changes | F26: STRUCTURE-20260918-C2087 | G26: 2026-09-18T00:17:48.912Z | H26: 184 folders checked through targeted live metadata; other rows retain the dated baseline. Folder Directory shows the basis.
A27: Naming and templates | B27: OP-ORG-20260918-v1.0; REVIEW_SCAFFOLD_V1 | C27: https://drive.google.com/file/d/1O_P3jbsHmKmA2U8OCks2_Hxf7W86Ae_Q/view?usp=drivesdk | D27: INSTALLED | E27: Operational naming and navigation only | F27: STRUCTURE-20260918-C2087 | G27: 2026-09-18T00:17:48.912Z | H27: Current triage index: https://drive.google.com/file/d/14eIT8SEj20pwUqnJ8DSjrrQcY9g4Ytjt/view?usp=drivesdk; existing T4/T5 charters and all 15 review scaffolds verified.
A28: Structure completion | B28: 18 September folder optimization report and rollback record | C28: https://drive.google.com/file/d/14z_m-gec3YRFWmJJksoJNRdT9_EN8h1C/view?usp=drivesdk | D28: COMPLETE | E28: 20 structure edits verified; source map updated | F28: STRUCTURE-20260918-C2087 | G28: 2026-09-18T00:23:00.610Z | H28: Report includes scope and readback evidence; guarded rollback: https://drive.google.com/file/d/1f14Tr1Pi1nrcByCFrx-8EnkuX_9n7SLG/view?usp=drivesdk
A29: Reusable operations | B29: Search by intended action; match scope and refresh exact source | C29: https://docs.google.com/spreadsheets/d/1O6x8ivmaVUxYqKmCOXmToIHpMXqDI362ibqBl8HY8no/edit#gid=2026091801 | D29: 15 SCOPED ENTRIES | E29: 8 conditional rules; 3 candidates; 2 negative rules; 2 boundaries | F29: OP-REUSE-20260918-66ba2ff9 | G29: 2026-09-18T03:02:43.860Z | H29: Guide: https://docs.google.com/document/d/1e7MLN7QbnHltfOq57jE7F738lEq5zM9PF1QhhkM9bdM/edit — usefulness UNMEASURED; source states preserved
A30: Operation trials | B30: Log prospective fixed-library / lemma-cache / operation comparisons | C30: https://docs.google.com/spreadsheets/d/1O6x8ivmaVUxYqKmCOXmToIHpMXqDI362ibqBl8HY8no/edit#gid=2026091802 | D30: READY; NO TRIALS YET | E30: Matched budgets, verified outcomes, overhead and held-out tasks | F30: OP-REUSE-20260918-66ba2ff9 | G30: 2026-09-18T03:02:43.860Z | H30: Exposed retrieval controls are not held-out usefulness evidence. Keep failures; no self-citation credit.
A31: Support withdrawal and scheduling | B31: Preserve premises, distinguish scheduling from truth, and require exact survivor warrants | C31: https://drive.google.com/file/d/1YvukN4MGwEoLcsLJRQjPjoESAjWsNbr_/view | https://github.com/d6g8k5htny-coder/main/pull/4 | D31: OPS SAFEGUARDS ACTIVE / CODE PILOT UNREVIEWED / SCIENCE NOT MIGRATED | E31: New work only; loss-only candidate checks; no scientific verdict, restoration, broad migration or automatic deployment | F31: R17 Work Events; RV-WITHDRAWAL-20260921-01 nonauthor technical review | G31: 2026-09-21T17:05:02Z | H31: OP-WITHDRAWAL-20260921-v1.0; source SHA256 0e9fcb229e2cdfab18c7aba6dfc6ec8c102611d4f463439cdb3290fc8d6e98e9. Recheck current source and exact heads at each task boundary. Do not invent dependency coverage or treat closed work as discharge.
A32: Governance rollout audit | B32: Re-evaluate installed rules for intent, typed scope, consumer migration and stage-skipping | C32: https://drive.google.com/file/d/1cKPOpv1foB7F7aBA-N0O8vtzetPWKjyR/view | https://github.com/d6g8k5htny-coder/main/pull/4 | D32: SCOPED CORRECTION v1.1 / CODE SHADOW / AUDIT INCOMPLETE | E32: Operational governance; no scientific status changes | F32: Any worker may report conflicts; changes require scoped evidence | G32: 2026-09-21T22:18:54Z | H32: R17's authorized supersessions remain effective; no retired-rule revival. Phase material behavior changes; guarded semantics-preserving maintenance has a bounded path. Binding classes require protocol/version. Source policy SHA256 2cb52776552681f9f17ba5cb5d50fc81b05003dd75e6f31893a7d427a51713d5. Review RV-ROLLOUT-R2-20260921-01 remains OPEN; no scientific migration or global uptake claim.
A33: Standing owner authorization — all models | B33: All project work preapproved; proceed without renewed permission or owner approval. | C33: https://drive.google.com/file/d/1N-afVwLVTloSB79GtEK1Fhfx7vdI4_b7/view | D33: EFFECTIVE / NO OWNER-APPROVAL WAIT | E33: All models; GitHub and Drive research, integration and administration; until Dylan changes it. | F33: Dylan Roy — corrected direct instruction; transcribed by ChatGPT | G33: 2026-09-23T19:35:04Z | H33: OP-AUTONOMY-20260923-v1.0 supersedes older project-specific owner-permission restrictions and the 48-hour limit. SHA256 1d51a9c68940b6047618286d7f9b3c55146d2650fe9d23d363e7d6133f7f4362. Preapproval is permission, not proof or a test result. No need to wait for all mirrors to update.

Sheet Review Queue
A1: Review key | B1: Domain | C1: Exact object | D1: Technical status | E1: Next action | F1: Packet or source | G1: Prior review / exposure | H1: Independence status | I1: Request time UTC | J1: Date basis | K1: Last substantive review UTC | L1: Age days | M1: Aging action | N1: Author / provider | O1: Body SHA-256 | P1: Body bytes | Q1: Reviewer / claim | R1: Verdict artifact | S1: Scope / dependencies
A2: RV-LM003-MAIN | B2: MATH | C2: LCR-DER-014-v1.0 | D2: NEEDS_RECONCILIATION | E2: Verify and register the existing exact technical verdict; perform new mathematics only for missing or changed criteria | F2: https://docs.google.com/document/d/13aLHEMKmN9n1v7PLSGbs_u_7dQ-Euvc91eWC4veIP0g/edit | G2: CURRENT EXACT BODY REPRODUCED / SAME-LINE MATHEMATICS PASS / ORGANIZATIONALLY DISTINCT EXACT-HASH THEOREM VERDICT OPEN / NONTERMINAL | H2: EXTERNAL_REVIEW_OPEN | I2: 2026-07-25T22:45:00Z | J2: Legacy review-routing record; request onset not independently reconstructed | L2: =IF(I2="","",MAX(0,TODAY()-DATE(VALUE(LEFT(I2,4)),VALUE(MID(I2,6,2)),VALUE(MID(I2,9,2))))) -> 60 | M2: =IF(L2="","UNKNOWN",IF(D2="PASS_TECHNICAL","EXTERNAL ONLY",IF(L2>=30,"ESCALATE",IF(L2>=14,"DECOMPOSE",IF(L2>=7,"PRIORITIZE","NEW"))))) -> ESCALATE | N2: OpenAI; exact author session to be disclosed | O2: 5173d26d6bfaae5ef65a8ae2d0ca9b829a291be3f7dacaba82bb38d2526bb83e | P2: 6874 | Q2: UNASSIGNED | S2: H1–H5 imply exact determinant-weighted boundary-layer probability O(r^3). | One organizationally distinct reviewer must bind an affirmative or corrective theorem verdict to the exact 6,874-byte body, checking support inclusion, empty intervals, the r^5 numerator, and normalizer direction.
A3: RV-LM004-MAIN | B3: MATH | C3: LCR-DER-016-v1.1 | D3: PASS_TECHNICAL | E3: Obtain one qualifying organizationally distinct LCR-REQ-039 exact-object verdict; do not repeat OpenAI technical work absent a new defect or hash change | F3: https://docs.google.com/document/d/1LKbFbisGVoEwzm3W-23-rdnzEF6crjxYCK-3G3J5OrA/edit | G3: CURRENT v1.1 EXACT BODY REPRODUCED / S2 SAME-FAMILY PASS RECONCILED / ANTHROPIC IMPORT RECONSTRUCTION SUPPORTS C1 TRANSFER BUT DID NOT ISSUE THE ISOLATED ACCEPTED EXACT-HASH VERDICT / NONTERMINAL | H3: EXTERNAL_REVIEW_OPEN | I3: 2026-07-25T21:12:00Z | J3: Legacy review-routing record; request onset not independently reconstructed | K3: 2026-09-17T16:55:40.169Z | L3: =IF(I3="","",MAX(0,TODAY()-DATE(VALUE(LEFT(I3,4)),VALUE(MID(I3,6,2)),VALUE(MID(I3,9,2))))) -> 60 | M3: =IF(L3="","UNKNOWN",IF(D3="PASS_TECHNICAL","EXTERNAL ONLY",IF(L3>=30,"ESCALATE",IF(L3>=14,"DECOMPOSE",IF(L3>=7,"PRIORITIZE","NEW"))))) -> EXTERNAL ONLY | N3: OpenAI; exact author session to be disclosed | O3: d43179f3abfd7e93f988725f3b89a5826cc71e0fa04840f65c7f93f3359d0f87 | P3: 10416 | Q3: Prior OpenAI technical reconciliation; ROUND5 author-line erratum; zero org credit | R3: https://drive.google.com/file/d/1QKujzzkp_nzCWFLky9ZayTzP_fbStxry/view | S3: Exact 10,416-byte body unchanged; duplicate-term finding withdrawn. Existing technical disposition retained. Qualifying organizationally distinct LCR-REQ-039 exact-hash verdict remains open.
A4: RV-LM006-MAIN | B4: MATH | C4: LCR-DER-019-v1.0 | D4: NEEDS_RECONCILIATION | E4: Verify and register the existing exact technical verdict; perform new mathematics only for missing or changed criteria | F4: https://docs.google.com/document/d/13aLHEMKmN9n1v7PLSGbs_u_7dQ-Euvc91eWC4veIP0g/edit | G4: EXTERNAL BYTE/HASH REPRODUCTION PASS / SAME-LINE THEOREM PASS / FULL ORGANIZATIONALLY DISTINCT THEOREM VERDICT OPEN / NONTERMINAL | H4: EXTERNAL_REVIEW_OPEN | I4: 2026-07-25T22:45:00Z | J4: Legacy review-routing record; request onset not independently reconstructed | L4: =IF(I4="","",MAX(0,TODAY()-DATE(VALUE(LEFT(I4,4)),VALUE(MID(I4,6,2)),VALUE(MID(I4,9,2))))) -> 60 | M4: =IF(L4="","UNKNOWN",IF(D4="PASS_TECHNICAL","EXTERNAL ONLY",IF(L4>=30,"ESCALATE",IF(L4>=14,"DECOMPOSE",IF(L4>=7,"PRIORITIZE","NEW"))))) -> ESCALATE | N4: OpenAI; exact author session to be disclosed | O4: 239ed094f70aa4352021572ad8bdc0c6ac6404edab4e1d7e61addec0c6659150 | P4: 9147 | Q4: UNASSIGNED | S4: Exact full-field typed normalizer satisfies Z_r/r²→E[Q_L²1{Q_L<0}]∈(0,∞). | Obtain a full organizationally distinct theorem verdict on the exact body: exact-torus Q_L limit, type boundary, uniform integrability, positivity, and two-sided r^2 bounds. Do not repeat transport-only work.
A5: RV-LM009-MAIN | B5: MATH | C5: LCR-DER-027-v1.0 | D5: PASS_TECHNICAL | E5: Finish external exact-object predicate; do not repeat Markov proof | F5: https://docs.google.com/document/d/17G4cRezBpLk9E1ds5rA615caPY9P19_JA80L57sF2ek/edit | G5: CURRENT v1.0 EXACT BODY REPRODUCED / SAME-LINE MATHEMATICS PASS / ORGANIZATIONALLY DISTINCT EXACT-HASH REVIEW OPEN / NONTERMINAL | H5: EXTERNAL_REVIEW_OPEN | I5: 2026-07-26T13:24:44Z | J5: Legacy review-routing record; request onset not independently reconstructed | K5: 2026-09-17T16:25:48.473074Z | L5: =IF(I5="","",MAX(0,TODAY()-DATE(VALUE(LEFT(I5,4)),VALUE(MID(I5,6,2)),VALUE(MID(I5,9,2))))) -> 59 | M5: =IF(L5="","UNKNOWN",IF(D5="PASS_TECHNICAL","EXTERNAL ONLY",IF(L5>=30,"ESCALATE",IF(L5>=14,"DECOMPOSE",IF(L5>=7,"PRIORITIZE","NEW"))))) -> EXTERNAL ONLY | N5: OpenAI; exact author session to be disclosed | O5: ccc07d959428519733c7fdf6c72f1bce63a40d0b0dc956ce0fe9f2ec459eb0b1 | P5: 3919 | Q5: OPS4 nonauthor / exposed / OpenAI | R5: https://drive.google.com/file/d/1cDFrsYx8l6jfGzQzYi0RemAw8Tv4d2qk/view | S5: All fixed moments imply REG_r failure is O(r^N) for every requested N. | One organizationally distinct reviewer must bind an affirmative or corrective verdict to the exact 3,919-byte body under LCR-REQ-029-v1.0 or the current LCR-REQ-052-v1.1 tail bundle, checking exponent selection, radius direction, exact U crosswalk, conditioned-to-Palm exponent doubling, and the no-fixed-exponential-tail firewall.
A6: RV-LM010-MAIN | B6: MATH | C6: LCR-DER-030-v1.1 | D6: NEEDS_RECONCILIATION | E6: Verify and register the existing exact technical verdict; perform new mathematics only for missing or changed criteria | F6: https://docs.google.com/document/d/13aLHEMKmN9n1v7PLSGbs_u_7dQ-Euvc91eWC4veIP0g/edit | G6: CURRENT REPAIRED v1.1 BODY REPRODUCED / SAME-LINE MATHEMATICS PASS / ORGANIZATIONALLY DISTINCT EXACT-HASH THEOREM VERDICT OPEN / NONTERMINAL | H6: EXTERNAL_REVIEW_OPEN | I6: 2026-07-25T22:45:00Z | J6: Legacy review-routing record; request onset not independently reconstructed | L6: =IF(I6="","",MAX(0,TODAY()-DATE(VALUE(LEFT(I6,4)),VALUE(MID(I6,6,2)),VALUE(MID(I6,9,2))))) -> 60 | M6: =IF(L6="","UNKNOWN",IF(D6="PASS_TECHNICAL","EXTERNAL ONLY",IF(L6>=30,"ESCALATE",IF(L6>=14,"DECOMPOSE",IF(L6>=7,"PRIORITIZE","NEW"))))) -> ESCALATE | N6: OpenAI; exact author session to be disclosed | O6: 05e0f20f0feb938ab7fca43c49b1f70fd0b8a492138ae805a418a5d028177ef2 | P6: 9335 | Q6: UNASSIGNED | S6: Exact good-boundary numerator uses subweight while denominator remains full exact normalizer. | One organizationally distinct reviewer must bind a verdict to the exact v1.1 body, including the full-denominator firewall and support-respecting regular-conditional-version clarification.
A7: RV-LM011-MAIN | B7: MATH | C7: LCR-DER-033-v1.0 | D7: NEEDS_RECONCILIATION | E7: Verify and register the existing exact technical verdict; perform new mathematics only for missing or changed criteria | F7: https://docs.google.com/document/d/1Tlkrs-WtWJg-OkrUvMIbwei_qi9BCa0-9xfHv4BSuEk/edit | G7: CURRENT v1.0 EXACT BODY REPRODUCED / SAME-LINE CONDITIONAL SYNTHESIS PASS / CURRENT DEPENDENCY GRAPH / OWN EXTERNAL VERDICT AND OPEN COMPONENT PREDICATES REQUIRED | H7: EXTERNAL_REVIEW_OPEN | I7: 2026-07-25T21:12:00Z | J7: Legacy review-routing record; request onset not independently reconstructed | L7: =IF(I7="","",MAX(0,TODAY()-DATE(VALUE(LEFT(I7,4)),VALUE(MID(I7,6,2)),VALUE(MID(I7,9,2))))) -> 60 | M7: =IF(L7="","UNKNOWN",IF(D7="PASS_TECHNICAL","EXTERNAL ONLY",IF(L7>=30,"ESCALATE",IF(L7>=14,"DECOMPOSE",IF(L7>=7,"PRIORITIZE","NEW"))))) -> ESCALATE | N7: OpenAI; exact author session to be disclosed | O7: 17c37fa1da7aa246f3018bd4ecc69b6e7beef5d8a1bda616d250146b3629efa9 | P7: 9721 | Q7: UNASSIGNED | S7: Current exact interfaces compose to imply 1-a_r=O(r^3). | First obtain the open exact component verdicts for LM003, LM004-v1.1, LM006, LM009, LM010-v1.1, LM012-v1.1, and LM013 Carrier-B-v1.1 plus joint stack. Then issue the organizationally distinct final synthesis verdict on the exact 9,721-byte body under current LCR-REQ-053-v1.2, using LCR-REQ-037-v1.0 as the object-level checklist.
A8: RV-LM012-MAIN | B8: MATH | C8: LCR-DER-043-v1.1 | D8: NEEDS_RECONCILIATION | E8: Verify and register the existing exact technical verdict; perform new mathematics only for missing or changed criteria | F8: https://docs.google.com/document/d/1X-46gXEIqZr8JMc458ikHGKtLsQpRIrEgwUknhUd5ig/edit | G8: CONTROLLING DEEP-THRESHOLD SUCCESSOR v1.1 / EXACT BODY VERIFIED SAME-LINE / ORGANIZATIONALLY DISTINCT EXACT-HASH REVIEW OPEN / NONTERMINAL | H8: EXTERNAL_REVIEW_OPEN | I8: 2026-07-26T13:36:00Z | J8: Legacy review-routing record; request onset not independently reconstructed | L8: =IF(I8="","",MAX(0,TODAY()-DATE(VALUE(LEFT(I8,4)),VALUE(MID(I8,6,2)),VALUE(MID(I8,9,2))))) -> 59 | M8: =IF(L8="","UNKNOWN",IF(D8="PASS_TECHNICAL","EXTERNAL ONLY",IF(L8>=30,"ESCALATE",IF(L8>=14,"DECOMPOSE",IF(L8>=7,"PRIORITIZE","NEW"))))) -> ESCALATE | N8: OpenAI; exact author session to be disclosed | O8: 68df32086da07fac8b042789de7a1c280aa2df56885532618c2fcabdb04b9ad4 | P8: 11543 | Q8: UNASSIGNED | S8: Coordinate-typed chart lift, one positive common small-r domain, and deep-threshold sample-event firewall for deterministic capture. | One organizationally distinct reviewer must execute LCR-REQ-045-v1.1 against the v1.1 hash and verify chart identity, deep-saddle threshold placement, common domain, and scaling.
A9: RV-LM013-BOREL-GLOBALIZATION | B9: MATH | C9: LCR-DER-061-v1.1 | D9: NEEDS_RECONCILIATION | E9: Verify and register the existing exact technical verdict; perform new mathematics only for missing or changed criteria | F9: https://docs.google.com/document/d/1c_-wbmoEiwKl4lzpKQFCY5BpdKDP0iYCqPhfEUSFkdk/edit | G9: PARENT EXACT-OBJECT REVIEW SATISFIED / CARRIER A EXACT-HASH APPROVE / CARRIER B v1.1 SAME-LINE PASS / EXTERNAL v1.1 CONVERSION AND JOINT STACK VERDICT OPEN / NONTERMINAL | H9: EXTERNAL_REVIEW_OPEN | I9: 2026-07-26T15:18:00Z | J9: Legacy review-routing record; request onset not independently reconstructed | L9: =IF(I9="","",MAX(0,TODAY()-DATE(VALUE(LEFT(I9,4)),VALUE(MID(I9,6,2)),VALUE(MID(I9,9,2))))) -> 59 | M9: =IF(L9="","UNKNOWN",IF(D9="PASS_TECHNICAL","EXTERNAL ONLY",IF(L9>=30,"ESCALATE",IF(L9>=14,"DECOMPOSE",IF(L9>=7,"PRIORITIZE","NEW"))))) -> ESCALATE | N9: OpenAI; exact author session to be disclosed | O9: 8ec4386fc1214523c98a5ae84acf4f5f64a6601aa2c63728f4382701b82dc3b7 | P9: 8928 | Q9: UNASSIGNED | S9: Countable Borel globalization, selector independence, Borel convergence event, certificate inclusion, and conditional exact Palm admissibility whenever 0<Z<infinity. | Obtain the narrow organizationally distinct Carrier B v1.1 conversion under LS-P01-REQ-002, then issue the repaired joint three-object interface verdict. Do not repeat the satisfied parent or Carrier A reviews.
A10: RV-DQ-005 | B10: MATH | C10: GP-DER/DATA-212 full-matrix exact finite-dimensional base-mass successor | D10: NEEDS_RECONCILIATION | E10: Resolve current exact target/hash and existing verdicts; then perform a bounded nonauthor technical review | F10: Proof https://docs.google.com/document/d/1XPukFF2usb9WyA2bRVvxwKebOxtHakZGJlfRSf7ewds/edit | source https://docs.google.com/document/d/1yaQ8R1OW1t-WJT7JGp3rVco3FQkIYXELshVI6Wt6vUY/edit | result https://docs.google.com/document/d/1mmIwF4m7yoXw2DOnjmdfqiZg36xyYNZX_PuAhMsoT3E/edit | request https://docs.google.com/document/d/1X9nr7tRhGrudpTdS-4QVsGxGoEAjt0OxLI7SEt592kg/edit | G10: OPEN / SUCCESSOR ELIGIBLE / GP-DATA-204 AMEND REQUIRED | OpenAI may reconcile only; organizationally distinct successor-hash review required | H10: LEGACY_PREDICATE_RETAINED | I10: 2026-07-25T16:15:00Z | J10: Dispatch Created UTC; not proof of zero intervening review | L10: =IF(I10="","",MAX(0,TODAY()-DATE(VALUE(LEFT(I10,4)),VALUE(MID(I10,6,2)),VALUE(MID(I10,9,2))))) -> 60 | M10: =IF(L10="","UNKNOWN",IF(D10="PASS_TECHNICAL","EXTERNAL ONLY",IF(L10>=30,"ESCALATE",IF(L10>=14,"DECOMPOSE",IF(L10>=7,"PRIORITIZE","NEW"))))) -> ESCALATE | N10: Disclose exact-object authorship; provider alone is insufficient | O10: UNRESOLVED — bind before review | Q10: UNASSIGNED | S10: Reconstruct and rerun GP-DATA-212; audit the full 9×9 spectral witnesses, direct-sum cross-check, exact nine-coordinate box geometry, derived distance rational, transformed torus reserve, perturbation chain, density lower bound, r_GR=r_D, p_B=10^-48, hashes, and controls; issue PASS / AMEND / FAIL. | Exact source/result roundtrip; execution or independent reconstruction; all 18 full-matrix Sylvester minors; explicit box intervals and distance derivation; periodization and density directions; hostile mutations; no theorem promotion.
A11: RV-DQ-017 | B11: COMPUTE | C11: LS-DATA-013 q0 verifier 1.2.1 hardening successor | D11: NEEDS_RECONCILIATION | E11: Resolve current exact target/hash and existing verdicts; then perform a bounded nonauthor technical review | F11: request https://docs.google.com/document/d/1zB58oOT1tmzzF5TAAlHqA8A1wxznjk2qTYMZ4BzV6Jw/edit | package https://docs.google.com/document/d/1B8_l-jXd5jo5ETMmoF-tMx8PcuwwshAq51KiagHDMp0/edit | audit https://docs.google.com/document/d/1B7YRIniaDmiXdKVSGLHy-S_y_hwQ7Yt5MNIx3zameCo/edit | G11: OPEN / EXTERNAL-FAMILY ELIGIBLE / NONCANONICAL ONLY | Non-OpenAI verifier/security reviewer or qualified human may earn successor-review credit; OpenAI logistics only | H11: LEGACY_PREDICATE_RETAINED | I11: 2026-07-26T00:02:00Z | J11: Dispatch Created UTC; not proof of zero intervening review | L11: =IF(I11="","",MAX(0,TODAY()-DATE(VALUE(LEFT(I11,4)),VALUE(MID(I11,6,2)),VALUE(MID(I11,9,2))))) -> 59 | M11: =IF(L11="","UNKNOWN",IF(D11="PASS_TECHNICAL","EXTERNAL ONLY",IF(L11>=30,"ESCALATE",IF(L11>=14,"DECOMPOSE",IF(L11>=7,"PRIORITIZE","NEW"))))) -> ESCALATE | N11: Disclose exact-object authorship; provider alone is insufficient | O11: UNRESOLVED — bind before review | Q11: UNASSIGNED | S11: Execute LS-REQ-014 against source SHA 5202c5fa33b1f08d502220943443573cc8c8e3a31682e6f3079443647fe0f6b9. Verify duplicate-key rejection at byte boundary, empty-route rejection, structural cycle invalidity, predecessor compatibility, 12 original tests, nine CL mutations, root-report equality, exact report/receipt identities, and active-file immutability. | Source and output capsule hashes reproduced; machine SHA 65af5209...2219; report SHA 5442f314...4b01; 12/12 + 9/9 pass; all cycles invalid; zero roots promotable unchanged; explicit APPROVE / AMEND / FAIL; no installation.
A12: RV-DQ-020 | B12: COMPUTE | C12: GP-DATA-218 stable-key guarded register-write reference and sandbox qualification | D12: NEEDS_RECONCILIATION | E12: Resolve current exact target/hash and existing verdicts; then perform a bounded nonauthor technical review | F12: request https://docs.google.com/document/d/1fVXf0h33ZKHqklydALKXCXB65gPKJZSdILew1Genmeg/edit | proof https://docs.google.com/document/d/1pzgS54wGicsakLmpL53m2Jf5-YLAlfNfBIDXRgWUvWw/edit | controlling package https://docs.google.com/document/d/1EktScfxgfH9OkeosIS8_6h1flyQmHgnCs142iFvQcRc/edit | supplement https://docs.google.com/document/d/1kPR2Fsh47eT73WHvyT_dv90hRQxjCNaVlU37LyanU_A/edit | G12: OPEN / EXTERNAL-FAMILY ELIGIBLE / SANDBOX-ONLY | Non-OpenAI verifier/security reviewer or qualified human may earn successor-review credit; OpenAI logistics only | H12: LEGACY_PREDICATE_RETAINED | I12: 2026-07-26T02:29:00Z | J12: Dispatch Created UTC; not proof of zero intervening review | L12: =IF(I12="","",MAX(0,TODAY()-DATE(VALUE(LEFT(I12,4)),VALUE(MID(I12,6,2)),VALUE(MID(I12,9,2))))) -> 59 | M12: =IF(L12="","UNKNOWN",IF(D12="PASS_TECHNICAL","EXTERNAL ONLY",IF(L12>=30,"ESCALATE",IF(L12>=14,"DECOMPOSE",IF(L12>=7,"PRIORITIZE","NEW"))))) -> ESCALATE | N12: Disclose exact-object authorship; provider alone is insufficient | O12: UNRESOLVED — bind before review | Q12: UNASSIGNED | S12: Execute GP-REQ-219 against controlling source SHA 199b7ce57f065b54b2a8f160e89fe38ef90f3118408d2fbb5eeca8a601a8855a. Reproduce the package; audit fresh sheet-title resolution, unique primary-key location, stale-row and stale-grid resistance, preconditions, patch scope, post-write verification, receipts, and all six isolated target schemas including Duplicate Flags. Use DQ018-AUD-001 only as same-family mutation and schema-coverage guidance. | Three controlling raw identities reproduced; R0-R15 plus R12A/R13A complete; M1-M14 attempted; 14/14 controlling reference checks, 20/20 supplement tests, and six-schema Drive correspondence verified; explicit APPROVE / AMEND / FAIL / CANNOT VERIFY verdict; no production installation.
A13: RV-DQ-023 | B13: MATH | C13: LS-DER-021 TB-G2 compact-mark all-typed contact-intensity candidate | D13: NEEDS_RECONCILIATION | E13: Resolve current exact target/hash and existing verdicts; then perform a bounded nonauthor technical review | F13: corrected work order https://docs.google.com/document/d/17jWejscjJpJrkml5bXQbWn8nvTeMRwcW_5-V32lJfWU/edit | parent request https://docs.google.com/document/d/12Y2SurB-s-V-UqkmJih-Lu2k3gTdYLuLZnUTCs6EZ7o/edit | parent theorem https://docs.google.com/document/d/16dSMQF3nbRcx93feO8vJzdnT8wDQvO-p6zViPtyUazw/edit | companion https://docs.google.com/document/d/1AUEXzPfbZsdtArlkHNhIUK4hbHqg8ATbb5M99Ex57HU/edit | reconciliation https://docs.google.com/document/d/1oGWql4Hez1BGDfUVl1USgZ2K3--DO5D2XGmcEgKwiSo/edit | erratum https://docs.google.com/document/d/1qYErvvtnUYio27BC7n6BJCnBw-GgC_dR3Y6eguUD5KA/edit | G13: OPEN / PRIOR ANTHROPIC SCOPED REVIEW EXISTS / THIRD-FAMILY EXACT-HASH AND UNIFORM-ENVELOPE GATE OPEN / DQ-053 COMPANION REVIEW OPEN | One Anthropic lineage supplies scoped partial TB-G2 evidence; OpenAI LS-DER-032 supplies zero-credit same-family interface proof; DQ-023’s next independent path must be neither OpenAI nor Anthropic. | H13: LEGACY_PREDICATE_RETAINED | I13: 2026-07-26T13:35:00Z | J13: Dispatch Created UTC; not proof of zero intervening review | L13: =IF(I13="","",MAX(0,TODAY()-DATE(VALUE(LEFT(I13,4)),VALUE(MID(I13,6,2)),VALUE(MID(I13,9,2))))) -> 59 | M13: =IF(L13="","UNKNOWN",IF(D13="PASS_TECHNICAL","EXTERNAL ONLY",IF(L13>=30,"ESCALATE",IF(L13>=14,"DECOMPOSE",IF(L13>=7,"PRIORITIZE","NEW"))))) -> ESCALATE | N13: Disclose exact-object authorship; provider alone is insufficient | O13: UNRESOLVED — bind before review | Q13: UNASSIGNED | S13: Execute LS-DER-021-REVIEW-002 against LS-DER-021. Reproduce the exact body, adjudicate the six-pin eigenfloor, uniform density/moment/integrability envelope, equations (15),(16),(23), q-behaviour, and full same-law normalizer; reconcile separately with LS-DER-032/DQ-053. | Capability and canary pass; OP-PROT-017 body reproduced; blind method reservation frozen; mutations M1–M9 completed; reviewer is neither OpenAI nor Anthropic; exact scoped verdict and downstream/non-effect statement returned; no first-review claim.
A14: RV-DQ-027 | B14: COMPUTE | C14: TRC-EC020-v0.4 derived carrier successors and GP-DATA-233 validator | D14: NEEDS_RECONCILIATION | E14: Resolve current exact target/hash and existing verdicts; then perform a bounded nonauthor technical review | F14: https://docs.google.com/document/d/1Flv8fSNCQmiN1FJ05quf1dsfiGRTKlh5hZODCFvj1VQ/edit | G14: OPEN / EXTERNAL-FAMILY ELIGIBLE / EXACT-HASH PACKAGE REVIEW READY / ZERO-CREDIT GP PREFLIGHT PASS | Non-OpenAI package reviewer may earn one package-review independence credit; OpenAI preflight supplies zero credit. | H14: LEGACY_PREDICATE_RETAINED | I14: 2026-07-26T14:42:24Z | J14: Dispatch Created UTC; not proof of zero intervening review | L14: =IF(I14="","",MAX(0,TODAY()-DATE(VALUE(LEFT(I14,4)),VALUE(MID(I14,6,2)),VALUE(MID(I14,9,2))))) -> 59 | M14: =IF(L14="","UNKNOWN",IF(D14="PASS_TECHNICAL","EXTERNAL ONLY",IF(L14>=30,"ESCALATE",IF(L14>=14,"DECOMPOSE",IF(L14>=7,"PRIORITIZE","NEW"))))) -> ESCALATE | N14: Disclose exact-object authorship; provider alone is insufficient | O14: UNRESOLVED — bind before review | Q14: UNASSIGNED | S14: Execute GP-REQ-235 R0-R10 as the permitted outside reviewer. The GP preflight reproduced all exact hashes, the validator receipt, nine leaves, live IDs/MIMEs, topology, and 10 fail-closed controls; independently adjudicate three Drive-title mismatches. | Reproduce SHA-256 values 0c19d4bb...20a95, 23861601...77b1, 466d544d...ddb1 and validator source e8d51d76...d64b8; decide whether the three title mismatches are nonmaterial or require a numbered successor; issue the required scoped verdict. Root NONE; SEALED NO.
A15: RV-DQ-035 | B15: MATH | C15: LS-DER-026 TB-G4 full-kappa selected near-diagonal tail theorem | D15: NEEDS_RECONCILIATION | E15: Resolve current exact target/hash and existing verdicts; then perform a bounded nonauthor technical review | F15: request https://docs.google.com/document/d/1Y99z0sQWMDweMCdHzWAYgoRTuysmkiQwQFPLGDs49ho/edit | candidate https://docs.google.com/document/d/1kSk34R28YpUdPmFjrLam1yDfOrcghyWJhTE_WbzqDGE/edit | G15: OPEN / EXTERNAL-FAMILY ELIGIBLE / EXACT-HASH REVIEW READY | Non-OpenAI Gaussian-analysis reviewer or qualified human may earn organizational-independence credit; OpenAI logistics only | H15: LEGACY_PREDICATE_RETAINED | I15: 2026-07-26T15:25:52Z | J15: Dispatch Created UTC; not proof of zero intervening review | L15: =IF(I15="","",MAX(0,TODAY()-DATE(VALUE(LEFT(I15,4)),VALUE(MID(I15,6,2)),VALUE(MID(I15,9,2))))) -> 59 | M15: =IF(L15="","UNKNOWN",IF(D15="PASS_TECHNICAL","EXTERNAL ONLY",IF(L15>=30,"ESCALATE",IF(L15>=14,"DECOMPOSE",IF(L15>=7,"PRIORITIZE","NEW"))))) -> ESCALATE | N15: Disclose exact-object authorship; provider alone is insufficient | O15: UNRESOLVED — bind before review | Q15: UNASSIGNED | S15: Execute LS-REQ-022 against LS-DER-026 frozen body 11,725 bytes / SHA-256 e4d8094ed1bfc9f9cc7491f13efd5cc5294ba3b5f4fbd4bc8bbba33dd1a2ab5d. Reconstruct corrected-pin decay, determinant moments, compact selection portability, cutoff, and dominated convergence. | Hash reproduced; R0-R17 complete; M1-M16 attempted; explicit APPROVE / CLARIFY / AMEND / FAIL / CANNOT VERIFY verdict; exact near-diagonal scope; no full-density promotion.
A16: RV-DQ-038 | B16: MATH | C16: LS-DER-022 TB-G3 exact actual-selection reduction and kappa-normalized capture | D16: NEEDS_RECONCILIATION | E16: Resolve current exact target/hash and existing verdicts; then perform a bounded nonauthor technical review | F16: request https://docs.google.com/document/d/10ai9iyt83V3wwkasqOzifVuw0xES5G4dAUTJJwq_UHo/edit | candidate https://docs.google.com/document/d/1rwKtmy2vnXTYfp0jFrf5Ca1jaBj0DYr7Uf5-Pui33Uo/edit | Anthropic review https://docs.google.com/document/d/1o0aeX97l_f6Z0fRc9yTgw0TY_pYcWHS7RTB8YxeanDw/edit | reconciliation https://docs.google.com/document/d/1oGWql4Hez1BGDfUVl1USgZ2K3--DO5D2XGmcEgKwiSo/edit | identity https://docs.google.com/document/d/1J7ZI-VzAyBQjsa8aKGcgySFI1y2Y23SYi6_tuv8NTBg/edit | G16: OPEN / ONE ANTHROPIC PARTIAL VERDICT RECEIVED / EXACT-OBJECT COMPLETION STILL REQUIRED | One Anthropic lineage approves the safe probability bridge at mathematical core; exact hash and lower-layer fixed-mark/import scope remain incomplete | H16: LEGACY_PREDICATE_RETAINED | I16: 2026-07-26T15:47:00Z | J16: Dispatch Created UTC; not proof of zero intervening review | L16: =IF(I16="","",MAX(0,TODAY()-DATE(VALUE(LEFT(I16,4)),VALUE(MID(I16,6,2)),VALUE(MID(I16,9,2))))) -> 59 | M16: =IF(L16="","UNKNOWN",IF(D16="PASS_TECHNICAL","EXTERNAL ONLY",IF(L16>=30,"ESCALATE",IF(L16>=14,"DECOMPOSE",IF(L16>=7,"PRIORITIZE","NEW"))))) -> ESCALATE | N16: Disclose exact-object authorship; provider alone is insufficient | O16: UNRESOLVED — bind before review | Q16: UNASSIGNED | S16: Execute LS-REQ-018 against LS-DER-022 frozen body 21,932 bytes / SHA-256 e5a61739bf09c1972edeb39e683c38da4adbf387c95d65aadf979b84a9568aaf. Verify p=a q_adj+eta, safe complement inequality, fixed-mark composition, positive-time kappa normalization, compact Gaussian block, and exact residual blockers. | Hash reproduced; packet R1-R15 and M1-M12 complete; explicit APPROVE / CLARIFY / AMEND / FAIL / CANNOT VERIFY verdict; exact reduction scope; no dependency or Theorem B promotion.
A17: RV-DQ-053 | B17: MATH | C17: LS-DER-032 TB-G2 uniform six-pin covariance and conditional-moment interface | D17: NEEDS_RECONCILIATION | E17: Resolve current exact target/hash and existing verdicts; then perform a bounded nonauthor technical review | F17: request https://docs.google.com/document/d/1sAkJPHfdkUhq-SeY6mpB2bkqCY54vtWKEnVXM52bNUA/edit | companion https://docs.google.com/document/d/1AUEXzPfbZsdtArlkHNhIUK4hbHqg8ATbb5M99Ex57HU/edit | parent https://docs.google.com/document/d/16dSMQF3nbRcx93feO8vJzdnT8wDQvO-p6zViPtyUazw/edit | G17: OPEN / EXTERNAL-FAMILY ELIGIBLE / EXACT-HASH REVIEW READY | Non-OpenAI reviewer or qualified human may earn object-specific review credit; Anthropic remains its existing single lineage | H17: LEGACY_PREDICATE_RETAINED | I17: 2026-07-26T19:30:00Z | J17: Dispatch Created UTC; not proof of zero intervening review | L17: =IF(I17="","",MAX(0,TODAY()-DATE(VALUE(LEFT(I17,4)),VALUE(MID(I17,6,2)),VALUE(MID(I17,9,2))))) -> 59 | M17: =IF(L17="","UNKNOWN",IF(D17="PASS_TECHNICAL","EXTERNAL ONLY",IF(L17>=30,"ESCALATE",IF(L17>=14,"DECOMPOSE",IF(L17>=7,"PRIORITIZE","NEW"))))) -> ESCALATE | N17: Disclose exact-object authorship; provider alone is insufficient | O17: UNRESOLVED — bind before review | Q17: UNASSIGNED | S17: Execute LS-REQ-028 against LS-DER-032 frozen body 12,106 bytes / SHA-256 3531e6e5c569319388964429d36af8de0ca8768668ac43a53b5a5b2490fd4dba. Reconstruct Fourier symbols, lattice rigidity, uniform eigenfloors, density bounds, regression moments, Q nondegeneracy, and the expectation-limit interface. | Hash reproduced; R0-R12 and M1-M10 completed; explicit scoped verdict, source exposure, and lineage; no automatic LS-DER-021 approval, DQ-023 closure, or Theorem B promotion.
A18: RV-DQ-057 | B18: MATH | C18: LS-DER-036-v1.1 fixed-compact exact Palm O(r^3) loop successor | D18: NEEDS_RECONCILIATION | E18: Resolve current exact target/hash and existing verdicts; then perform a bounded nonauthor technical review | F18: review https://docs.google.com/document/d/19RaCdwEHAVRjOynksS2umRRV7luCBfvAlWlHXVi50oo/edit | successor https://docs.google.com/document/d/1f_bqwcWGp9sS13-v4qHdzNROKx2hzvAlDTTl-skco-Q/edit | predecessor verdict https://docs.google.com/document/d/1zMq504Z2iW4cDr220n8D5sc66kMzwDGGqNMrlwY8f6U/edit | G18: OPEN / NUMBERED SUCCESSOR PUBLISHED / EXACT-HASH REVIEW READY / DQ-023 AND DQ-028 OPEN | An eligible successor reviewer may qualify v1.1 without transferring or multiplying predecessor Anthropic credit | H18: LEGACY_PREDICATE_RETAINED | I18: 2026-07-27T17:52:00Z | J18: Dispatch Created UTC; not proof of zero intervening review | L18: =IF(I18="","",MAX(0,TODAY()-DATE(VALUE(LEFT(I18,4)),VALUE(MID(I18,6,2)),VALUE(MID(I18,9,2))))) -> 58 | M18: =IF(L18="","UNKNOWN",IF(D18="PASS_TECHNICAL","EXTERNAL ONLY",IF(L18>=30,"ESCALATE",IF(L18>=14,"DECOMPOSE",IF(L18>=7,"PRIORITIZE","NEW"))))) -> ESCALATE | N18: Disclose exact-object authorship; provider alone is insufficient | O18: UNRESOLVED — bind before review | Q18: UNASSIGNED | S18: Execute LS-REQ-032: reconstruct fixed-chart Gaussian regression, Dudley/Borell concentration, boundary r-power ledger, outward corridor, one-branch logic, and corrected TB-G3B reduction. | Reproduce 16,856 bytes / SHA-256 3416ddeebacd071f316a1e281aa3df2e99cf1e4965c1eb8bac203d23b6eb05b3; complete R0-R20 and M1-M18; state C1-C4 disposition and dependency firewall.
A19: RV-DQ-061 | B19: MATH | C19: LS-DER-038 corrected compact actual-selection and specific minus-one-third component successor | D19: NEEDS_RECONCILIATION | E19: Resolve current exact target/hash and existing verdicts; then perform a bounded nonauthor technical review | F19: request https://docs.google.com/document/d/1HLgGIYkveWdh7SxzkDaQUJ2xRP3LapmWLQrAeMvtHHw/edit | candidate https://docs.google.com/document/d/1c8eP9TWsgGoLdm393k7QUATzCH16oCThcuB-SH4IriY/edit | predecessor verdict https://docs.google.com/document/d/1LU4Mxm3Gmh2Vhqsdemt7XDjwnHVE1ZCMMKcTu_YNqwU/edit | G19: OPEN / EXTERNAL-FAMILY ELIGIBLE / EXACT-HASH REVIEW READY | A reviewer outside OpenAI may earn exact-object review credit; existing Anthropic synthesis lineage counts once | H19: LEGACY_PREDICATE_RETAINED | I19: 2026-07-28T06:23:35Z | J19: Dispatch Created UTC; not proof of zero intervening review | L19: =IF(I19="","",MAX(0,TODAY()-DATE(VALUE(LEFT(I19,4)),VALUE(MID(I19,6,2)),VALUE(MID(I19,9,2))))) -> 57 | M19: =IF(L19="","UNKNOWN",IF(D19="PASS_TECHNICAL","EXTERNAL ONLY",IF(L19>=30,"ESCALATE",IF(L19>=14,"DECOMPOSE",IF(L19>=7,"PRIORITIZE","NEW"))))) -> ESCALATE | N19: Disclose exact-object authorship; provider alone is insufficient | O19: UNRESOLVED — bind before review | Q19: UNASSIGNED | S19: Execute LS-REQ-033 against LS-DER-038. Verify corrected event algebra, L_same import, compact selection, unit multiplicity, radial Jacobian, specific coefficient, and total factor 576. | Reproduce 10,410 bytes / SHA-256 5fd2413c52eac9538f85dba3ecaad68861c23f31a03e4a8b766c9914e518b7e5; complete R0-R17 and M1-M18; no full-density or theorem promotion.
A20: RV-DQ-096 | B20: MATH | C20: LS-REQ-037 review of LS-DER-064/068 and LS-DER-065/067/069 | D20: NEEDS_RECONCILIATION | E20: Resolve current exact target/hash and existing verdicts; then perform a bounded nonauthor technical review | F20: https://docs.google.com/document/d/1KGpfr5lWfTq7evVi2_inA0qIrA9TPnsu4GlBddRhsWo/edit | G20: READY / UNCLAIMED / EXECUTE AFTER RESET | Packet itself creates zero independence; Anthropic verdict required | H20: LEGACY_PREDICATE_RETAINED | I20: 2026-07-28T20:58:00Z | J20: Dispatch Created UTC; not proof of zero intervening review | L20: =IF(I20="","",MAX(0,TODAY()-DATE(VALUE(LEFT(I20,4)),VALUE(MID(I20,6,2)),VALUE(MID(I20,9,2))))) -> 57 | M20: =IF(L20="","UNKNOWN",IF(D20="PASS_TECHNICAL","EXTERNAL ONLY",IF(L20>=30,"ESCALATE",IF(L20>=14,"DECOMPOSE",IF(L20>=7,"PRIORITIZE","NEW"))))) -> ESCALATE | N20: Disclose exact-object authorship; provider alone is insufficient | O20: UNRESOLVED — bind before review | Q20: UNASSIGNED | S20: Attack analytic Hessian/image-tail proof and the full side-24 G1-G7 selected-persistence composition; issue strict terminal verdict. | Frozen packet 7,013 bytes / SHA-256 e5ae1b6d55539a7b5dd4b90e6e38a48b8402437bc7d7af9f5a884f163cf06737.
A21: RV-RN3 | B21: MATH | C21: RN3 joint far-zone fixed r=1/20 | D21: READY | E21: Replay RN3 bundle and audit every uniform bound; RN5 report-level crosswalk explains distinct kappa majorants and scopes the near-moment defect | F21: https://drive.google.com/file/d/1f0EBsq6UIZ0jDCABT251TTNEWYCVA0FO/view | G21: Author replay only; alternative Anthropic far-zone work is not a review | H21: EXTERNAL_REVIEW_OPEN | I21: 2026-09-17T16:25:48.473074Z | J21: New R17 request | L21: =IF(I21="","",MAX(0,TODAY()-DATE(VALUE(LEFT(I21,4)),VALUE(MID(I21,6,2)),VALUE(MID(I21,9,2))))) -> 6 | M21: =IF(L21="","UNKNOWN",IF(D21="PASS_TECHNICAL","EXTERNAL ONLY",IF(L21>=30,"ESCALATE",IF(L21>=14,"DECOMPOSE",IF(L21>=7,"PRIORITIZE","NEW"))))) -> NEW | N21: OpenAI / RN3-20260917-b9c2 | O21: 0c9446b7cb49e6e1e45e43f84bb72ce680f022882e225fdff61c8e6edede1373 | P21: 12956 | Q21: UNASSIGNED | S21: Fixed r, fixed axis, side-24; near annulus and all-small-r remain open. Bundle https://drive.google.com/file/d/1z_zNdgxtbs7XWxLu56HN8_QbVXxdmMMq/view
A22: RV-RN-ALIGN | B22: MATH | C22: CL-RNU-003 and RN3 exact-object crosswalk | D22: AMEND | E22: Correct near-moment claim and complete spatial cover; locate named CL v5 archive / rnu_t4.py / rnu_spine.py before executable crosswalk | F22: https://drive.google.com/file/d/1aCa-QG9CSrNUB9SUFKISifghSf-41fRy/view | G22: Report-level comparison complete; wrong near determinant moment proved. No CL executable replay; RN3 author lineage. | H22: AUTHOR_SIDE / ZERO ORG CREDIT | I22: 2026-09-17T16:25:48.473074Z | J22: New R17 request | K22: 2026-09-17T17:19:16.450Z | L22: =IF(I22="","",MAX(0,TODAY()-DATE(VALUE(LEFT(I22,4)),VALUE(MID(I22,6,2)),VALUE(MID(I22,9,2))))) -> 6 | M22: =IF(L22="","UNKNOWN",IF(D22="PASS_TECHNICAL","EXTERNAL ONLY",IF(L22>=30,"ESCALATE",IF(L22>=14,"DECOMPOSE",IF(L22>=7,"PRIORITIZE","NEW"))))) -> NEW | N22: Anthropic CL-RNU-003; OpenAI RN3 | O22: RN3 0c9446b7cb49e6e1e45e43f84bb72ce680f022882e225fdff61c8e6edede1373; CL 59b8f002f1b1e81e7829416baf16ef1d84b1326d4b3b4604b833e5a55a9d6d53 | Q22: ROUND5 / OpenAI / author-side | R22: https://drive.google.com/file/d/1LtnvNd0vAW-y3pzbyHLjgtF7Uw5sTph5/view | S22: Different kappa majorants are not conflicting heads. CL report Section 3 on scoped hold. CANNOT_VERIFY current CL executable/checkpoint identity: named code/archive not found in bounded source lookups.
A23: RV-P15 | B23: MATH | C23: P15-A/B/C/D structural localization | D23: READY | E23: Bind archive and exact proof paths, then execute R1–R8 packet; split into four scoped reviews | F23: https://drive.google.com/file/d/1mLizXdV8guLCJoJGa7iyvjDc3C1XElxr/view | G23: Author-side complete; external reviews 0 in current state | H23: EXTERNAL_REVIEW_OPEN | I23: 2026-09-17T16:25:48.473074Z | J23: New R17 request | L23: =IF(I23="","",MAX(0,TODAY()-DATE(VALUE(LEFT(I23,4)),VALUE(MID(I23,6,2)),VALUE(MID(I23,9,2))))) -> 6 | M23: =IF(L23="","UNKNOWN",IF(D23="PASS_TECHNICAL","EXTERNAL ONLY",IF(L23>=30,"ESCALATE",IF(L23>=14,"DECOMPOSE",IF(L23>=7,"PRIORITIZE","NEW"))))) -> NEW | N23: Author lineage to be read from exact archive | O23: UNRESOLVED — archive manifest required | Q23: UNASSIGNED | S23: No unrestricted prize closure; current state https://drive.google.com/file/d/1r8weyHObFfHAp-_PfI8mlSXPZQC8Zoh1/view
A24: RV-H5-REPAIR | B24: COMPUTE | C24: H5 corrected-kernel full consumer replay | D24: AMEND | E24: Replay all affected upper/lower certificate consumers against the repaired kernel before certification | F24: https://drive.google.com/file/d/1qtuFKUR0SsX3aeB_uI08b2sJw0DX2EOL/view | G24: Defect and one-box repair replay documented; full cover remains open | H24: REVIEW_AFTER_FULL_REPLAY | I24: 2026-09-17T16:25:48.473074Z | J24: New R17 consolidated request | L24: =IF(I24="","",MAX(0,TODAY()-DATE(VALUE(LEFT(I24,4)),VALUE(MID(I24,6,2)),VALUE(MID(I24,9,2))))) -> 6 | M24: =IF(L24="","UNKNOWN",IF(D24="PASS_TECHNICAL","EXTERNAL ONLY",IF(L24>=30,"ESCALATE",IF(L24>=14,"DECOMPOSE",IF(L24>=7,"PRIORITIZE","NEW"))))) -> NEW | N24: Multiple legacy authors; repaired candidate OpenAI | O24: See Quarantine Index: 11 archive-member hashes | Q24: UNASSIGNED | S24: No H5 certificate chain may consume signed odd-frequency or missing denominator-tail bounds without replay.
A25: RV-OPS-R17 | B25: OPS | C25: OP-PROT-019-v1.1 implementation | D25: READY | E25: Challenge stale handoff, same-family coauthor, publication-race and restoration cases using bundled tests | F25: https://drive.google.com/file/d/1hBph5Fpxd5dVrolNkvzU8nb7xpxUiUdc/view | G25: Author-side implementation; not independently reviewed | H25: EXTERNAL_REVIEW_OPEN | I25: 2026-09-17T16:25:48.473074Z | J25: New R17 request | L25: =IF(I25="","",MAX(0,TODAY()-DATE(VALUE(LEFT(I25,4)),VALUE(MID(I25,6,2)),VALUE(MID(I25,9,2))))) -> 6 | M25: =IF(L25="","UNKNOWN",IF(D25="PASS_TECHNICAL","EXTERNAL ONLY",IF(L25>=30,"ESCALATE",IF(L25>=14,"DECOMPOSE",IF(L25>=7,"PRIORITIZE","NEW"))))) -> NEW | N25: OpenAI / OPS4-20260917-b9c2 | O25: 04987ba47b58be623a3b2a5a8a21236f43d4393cc04009e87f4a62b59a787390 | P25: 14073 | Q25: UNASSIGNED | S25: Cooperative conflict detection, not deployed transactional locking.
A26: RV-RN5-MOMENT-REPAIR | B26: MATH / COMPUTE | C26: RN5 corrected moment and local spatial-box candidate | D26: READY | E26: Execute R1–R10 in bundle; reconstruct Holder, L2 Taylor remainders and marginal whitening; then extend complete near cover | F26: https://drive.google.com/file/d/1LtnvNd0vAW-y3pzbyHLjgtF7Uw5sTph5/view | G26: OpenAI author-side proof/replay; 66 checks; no independent review yet | H26: EXTERNAL_REVIEW_OPEN | I26: 2026-09-17T17:19:16.450Z | J26: New exact RN5 candidate; parent near-annulus remains unresolved | L26: =IF(I26="","",MAX(0,TODAY()-DATE(VALUE(LEFT(I26,4)),VALUE(MID(I26,6,2)),VALUE(MID(I26,9,2))))) -> 6 | M26: =IF(L26="","UNKNOWN",IF(D26="PASS_TECHNICAL","EXTERNAL ONLY",IF(L26>=30,"ESCALATE",IF(L26>=14,"DECOMPOSE",IF(L26>=7,"PRIORITIZE","NEW"))))) -> NEW | N26: OpenAI / ROUND5-20260917-b9c2 | O26: ac89f60b8206bfe011e6c2bc653e7acb39bc83a55c2a2c8fd1e17fd70c6c0383 | P26: 13725 | Q26: UNASSIGNED | S26: 65 exact spatial points with complete mark caps; 10 spatial boxes. No annulus cover, no all-small-r extension, no external acceptance. Bundle https://drive.google.com/file/d/1g5UP_KYlvPmx7LFwjGk6qK5QZLnL1hLj/view
A27: RV-HG-ENVELOPE-20260919-v1 | B27: MATH / COMPUTE | C27: HG-GLOBAL-ENVELOPE-20260919-v1 | D27: READY | E27: Review Hermite normalization and derivative identity; even/odd monomial bounds and two-axis product; interval containment and infinite-shell tail; replay 66 exact cases and negative controls; confirm scope and review flags. | F27: https://drive.google.com/file/d/1pWBlanUuRBPVSrrbSd4XDUxIcX0gU8va/view?usp=drivesdk | G27: OpenAI author proof/checks only; no nonauthor technical review | H27: REVIEW OPEN / 0 INDEPENDENCE CREDIT | I27: 2026-09-20T00:24:04.500427+00:00 | J27: New request for this exact 3641-byte author candidate; no prior review age reset. | L27: =IF(I27="","",MAX(0,TODAY()-DATE(VALUE(LEFT(I27,4)),VALUE(MID(I27,6,2)),VALUE(MID(I27,9,2))))) -> 3 | M27: =IF(L27="","UNKNOWN",IF(D27="PASS_TECHNICAL","EXTERNAL ONLY",IF(L27>=30,"ESCALATE",IF(L27>=14,"DECOMPOSE",IF(L27>=7,"PRIORITIZE","NEW"))))) -> NEW | N27: OpenAI / Codex / task 01a0bbb5-2fcb-77f0-b78b-4d220ddd7ab2 | O27: 8c0dccdfd177b7ae03a0edd62f92b330825469a9e991d33d2226eb62cfd6083e | P27: 3641 | Q27: UNASSIGNED | S27: Bundle https://drive.google.com/file/d/1WqIeKAosnVrdco7DNemuEgUKRrLVCd9D/view?usp=drivesdk; Git 508ae7e20301df57da0045b13bc7ed9eb0b67ead. Plane derivative envelope and conditional axial-box tails only; no full 24-jet,six-pin,band certificate or obligation closure.
A28: RV-RN-AFFINE-MOMENTS-20260920-v1 | B28: MATH / COMPUTE | C28: RN-AFFINE-MOMENTS-20260920-v1 | D28: READY | E28: Reconstruct correlated affine Gaussian recurrence, noncentral trace formula, PSD singular cases and Bernstein full-interval enclosure; check RN5 coordinate order/common conditioning; replay negative controls and disclosed evaluation overlap. No field or status inference. | F28: https://drive.google.com/file/d/1RXhWblyRQYpadj6X7e3IZTmNO4JXXgo3/view | G28: Author verification plus exposed same-provider context review; modulo35 evaluation alias found and corrected. No independent approval. | H28: REVIEW OPEN / 0 INDEPENDENCE CREDIT | I28: 2026-09-20T01:39:25.155338+00:00 | J28: New exact7394-byte candidate request; previous Hermite request unchanged. | L28: =IF(I28="","",MAX(0,TODAY()-DATE(VALUE(LEFT(I28,4)),VALUE(MID(I28,6,2)),VALUE(MID(I28,9,2))))) -> 3 | M28: =IF(L28="","UNKNOWN",IF(D28="PASS_TECHNICAL","EXTERNAL ONLY",IF(L28>=30,"ESCALATE",IF(L28>=14,"DECOMPOSE",IF(L28>=7,"PRIORITIZE","NEW"))))) -> NEW | N28: OpenAI / Codex / task01a0bbb5-2fcb-77f0-b78b-4d220ddd7ab2 | O28: 4c1803f23e5bbb02baf0a5f5dec6bd4c00d5c580fdffce05180619e7d9158520 | P28: 7394 | Q28: UNASSIGNED
A29: RV-RN-INTERVAL-FAMILIES-20260920-v1 | B29: MATH / COMPUTE | C29: RN-INTERVAL-FAMILIES-20260920-v1 | D29: READY | E29: Reconstruct coefficient interval inclusion, all-PSD sufficient test versus PSD-member quantifier, exact singleton recovery and full Bernstein mark subdivisions. Replay independent Gaussian expansion and covariance/midpoint/mixed-law controls. No actual field identification or spatial-cover inference. | F29: https://drive.google.com/file/d/1r5_R5VoKM10-7eofPwGa_yHuxTAS7S2q/view | G29: Author verification plus exposed same-provider bounded source/code review. Frozen review versions and later changes disclosed; no independent approval. | H29: REVIEW OPEN / 0 INDEPENDENCE CREDIT | I29: 2026-09-20T02:39:50.562453+00:00 | J29: New exact8330-byte interval-family candidate request; prior affine moment request unchanged. | L29: =IF(I29="","",MAX(0,TODAY()-DATE(VALUE(LEFT(I29,4)),VALUE(MID(I29,6,2)),VALUE(MID(I29,9,2))))) -> 3 | M29: =IF(L29="","UNKNOWN",IF(D29="PASS_TECHNICAL","EXTERNAL ONLY",IF(L29>=30,"ESCALATE",IF(L29>=14,"DECOMPOSE",IF(L29>=7,"PRIORITIZE","NEW"))))) -> NEW | N29: OpenAI / Codex / task01a0bbb5-2fcb-77f0-b78b-4d220ddd7ab2 | O29: 0b53ae366eae2b603811f4eb02b09fa44abc220be442419a6801c6349d53adff | P29: 8330 | Q29: UNASSIGNED
A30: RV-RESEARCH-EXECUTION-CERTIFICATES-20260920-v1 | B30: MATH / COMPUTE / FORMAL | C30: RESEARCH-EXECUTION-CERTIFICATES-20260920-v1 | D30: READY | E30: Review exact Gaussian recurrence and interval inclusion, PSD quantifiers, complete Bernstein coverage, LPW parent versus conditional law and radius imports. Inspect recovered Lean statements and sole noncomputable repair; verify receipt completeness and mutation controls. Actual field and analytic premises remain separate. | F30: https://drive.google.com/file/d/1NmwwIUUfIgVepvWjjSaPtLisJar7dpJu/view | G30: Author verification and same-provider coauthor probes. RN malformed/correlated controls, LPW original replay and recovered Lean build disclosed. No independent approval. | H30: REVIEW OPEN / 0 INDEPENDENCE CREDIT | I30: 2026-09-20T03:49:26.405969+00:00 | J30: New exact candidate combining executable scoped results; earlier RN review requests remain unchanged. | L30: =IF(I30="","",MAX(0,TODAY()-DATE(VALUE(LEFT(I30,4)),VALUE(MID(I30,6,2)),VALUE(MID(I30,9,2))))) -> 3 | M30: =IF(L30="","UNKNOWN",IF(D30="PASS_TECHNICAL","EXTERNAL ONLY",IF(L30>=30,"ESCALATE",IF(L30>=14,"DECOMPOSE",IF(L30>=7,"PRIORITIZE","NEW"))))) -> NEW | N30: OpenAI / Codex / task 01a0bbb5-2fcb-77f0-b78b-4d220ddd7ab2 | O30: dc84d820053832437577dfc4a5254031fb58eef521b59f36ad10f77c024e7465 | P30: 33105 | Q30: UNASSIGNED | S30: RN actual field/spatial cover, LPW analytic imports, lost GP-FOR-001 recovery and independent statement/scope review remain open.
A31: RV-RN-SIDE24-POINT-LAW-20260920-v1 | B31: MATH / COMPUTE | C31: RN-SIDE24-POINT-LAW-20260920-v1 | D31: READY | E31: Review normalized periodized kernel and complete order0..4 image tails; derivative signs, nine-pin affine law, interval LDL/Schur inclusion and PSD premise; replay M4/S4/y2 witnesses and Holder bound at y=(1,1). Verify all source and scope boundaries. | F31: https://drive.google.com/file/d/1nzc7GJeAR06L03c6y8Kf958VHU4n-mJ_/view | G31: 503 source-exposed nonauthor code checks; 342 Decimal diagnostics; preimplementation source suggestions disclosed. Code-check PASS only, organizational independence0. | H31: SCIENTIFIC REVIEW OPEN / 0 INDEPENDENCE CREDIT | I31: 2026-09-20T04:29:09.031711+00:00 | J31: New exact point-law candidate; earlier RN routes unchanged. | L31: =IF(I31="","",MAX(0,TODAY()-DATE(VALUE(LEFT(I31,4)),VALUE(MID(I31,6,2)),VALUE(MID(I31,9,2))))) -> 3 | M31: =IF(L31="","UNKNOWN",IF(D31="PASS_TECHNICAL","EXTERNAL ONLY",IF(L31>=30,"ESCALATE",IF(L31>=14,"DECOMPOSE",IF(L31>=7,"PRIORITIZE","NEW"))))) -> NEW | N31: OpenAI / Codex / task 01a0bbb5-2fcb-77f0-b78b-4d220ddd7ab2 | O31: d953aa0ee6aa08ee178ad21a4c01caeb307ede5d97b14b3b1b282e4d214f5753 | P31: 20773 | Q31: UNASSIGNED | S31: No density/window factor, H3 normalizer, spatial cover, remote budget, all-small-r theorem or canonical promotion. Private GitHub publication; scientific review remains open.
A32: RV-RN-SIDE24-DENSITY-WINDOW-20260920-v1 | B32: MATH / COMPUTE | C32: RN-SIDE24-DENSITY-WINDOW-20260920-v1 | D32: READY | E32: Review six-pin conditional jet, gradient LDL density, gradient-zero height mean/variance and full-window nearest-distance cap; compose whole-mark M4/S4/y2 bound with imported H3 floor in original Hessian units. Verify source basis, exact scope and numerical negative controls. | F32: https://drive.google.com/file/d/1BP6EjmOeezUlH3aLID4N2Qc-wun5RR8C/view | G32: 37 source-exposed nonauthor audit checks; 7 report mutations rejected; 17 Decimal quantities and five joint-density comparisons. Prior suggestions disclosed; zero organizational independence. | H32: SCIENTIFIC REVIEW OPEN / 0 INDEPENDENCE CREDIT | I32: 2026-09-20T05:00:48.931972+00:00 | J32: New exact density/window candidate; earlier RN routes unchanged. | L32: =IF(I32="","",MAX(0,TODAY()-DATE(VALUE(LEFT(I32,4)),VALUE(MID(I32,6,2)),VALUE(MID(I32,9,2))))) -> 3 | M32: =IF(L32="","UNKNOWN",IF(D32="PASS_TECHNICAL","EXTERNAL ONLY",IF(L32>=30,"ESCALATE",IF(L32>=14,"DECOMPOSE",IF(L32>=7,"PRIORITIZE","NEW"))))) -> NEW | N32: OpenAI / Codex / task 01a0bbb5-2fcb-77f0-b78b-4d220ddd7ab2 | O32: c53bf5989aceb258f28aeabb4ff8f4359a968094916929e06552185be2146310 | P32: 15286 | Q32: UNASSIGNED | S32: H3 imported hypothesis not reproved; no spatial integral/cover, remote-budget closure, all-small-r theorem or canonical promotion. Private draft publication; recurring hourly execution does not alter scientific gates.
A33: RV-RN-SPATIAL-PARALLEL-MATH-20260920-v1 | B33: MATH / COMPUTE | C33: RN-SPATIAL-PARALLEL-MATH-20260920-v1 | D33: READY | E33: Review Gaussian L2 mean/covariance spatial transport, six-pin then gradient/mark conditioning, 4/4/2 witnesses, complete four-cell area sum; fixed-r H3 safe-box quartic and r² scale; LPW full spectral tails/quadratic profiles; c2 cancellation-preserving band. Check scope separation and strict typed candidate replay. | F33: https://drive.google.com/file/d/13a9tebHQ7URIEE9qtAO499Ju6oLznuyG/view | G33: 33 checks, 2406 tests passed, 1 existing skip. Cell review91 tests,6375 Decimal diagnostic inclusions; same-provider, independence0. Parent cross-target H3 review reconstructs saved-law quartic; original artifacts preserved. | H33: SCIENTIFIC REVIEW OPEN / 0 INDEPENDENCE CREDIT | I33: 2026-09-20T06:01:06.985303+00:00 | J33: Four scoped candidates; full near annulus and wider claims unchanged. | L33: =IF(I33="","",MAX(0,TODAY()-DATE(VALUE(LEFT(I33,4)),VALUE(MID(I33,6,2)),VALUE(MID(I33,9,2))))) -> 3 | M33: =IF(L33="","UNKNOWN",IF(D33="PASS_TECHNICAL","EXTERNAL ONLY",IF(L33>=30,"ESCALATE",IF(L33>=14,"DECOMPOSE",IF(L33>=7,"PRIORITIZE","NEW"))))) -> NEW | N33: OpenAI / Codex / task 01a0bbb5-2fcb-77f0-b78b-4d220ddd7ab2 | O33: 4bd14f065f98afca128c50e7ab83d267f146ca771313a489fe9196f06ed8de33 | P33: 21408 | Q33: UNASSIGNED | S33: RN full annulus/remote budget/all-r open. H3 original lower floor re-proved only at fixedr; original upper interval not replayed. LPW endpoint/model premises retained. H5 onejet/candidateband only; zero status promotions. Private proof/bundle.
A34: RV-Q0-TWELVE-MATH-20260920-v1 | B34: MATH / COMPUTE | C34: Q0-TWELVE-MATH-20260920-v1 | D34: READY | E34: Review H3 covariance/typed limit and fixed-r ceiling; LPW conditional regression and elder-pairing scope; unconditional two-jet bands; persistence event interface, contact Jacobians, full-mark tail hypotheses, WP conditioning-first loss, Lambda replacements, Gaussian tube success ball, optimized integer-count and eta identities | F34: https://drive.google.com/file/d/11mOqEy1T7YGgEbW35EhOs5So68I-ZaBR/view | G34: 34 checks, 2460 tests passed, 1 existing skip; twelve exact original-report replays. Same-provider technical review; independence0. Original proofs and source archive are immutable; exact portable replay and corrupt-input controls recorded. | H34: SCIENTIFIC REVIEW OPEN / 0 INDEPENDENCE CREDIT | I34: 2026-09-20T06:49:53.343184+00:00 | J34: Twelve scoped candidates; actual all-angle/weighted-field/continuum interfaces remain open. | L34: =IF(I34="","",MAX(0,TODAY()-DATE(VALUE(LEFT(I34,4)),VALUE(MID(I34,6,2)),VALUE(MID(I34,9,2))))) -> 3 | M34: =IF(L34="","UNKNOWN",IF(D34="PASS_TECHNICAL","EXTERNAL ONLY",IF(L34>=30,"ESCALATE",IF(L34>=14,"DECOMPOSE",IF(L34>=7,"PRIORITIZE","NEW"))))) -> NEW | N34: OpenAI / Codex / task 01a0bbb5-2fcb-77f0-b78b-4d220ddd7ab2 | O34: 3cdb13fa4b8f6502b5e97b8f4cac5c212bb259a11b4bf2d4896f0db8b42a4436 | P34: 17480 | Q34: UNASSIGNED | S34: No canonical promotion. LPW event firewall preserved; H3 lower radius existential, ceiling fixed-r. Synthetic tail/WP/Lambda/tube constants not actual field certificates. Private proof/bundle.
A35: RV-H3-RN-N6-20260920-v1 | B35: MATH / COMPUTE | C35: H3-RN-N6-20260920-v1 | D35: READY | E35: Review whole-band fixed-axis H3 lower1.7/upper3.49, cancellation-free pin energy<8, degree-six RN transport/remainders/unwhitening, full-mark local caps and stronger fixed-r floor preservation | F35: https://drive.google.com/file/d/15tpKrM1RnYa_2QxKBL-vZt3Zb06pTXUw/view | G35: 35 checks, 2522 tests passed, 1 existing skip; ten exact executions and34 original-output comparisons. Same-provider technical review; independence0. Original proofs and source archive are immutable; exact portable replay and corrupt-input controls recorded. | H35: SCIENTIFIC REVIEW OPEN / 0 INDEPENDENCE CREDIT | I35: 2026-09-20T07:51:58.926860+00:00 | J35: Fixed-axis H3 continuum candidate theorem; RN local square bounds only. Fullannulus and allangle remain open. | L35: =IF(I35="","",MAX(0,TODAY()-DATE(VALUE(LEFT(I35,4)),VALUE(MID(I35,6,2)),VALUE(MID(I35,9,2))))) -> 3 | M35: =IF(L35="","UNKNOWN",IF(D35="PASS_TECHNICAL","EXTERNAL ONLY",IF(L35>=30,"ESCALATE",IF(L35>=14,"DECOMPOSE",IF(L35>=7,"PRIORITIZE","NEW"))))) -> NEW | N35: OpenAI / Codex / task 01a0bbb5-2fcb-77f0-b78b-4d220ddd7ab2 | O35: ff642dd0d3cf53293f040f96a3b9d802d9e71e306aeee806405edc3c3f93cba6 | P35: 9233 | Q35: UNASSIGNED | S35: No canonical promotion. Twenty whole-radius interval cells; not point sampling. RN squares overlap and cross annulus boundary; no complete-cover sum. Cached intermediate custody is not fresh; final route rechecks source status. Private proof/bundle.
A36: RV-WITHDRAWAL-20260921-01 | B36: OPS / SUPPORT-WITHDRAWAL PILOT | C36: OP-WITHDRAWAL-20260921-v1.0; Git commit 1dfa341f99800db6d1cc7568387b3b4d44f0f1ec; 10-file payload manifest | D36: READY | E36: Reproduce exact code/tests; challenge AND/OR support, premise retention, typed identity, impact/survivor coverage, publication limits and unknown-version rejection. Review one bounded live-slice mapping before any migration. Prior Technical status preserved verbatim: OPEN / NONAUTHOR TECHNICAL REVIEW REQUIRED. Vocabulary repair only (R17 section4); READY means awaiting the required review, not a PASS or scientific acceptance. Coordination: PR21 comment5802748321. | F36: https://github.com/d6g8k5htny-coder/main/pull/4 | https://drive.google.com/drive/folders/1VfuXdkyIi0VIsmz42WS6ALEhlc2qneM_ | manifest 1nVFXIhpJEslWsVwayvsg2DwVvp6dieyR | G36: Author-side only: 36 normal tests + 36 optimized tests; 11/11 Drive exact-byte readbacks; fresh Drive-code replay 36/36. Proposal and tests exposed to author; no nonauthor verdict. | H36: UNASSESSED; author-side credit ZERO; disclose prior exposure and provider lineage under R17 | I36: 2026-09-21T17:05:02Z | J36: Current owner-authorized implementation; first review request | L36: {=MAX(0,INT(NOW()-DATEVALUE(LEFT(INDIRECT("I"&ROW()),10))))} -> 2 | M36: New scoped review; existing R17 aging rules apply; no automatic approval | N36: CHATGPT-WITHDRAWAL-20260921-2b090452 / OpenAI | O36: 3d9f058abeff5848ea9febafb233e16daf0079d83425438e5a5074463a10df17 | P36: 2553 | Q36: UNASSIGNED / claim through Work Events | R36: NONE | S36: Operational pilot only. No scientific records migrated; no final refutation/restoration adapter; no review-authenticity checker; no automated cross-system writer; no required branch-check setting. Existing source and scientific gates preserved.
A37: RV-ROLLOUT-R2-20260921-01 | B37: OPS / ROLLOUT SHADOW CONTROLS | C37: R2 exact commit 63eb5baadd7526a7842c43f2d391aad55b01cac9; nine-file manifest 1zBhkuDpB9_QLkiAssHzJxbZ3TpOvHLnm | D37: READY | E37: Replay 46 new tests plus 36 retained withdrawal tests; challenge precedence/uptake separation, qualified binding classes, clean-merge semantic counterexample, cohort completeness and maintenance-vs-behavior classification. Separately observe a future daily pickup after routing repair. Prior Technical status preserved verbatim: OPEN / NONAUTHOR TECHNICAL REVIEW REQUIRED. Vocabulary repair only (R17 section4); READY means awaiting the required review, not a PASS or scientific acceptance. Coordination: PR21 comment5802748321. | F37: https://github.com/d6g8k5htny-coder/main/pull/4 | https://drive.google.com/drive/folders/1tHfFIOu__-26TyWS2U1iIz595q2pEVYP | G37: Author-side tests only: 82 normal and82 optimized pass, no skips locally. Original RV-WITHDRAWAL-20260921-01 exact target retained; R2 is a distinct successor review. Runtime adoption not established. | H37: ZERO AUTHOR-SIDE CREDIT / NONAUTHOR REVIEW UNASSIGNED | I37: 2026-09-21T22:18:54Z | J37: Current R2 delivery request; actual runtime UTC | L37: DERIVE_FROM_REQUEST_UTC | M37: Apply R17 aging to request timestamp; this row has no cached age formula | N37: ROLLOUT-R2-20260921-e4ea82e2 / OpenAI | O37: c462ecbae4c4a22bf193d16691e685dd4f0792060b06b3674fbdb890413c724d | P37: 2268 | Q37: UNASSIGNED | R37: NONE | S37: Read-only plan validation, not authorization or science. No global migration, new scheduler, merge, settings, frozen-source or scientific-status changes. Full repository suite not run locally.
A38: RV-H3-SOLVER-20260921-01 | B38: MATH / H3 SEARCH-AND-CERTIFY PILOT | C38: Whole-band fixed-axis candidate Z(r)>=(1747/1000)r^2; exact commit2371f660d90963e558a0d08921c634a36b3be016; proof1GNxSkObZLXbrR_UWUC6i9PW59pLNrLKB; certificate1yGE1AZGPChZJ9nBn1BGe-opLWj9dw2KW | D38: READY | E38: Verify generalized epsilon=103/500,d=9/100 event argument; normalized image tails, shifted Gram transport, two-sided tail bounds, independence and positive-bracket inequality. Cold-recompute exact certificate; challenge 57 controls and cache boundaries. Do not substitute the new band floor for stronger fixed-r RN floor. Prior Technical status preserved verbatim: OPEN / NONAUTHOR MATHEMATICAL AND SOFTWARE REVIEW REQUIRED. Vocabulary repair only (R17 section4); READY means awaiting the required review, not a PASS or scientific acceptance. Coordination: PR21 comment5802748321. | F38: https://github.com/d6g8k5htny-coder/main/pull/5 | https://drive.google.com/drive/folders/1WsgETGCUiLRj37ku0V-1bJBoTMo29dED | manifest14GAoMD42hdUQmoYb1yOG2l6iOKErPddn | G38: Source-exposed author-side alternate-method rational arithmetic.57 normal,57 optimized,57 raw-Drive replay tests PASS; no skips.27 mpmath point diagnostics PASS, noncertifying. Original full wrapper not replayed; Arb not executed. Search30351 pairs is proposal generation, not proof. | H38: ZERO AUTHOR-SIDE ORGANIZATIONAL-INDEPENDENCE CREDIT | I38: 2026-09-21T23:09:41.688406+00:00 | J38: Current exact-candidate publication; no prior independent review of this successor | L38: DERIVE_FROM_REQUEST_UTC | M38: R17 review aging only; never automatic acceptance | N38: CHATGPT-SOLVER-H3-20260921 / OpenAI | O38: 0d5fc5ece05df2f5717e0c8fc61c041b8663997933e8ec92c58c8cdf4b4f192d | P38: 8469 | Q38: UNASSIGNED | R38: NONE | S38: Exact 2D normalized SIDE24 fixed x-axis; b=6/5,gap=r^3/6; canonical six-pin law;0<r<=1/20. Scalar formula enclosure[1.747106129274,1.747994749902] is NOT Z/r² enclosure. No all-angle/full-RN/q0/prize closure or scientific status migration. Certificate canonicalSHA dfc9c25f1ebdd6545b56bf1ecc3606cd3b950a8f2b5e779bcfe11b88f94c7dea.
A39: RV-RN-INNER-WEDGE-20260920-v1 | B39: MATH / COMPUTE | C39: RN-INNER-WEDGE-20260920-v1 | D39: READY | E39: Review Gaussian energy/variance coupling, sixth-moment Bernstein controls, shared determinant polynomial and every L2 remainder term, full-height Q, twelve-strip containment and one polar area | F39: https://drive.google.com/file/d/1UCK6Lz30SmeiBXKgzk6J3y6YS05TtbFE/view | G39: 40 required commands; 2832 executed tests passed, 2 skips; exact logs/JUnit retained. Technical review is source-exposed and same-provider; independence0. Original imported H3 floor is retained, not reproved. | H39: SCIENTIFIC REVIEW OPEN / 0 INDEPENDENCE CREDIT | I39: 2026-09-21T23:29:14.427452+00:00 | J39: Fixed r=1/20, b=6/5, original x-axis six pins; full height window [57599/48000,6/5]; rho in [1/10,11/100], signed turns [-1/1024,1/1024]. Imported original H3 floor Z>=0.0077592917375327855 retained. Integrand <1/100000, area21*pi/5120000, integral <33/256000000000. Full annulus, all-radii, all-pin-angle, weighted-Palm/event identification and independent acceptance remain open; no scientific promotion. | L39: =IF(I39="","",MAX(0,TODAY()-DATE(VALUE(LEFT(I39,4)),VALUE(MID(I39,6,2)),VALUE(MID(I39,9,2))))) -> 2 | M39: =IF(L39="","UNKNOWN",IF(D39="PASS_TECHNICAL","EXTERNAL ONLY",IF(L39>=30,"ESCALATE",IF(L39>=14,"DECOMPOSE",IF(L39>=7,"PRIORITIZE","NEW"))))) -> NEW | N39: OpenAI / Codex / task 01a0bbb5-2fcb-77f0-b78b-4d220ddd7ab2 | O39: f363629f77c8fec80838b15fee4df9972ee3397252f484c5a1602a7c21ed3e57 | P39: 3251 | Q39: UNASSIGNED | S39: No canonical promotion. Twelve auxiliary strips bound one contained wedge; its area is integrated once. Earlier four N6 pilot squares are not added. Public GitHub candidate; Drive proof and bundle owner-only. Scientific acceptance remains open.
A40: RV-RN-BERNSTEIN-SHARP-WEDGE-20260921-v1 | B40: MATH / COMPUTE | C40: RN-BERNSTEIN-SHARP-WEDGE-20260921-v1 | D40: READY | E40: Review shared Bernstein polynomial, all error corrections, full-height Q, sharp normalized variance and same-wedge integral. | F40: https://github.com/d6g8k5htny-coder/main/blob/d107ab121d230de33c09e727c7804098ec4e8249/research/campaigns/rn_bernstein_sharp_variance_20260921_v1.zip | G40: 41 complete required commands; 2890 executed tests, 2 skips; zero failures/errors; actual logs/JUnit bound. | H40: SCIENTIFIC REVIEW OPEN / 0 INDEPENDENCE CREDIT | I40: 2026-09-22T01:00:03.202230+00:00 | J40: Normalized SIDE24; r=1/20, b=6/5, original x-axis six pins; full height window [57599/48000,6/5]. SAME wedge rho in [1/10,11/100], signed turns [-1/1024,1/1024]; area21*pi/5120000. One Bernstein rectangle, D>8/10^25, Q>=103; (m4+m2^2)^3<64.000001; integrand<1/1000000 and integral<33/2560000000000. Imported fixed-radius H3 floor0.0077592917375327855 retained. Expanded sector excluded. Full annulus, all radii, all pin orientations, weighted-Palm/event identification, canonical scientific acceptance and required independent review remain open. Elder pairing is not selected gradient-branch adjacency. No scientific promotion; organizational independence0; no original prize closure. | L40: =IF(I40="","",MAX(0,TODAY()-DATE(VALUE(LEFT(I40,4)),VALUE(MID(I40,6,2)),VALUE(MID(I40,9,2))))) -> 1 | M40: =IF(L40="","UNKNOWN",IF(D40="PASS_TECHNICAL","EXTERNAL ONLY",IF(L40>=30,"ESCALATE",IF(L40>=14,"DECOMPOSE",IF(L40>=7,"PRIORITIZE","NEW"))))) -> NEW | N40: OpenAI / Codex / task 01a0bbb5-2fcb-77f0-b78b-4d220ddd7ab2 | O40: 868682c92d41015fe9a41714aeef243d9a8ff4713bba29d613ca13529e797ce9 | P40: 157355 | Q40: UNASSIGNED | S40: Exact frozen48-member mathematical packet; combined custody https://drive.google.com/file/d/1_WOmF7PwidcB304vYl0nhKqB1FkcipKY/view. Public GitHub draft candidates; owner-only Drive note/bundle. Technical review is source-exposed; independence0.
A41: RV-H3-SOURCE-ADMISSION-CHANGESET-20260921-v1 | B41: SOURCE ADMISSION / COMPUTE | C41: H3-SOURCE-ADMISSION-CHANGESET-20260921-v1 | D41: READY | E41: Review exact source-admission and inherited typed-topology fixture changeset: lineage, current denials, cold/cache ordering, drift and truthful one-body scope; scalar proof unchanged. Complete certificate and original author evidence bundle preserved for public review; historical runner is not current execution authority. | F41: https://github.com/d6g8k5htny-coder/main/commit/fb6fee88c2bcac65f284f72b6eb8998cf6635b63 | G41: 37 complete required commands; 2800 executed tests, 1 skips; zero failures/errors; actual logs/JUnit bound. | H41: TECHNICAL REVIEW OPEN / 0 INDEPENDENCE CREDIT | I41: 2026-09-22T01:00:03.202230+00:00 | J41: Source-admission/cache boundary repair only; exact1747/1000 fixed-axis whole-band scalar certificate preserved. Authored ancestor/nested archive and current local eligibility checked before proof-body reads/cache output; inherited typed-topology test fixtures repaired. Offline custody is not live permission or scientific acceptance. Complete certificate and original author evidence bundle preserved for public review; the historical runner is not current execution authority. No new mathematical inequality. Full annulus, all radii, all pin orientations, weighted-Palm/event identification, canonical scientific acceptance and required independent review remain open. Elder pairing is not selected gradient-branch adjacency. No scientific promotion; organizational independence0; no original prize closure. | L41: =IF(I41="","",MAX(0,TODAY()-DATE(VALUE(LEFT(I41,4)),VALUE(MID(I41,6,2)),VALUE(MID(I41,9,2))))) -> 1 | M41: =IF(L41="","UNKNOWN",IF(D41="PASS_TECHNICAL","EXTERNAL ONLY",IF(L41>=30,"ESCALATE",IF(L41>=14,"DECOMPOSE",IF(L41>=7,"PRIORITIZE","NEW"))))) -> NEW | N41: OpenAI / Codex / task 01a0bbb5-2fcb-77f0-b78b-4d220ddd7ab2 | O41: 7111c34e74734a7d4f3cc1bdf0958afb65237525e4bf5ec4ea15853a5a386e14 | P41: 1584 | Q41: UNASSIGNED | S41: Canonical sorted compact UTF-8 JSON map of the exact reviewed file identities, no newline; combined custody https://drive.google.com/file/d/1_WOmF7PwidcB304vYl0nhKqB1FkcipKY/view. Public GitHub draft candidates; owner-only Drive note/bundle. Technical review is source-exposed; independence0.

Sheet File Catalog
A1: Drive ID | B1: Title | C1: Domain / observed branch | D1: Routing status | E1: Observed path / destination | F1: Direct link | G1: Modified UTC (observed) | H1: Coverage note
A2: 1HK9hoO4vD2lhE3wDXLPxPXhNBbJZJnNdA01Oh1FDeqA | B2: HISTORICAL OP-PROT-011 — INDEPENDENCE GUIDANCE; TECHNICAL REVIEW NOW R17 | C2: AXIOM | D2: HISTORY | E2: AXIOM/00.1_GOVERNANCE_CANON | F2: https://drive.google.com/file/d/1HK9hoO4vD2lhE3wDXLPxPXhNBbJZJnNdA01Oh1FDeqA/view | G2: 2026-07-25T15:25:22.118Z | H2: Metadata inventoried; proof review only where explicitly recorded in the closure report; baseline active-tree inventory + bounded R17 updates; refresh target metadata before mutation
A3: 1dpinxQLBp3J8-Wu7TrvMiPn_9vmhVFEUKzIp3HQsQyc | B3: GP-COR-184-v1.0 — Current No-Vote Directive Supersedes Concurrent OP-PROT-010 Governance Race | C3: AXIOM | D3: METADATA_ONLY | E3: AXIOM/00.1_GOVERNANCE_CANON | F3: https://drive.google.com/file/d/1dpinxQLBp3J8-Wu7TrvMiPn_9vmhVFEUKzIp3HQsQyc/view | G3: 2026-07-24T18:24:46.024Z | H3: Metadata inventoried; proof review only where explicitly recorded in the closure report; baseline active-tree inventory + bounded R17 updates; refresh target metadata before mutation
A4: 1FwkOa06pccL_RmK63oI0oXBgGtFFRcN-MY63arzEeAA | B4: OP-CNS-001-R0.2 — Integrated Operational Architecture: Preservation, IDs, Automation, Closure, and Master Manifest | C4: AXIOM | D4: METADATA_ONLY | E4: AXIOM/00.1_GOVERNANCE_CANON | F4: https://drive.google.com/file/d/1FwkOa06pccL_RmK63oI0oXBgGtFFRcN-MY63arzEeAA/view | G4: 2026-07-24T18:26:29.548Z | H4: Metadata inventoried; proof review only where explicitly recorded in the closure report; baseline active-tree inventory + bounded R17 updates; refresh target metadata before mutation
A5: 12IlGMxNSCV9YTO7hPITHRGLqOYvpy6Cy1Xyf9840fRk | B5: OP-GDN-003 — Context-Window Freshness and Session Retirement Guidance | C5: AXIOM | D5: METADATA_ONLY | E5: AXIOM/00.1_GOVERNANCE_CANON | F5: https://drive.google.com/file/d/12IlGMxNSCV9YTO7hPITHRGLqOYvpy6Cy1Xyf9840fRk/view | G5: 2026-07-24T18:26:02.213Z | H5: Metadata inventoried; proof review only where explicitly recorded in the closure report; baseline active-tree inventory + bounded R17 updates; refresh target metadata before mutation
A6: 1xh4LRn1q7UuW-qcky9S3PDhKKVXCExasTFM3NsuKDwU | B6: OP-PROT-008-R0.1 — Safety-Hardened Graduated Autonomy Practice Framework — No-Vote Revision | C6: AXIOM | D6: METADATA_ONLY | E6: AXIOM/00.1_GOVERNANCE_CANON | F6: https://drive.google.com/file/d/1xh4LRn1q7UuW-qcky9S3PDhKKVXCExasTFM3NsuKDwU/view | G6: 2026-07-24T18:25:42.382Z | H6: Metadata inventoried; proof review only where explicitly recorded in the closure report; baseline active-tree inventory + bounded R17 updates; refresh target metadata before mutation
A7: 1FF1u9WarpRd1RxG2XKS0qbYzHI2FocrPZ0vkG-KgAqM | B7: OP-RES-001 — Records-Integrity Decisions: CM Aliases, TRC Successor, and GP-DATA-114 Disposition | C7: AXIOM | D7: METADATA_ONLY | E7: AXIOM/00.1_GOVERNANCE_CANON | F7: https://drive.google.com/file/d/1FF1u9WarpRd1RxG2XKS0qbYzHI2FocrPZ0vkG-KgAqM/view | G7: 2026-07-24T19:13:48.000Z | H7: Metadata inventoried; proof review only where explicitly recorded in the closure report; baseline active-tree inventory + bounded R17 updates; refresh target metadata before mutation
A8: 19vdTHxH0ZvRtT20R5U9DPeWLdHtH-vnJ | B8: GATE_FRAMEWORK_MASTER — CURRENT-v1.2-RECONCILED — 30769B — SHAea3b0bce — ID19vdTHxH.md | C8: AXIOM | D8: METADATA_ONLY | E8: AXIOM/00.1_GOVERNANCE_CANON/00_CURRENT_RECONCILED_SPECIFICATION | F8: https://drive.google.com/file/d/19vdTHxH0ZvRtT20R5U9DPeWLdHtH-vnJ/view | G8: 2026-07-22T20:37:39.762Z | H8: Metadata inventoried; proof review only where explicitly recorded in the closure report; baseline active-tree inventory + bounded R17 updates; refresh target metadata before mutation
A9: 1GShZef2a3ZQP7YwQiQUSuhYdvgNnES_- | B9: GATE_FRAMEWORK_MASTER — v1.1-C095-EXECUTABLE-LINEAGE — 27996B — SHA2442dc38 — ID1GShZef2.md | C9: AXIOM | D9: METADATA_ONLY | E9: AXIOM/00.1_GOVERNANCE_CANON/01_PRIOR_DIVERGENT_V1_1_LINEAGES | F9: https://drive.google.com/file/d/1GShZef2a3ZQP7YwQiQUSuhYdvgNnES_-/view | G9: 2026-07-22T20:38:00.049Z | H9: Metadata inventoried; proof review only where explicitly recorded in the closure report; baseline active-tree inventory + bounded R17 updates; refresh target metadata before mutation
A10: 1rVk5ShpplkZApTLMqP73WKDhDmX-d_sB | B10: GATE_FRAMEWORK_MASTER — v1.1-UPLOADED-STANDALONE-LINEAGE — 62173B — SHAa16c44d5 — ID1rVk5Shp.md | C10: AXIOM | D10: METADATA_ONLY | E10: AXIOM/00.1_GOVERNANCE_CANON/01_PRIOR_DIVERGENT_V1_1_LINEAGES | F10: https://drive.google.com/file/d/1rVk5ShpplkZApTLMqP73WKDhDmX-d_sB/view | G10: 2026-07-22T20:37:48.989Z | H10: Metadata inventoried; proof review only where explicitly recorded in the closure report; baseline active-tree inventory + bounded R17 updates; refresh target metadata before mutation
A11: 1nBgMT82BOUBAKO_xw-lSPn0-_HRzWNuD | B11: GATE_FRAMEWORK_MASTER — CURRENT-v1.2-RECONCILED-PDF — 92754B — SHAe2a8b7d3 — ID1nBgMT82.pdf | C11: AXIOM | D11: METADATA_ONLY | E11: AXIOM/00.1_GOVERNANCE_CANON/02_PDF_EXPORTS_AND_ORIGIN_DOCUMENTS | F11: https://drive.google.com/file/d/1nBgMT82BOUBAKO_xw-lSPn0-_HRzWNuD/view | G11: 2026-07-22T20:38:14.518Z | H11: Metadata inventoried; proof review only where explicitly recorded in the closure report; baseline active-tree inventory + bounded R17 updates; refresh target metadata before mutation
A12: 1tX2omUL6saHa5omzRi8LialKiRZWHov1 | B12: GATE_FRAMEWORK_MASTER — v1.0-ORIGIN-PDF — 77525B — SHAd933bcf4 — ID1tX2omUL.pdf | C12: AXIOM | D12: METADATA_ONLY | E12: AXIOM/00.1_GOVERNANCE_CANON/02_PDF_EXPORTS_AND_ORIGIN_DOCUMENTS | F12: https://drive.google.com/file/d/1tX2omUL6saHa5omzRi8LialKiRZWHov1/view | G12: 2026-07-22T20:38:31.669Z | H12: Metadata inventoried; proof review only where explicitly recorded in the closure report; baseline active-tree inventory + bounded R17 updates; refresh target metadata before mutation
... A2953: 1kzXocXd6qZH2-pSTwLoODh0F5K6piUml | B2953: RN5_OPERATIONS_EVIDENCE.zip | C2953: RN5 / OPERATIONS | D2953: VERIFIED OPERATIONS EVIDENCE | E2953: 16CQ-3XkwPyhItBH70JJpho-eA5pYWRm9 | F2953: https://drive.google.com/file/d/1kzXocXd6qZH2-pSTwLoODh0F5K6piUml/view | G2953: 2026-09-17T17:24:13.572Z | H2953: 31419 bytes SHA256 f1b7384268546a243e8e5a01144c683ba653f6b510855d43db0d94f463639b43; requests/readback,rollback,Library transfer-failure receipts

Sheet Quarantine Index
A1: Quarantine key | B1: Class | C1: Object / file ID | D1: Relative path or title | E1: Reason / affected scope | F1: Keeper or repair | G1: Original parent | H1: Current destination | I1: SHA-256 / identity | J1: Restoration test | K1: Disposition UTC
A2: Q-R17-DUP-001 | B2: EXACT_DUPLICATE | C2: 1Y_3zFonLsFIAHP5KSkUfsJXqHZXIUAL2 | D2: CL-GROK-CLOSE-001_PORTFOLIO_RECONCILIATION_2026-09-16.md | E2: Fresh raw download equals keeper; surplus RN-folder copy | F2: https://drive.google.com/file/d/1Hc8dJvdh504xKBBHXswU5Ly-_8uYp_Sv/view | G2: 1FmKnSQRpHc6EYCUEIl07FQDECUZsiEqG | H2: 1zm0bScV66jPsfU8MymIsNRRn7CBqJRTG | I2: cbc52f0b27a50624b0d73e592e544acd2ec6230aea91ef4cc743996f9c941363; 4088 bytes | J2: Restore original parent only if a distinct needed role is established; no new review credit | K2: 2026-09-17T16:25:48.473074Z
A3: Q-R17-TEMP-001 | B3: UNVERIFIED | C3: 1LooOZdyTyMMA_-kuCVifR3RNjWepkyfxbsH8ATP1lPQ | D3: TEMP TRANSPORT — evidence_export_identities.v0.4 | E3: Temporary native transport marked for quarantine; not a verified raw carrier | F3: Use current registered exact identity carrier; no keeper equivalence asserted | G3: 1KFs0lDjHQIhK2SN4ky2hAsihQweFuOvD | H3: 14QpTsBRSsWUpmqGAOTSkmamsGGqzUg3X | I3: Native document ID; content preserved | J3: Reproduce required bytes and establish current package role before consumption | K3: 2026-09-17T16:25:48.473074Z
A4: Q-R17-RN-OLD | B4: SUPERSEDED | C4: 1v7JAh_FbXHYMaL7W6DNwEoLnHPwQ5U21 | D4: rnu_ds3_scalar_SUPERSEDED.py | E4: Source portfolio explicitly retires scalar DS3; different content, not duplicate | F4: https://drive.google.com/file/d/14FIaDPHfbTTGQWzxZi8xKAzlKub5Iud8/view | G4: 1FmKnSQRpHc6EYCUEIl07FQDECUZsiEqG | H4: RETAINED_IN_PACKAGE; metadata rename only | I4: 7201-byte legacy source; no content edit | J4: Historical reproduction may use by exact ID; original name recorded in move log | K4: 2026-09-17T16:25:48.473074Z
A5: Q-R17-H5-01 | B5: DEFECTIVE_SCOPE | C5: 1vSI-evINWskhXVyiZ0slt-rLT74sPpXH | D5: K3_SIDE24_LB/UPPER2D/H5_closure/falsify.py | E5: Dependent H5 numerical certification held pending full corrected-kernel replay; this is not a declaration that every mathematical conclusion is false | F5: https://drive.google.com/file/d/1qtuFKUR0SsX3aeB_uI08b2sJw0DX2EOL/view | G5: Archive member; original carrier retained | H5: LOGICAL_QUARANTINE; frozen bytes retained | I5: 5bc9dbccb384fc49366a32c9c19d431a68dea1ccae74233d1fbc458e5bfeee0c; 3262 bytes | J5: Complete corrected consumer replay + exact replacement identities + scoped review | K5: 2026-09-17T16:25:48.473074Z
A6: Q-R17-H5-02 | B6: DEFECTIVE_SCOPE | C6: 1vSI-evINWskhXVyiZ0slt-rLT74sPpXH | D6: K3_SIDE24_LB/UPPER2D/H5_closure/h5_kernel.py | E6: Dependent H5 numerical certification held pending full corrected-kernel replay; this is not a declaration that every mathematical conclusion is false | F6: https://drive.google.com/file/d/1qtuFKUR0SsX3aeB_uI08b2sJw0DX2EOL/view | G6: Archive member; original carrier retained | H6: LOGICAL_QUARANTINE; frozen bytes retained | I6: b2e6014c2fd6eb9e72b2104cc828a764e280f76b8396a02edd37654b6ad83ad7; 66310 bytes | J6: Complete corrected consumer replay + exact replacement identities + scoped review | K6: 2026-09-17T16:25:48.473074Z
A7: Q-R17-H5-03 | B7: DEFECTIVE_SCOPE | C7: 1vSI-evINWskhXVyiZ0slt-rLT74sPpXH | D7: K3_SIDE24_LB/UPPER2D/H5_closure/h5_merge.py | E7: Dependent H5 numerical certification held pending full corrected-kernel replay; this is not a declaration that every mathematical conclusion is false | F7: https://drive.google.com/file/d/1qtuFKUR0SsX3aeB_uI08b2sJw0DX2EOL/view | G7: Archive member; original carrier retained | H7: LOGICAL_QUARANTINE; frozen bytes retained | I7: f14eba68577de55a61760b05ca2daf00c094f500eb729cb9b6a018643d370e0a; 13506 bytes | J7: Complete corrected consumer replay + exact replacement identities + scoped review | K7: 2026-09-17T16:25:48.473074Z
A8: Q-R17-H5-04 | B8: DEFECTIVE_SCOPE | C8: 1vSI-evINWskhXVyiZ0slt-rLT74sPpXH | D8: K3_SIDE24_LB/UPPER2D/H5_closure/h5_promote.py | E8: Dependent H5 numerical certification held pending full corrected-kernel replay; this is not a declaration that every mathematical conclusion is false | F8: https://drive.google.com/file/d/1qtuFKUR0SsX3aeB_uI08b2sJw0DX2EOL/view | G8: Archive member; original carrier retained | H8: LOGICAL_QUARANTINE; frozen bytes retained | I8: b0da452e606983d9072ec7cdcea5aaccd83db21a583758d661f0cfb9999e19e8; 10178 bytes | J8: Complete corrected consumer replay + exact replacement identities + scoped review | K8: 2026-09-17T16:25:48.473074Z
A9: Q-R17-H5-05 | B9: DEFECTIVE_SCOPE | C9: 1vSI-evINWskhXVyiZ0slt-rLT74sPpXH | D9: K3_SIDE24_LB/UPPER2D/H5_closure/h5_run.py | E9: Dependent H5 numerical certification held pending full corrected-kernel replay; this is not a declaration that every mathematical conclusion is false | F9: https://drive.google.com/file/d/1qtuFKUR0SsX3aeB_uI08b2sJw0DX2EOL/view | G9: Archive member; original carrier retained | H9: LOGICAL_QUARANTINE; frozen bytes retained | I9: 19504b978c8793006f03624b18410f9dc79ee3181566f4ec4a0a550711cc7d6c; 26420 bytes | J9: Complete corrected consumer replay + exact replacement identities + scoped review | K9: 2026-09-17T16:25:48.473074Z
A10: Q-R17-H5-06 | B10: DEFECTIVE_SCOPE | C10: 1vSI-evINWskhXVyiZ0slt-rLT74sPpXH | D10: K3_SIDE24_LB/UPPER2D/H5_closure/h5_totals.json | E10: Dependent H5 numerical certification held pending full corrected-kernel replay; this is not a declaration that every mathematical conclusion is false | F10: https://drive.google.com/file/d/1qtuFKUR0SsX3aeB_uI08b2sJw0DX2EOL/view | G10: Archive member; original carrier retained | H10: LOGICAL_QUARANTINE; frozen bytes retained | I10: f3e672a3cb4d4016a117624493a8ce766c5bf21e1a7697b840da82e896f98ecf; 2364 bytes | J10: Complete corrected consumer replay + exact replacement identities + scoped review | K10: 2026-09-17T16:25:48.473074Z
A11: Q-R17-H5-07 | B11: DEFECTIVE_SCOPE | C11: 1vSI-evINWskhXVyiZ0slt-rLT74sPpXH | D11: K3_SIDE24_LB/UPPER2D/H5_closure/h5_totals_r0.025_v2.json | E11: Dependent H5 numerical certification held pending full corrected-kernel replay; this is not a declaration that every mathematical conclusion is false | F11: https://drive.google.com/file/d/1qtuFKUR0SsX3aeB_uI08b2sJw0DX2EOL/view | G11: Archive member; original carrier retained | H11: LOGICAL_QUARANTINE; frozen bytes retained | I11: f7697bcfa0fe32b5c87c8ef8adef5d4384ab1bda7cd4a7c4782fef8c99103fcb; 2385 bytes | J11: Complete corrected consumer replay + exact replacement identities + scoped review | K11: 2026-09-17T16:25:48.473074Z
A12: Q-R17-H5-08 | B12: DEFECTIVE_SCOPE | C12: 1vSI-evINWskhXVyiZ0slt-rLT74sPpXH | D12: K3_SIDE24_LB/UPPER2D/H5_closure/h5_totals_r0.035355_v2.json | E12: Dependent H5 numerical certification held pending full corrected-kernel replay; this is not a declaration that every mathematical conclusion is false | F12: https://drive.google.com/file/d/1qtuFKUR0SsX3aeB_uI08b2sJw0DX2EOL/view | G12: Archive member; original carrier retained | H12: LOGICAL_QUARANTINE; frozen bytes retained | I12: 808d6901e3254a73181aa696904ed04567d401b6e58300454d489046c36f4f64; 2399 bytes | J12: Complete corrected consumer replay + exact replacement identities + scoped review | K12: 2026-09-17T16:25:48.473074Z
... A23: Q-RN5-LM004-A1 | B23: DEFECTIVE_SCOPE | C23: 1CHErajW7G2y8y7Mr0bKYMy2lJbA2HIAt | D23: AUTO-RV-LM004-20260917165201_TECHNICAL_RECONCILIATION.md | E23: A1 statement that the C1 derivative supremum is duplicated, and the proposed cleanup. Prior technical reconciliation is retained with the erratum. | F23: https://drive.google.com/file/d/1QKujzzkp_nzCWFLky9ZayTzP_fbStxry/view | G23: 1wPVf5p6Tz_4jy4NgRzrKJgUjEqM7MD3f | H23: 1cKcmxCj9jcFFCUBgUqpifDiOfJJyh17f | I23: c0571b7affc23c0d44e3479cb7ebafafbcfd49001a43097d43f00553f1d75f81; 5093 bytes | J23: Metadata move is reversible using original parent/name; historical report must always be read with LM004_REVIEW_ERRATUM_v1.1. False A1 finding is not restored as authority. | K23: 2026-09-17T17:19:16.450Z

Sheet Work Events
A1: Event ID | B1: UTC | C1: Session ID | D1: Provider | E1: Target key | F1: Event type | G1: Claim reference | H1: Lease until UTC | I1: Source SHA-256 | J1: Expected old head | K1: Proposed new head / artifact | L1: Status | M1: Notes | N1: Domain
A2: OPS4-INSTALL-20260917 | B2: 2026-09-17T16:25:48.473074Z | C2: OPS4-20260917-b9c2 | D2: OpenAI | E2: AI-DRIVE-CONTROL-R17 | F2: CLAIM | G2: OPS4-INSTALL-20260917 | H2: 2026-09-17T18:25:48.528725Z | I2: 04987ba47b58be623a3b2a5a8a21236f43d4393cc04009e87f4a62b59a787390 | J2: R16 | K2: R17 | L2: ACTIVE | M2: Owner-authorized overhaul; legacy claim CLAIM-OPS4-20260917-b9c2 | N2: OPS
A3: OPS4-LM009-REVIEW-20260917 | B3: 2026-09-17T16:25:48.473074Z | C3: OPS4-20260917-b9c2 | D3: OpenAI | E3: LM009-MAIN@ccc07d959428519733c7fdf6c72f1bce63a40d0b0dc956ce0fe9f2ec459eb0b1 | F3: RECORD_REVIEW | I3: ccc07d959428519733c7fdf6c72f1bce63a40d0b0dc956ce0fe9f2ec459eb0b1 | K3: https://drive.google.com/file/d/1cDFrsYx8l6jfGzQzYi0RemAw8Tv4d2qk/view | L3: PASS_TECHNICAL | M3: Exposed nonauthor session; same provider, zero organizational independence; exact abstract scope | N3: MATH
A4: OPS4-PUBLISH-R17-20260917 | B4: 2026-09-17T16:38:39.757Z | C4: OPS4-20260917-b9c2 | D4: OpenAI | E4: AI-DRIVE-CONTROL-R17 | F4: PUBLISH | G4: OPS4-INSTALL-20260917 | I4: 04987ba47b58be623a3b2a5a8a21236f43d4393cc04009e87f4a62b59a787390 | J4: R16 | K4: R17 / https://drive.google.com/file/d/1XRecEnh5HxbJtZHmBYYfw1DeqVjG6SYs/view | L4: VERIFIED | M4: Owner-authorized installation; guarded Docs writes; exact bundle readback | N4: OPS
A5: OPS4-RELEASE-R17-20260917 | B5: 2026-09-17T16:38:39.757Z | C5: OPS4-20260917-b9c2 | D5: OpenAI | E5: AI-DRIVE-CONTROL-R17 | F5: RELEASE | G5: OPS4-INSTALL-20260917 | I5: 04987ba47b58be623a3b2a5a8a21236f43d4393cc04009e87f4a62b59a787390 | J5: R17 | K5: R17 | L5: COMPLETE | M5: Legacy claim and structural lease released in same batch | N5: OPS
A6: OPS4-CUSTODY-R17-20260917 | B6: 2026-09-17T16:46:24.367Z | C6: OPS4-20260917-b9c2 | D6: OpenAI | E6: AI-DRIVE-CONTROL-R17 | F6: RECORD_CUSTODY | G6: OPS4-INSTALL-20260917 | I6: db26726a30d45debe9eb0da8b3a01924c6835aae7fa1054e6526130a10bd2ad8 | J6: R17 | K6: https://drive.google.com/file/d/1avbw3oP2wgQ21bTpNV6h7YaGJOw8OCQO/view | L6: VERIFIED | M6: Final verification bundle https://drive.google.com/file/d/1HUr4xXmcX-vsRt8s5uzie-2LTwpaj5fl/view SHA256 723f38d467aff6df61c5f1687ce32a05424ca075bbea7a60f4ad5556185409b7; install claim remains released | N6: OPS
A7: CLAIM-AUTO-RV-LM004-20260917165201 | B7: 2026-09-17T16:52:01.051Z | C7: AUTO-RV-LM004-20260917165201 | D7: OpenAI / Codex | E7: LCR-DER-016-v1.1@d43179f3abfd7e93f988725f3b89a5826cc71e0fa04840f65c7f93f3359d0f87 | F7: CLAIM | G7: AUTO-RV-LM004-20260917165201 | H7: 2026-09-17T18:52:01.051Z | I7: d43179f3abfd7e93f988725f3b89a5826cc71e0fa04840f65c7f93f3359d0f87 | J7: REV-S2-AUD006-SAME | K7: PENDING RECONCILIATION | L7: ACTIVE | M7: Oldest eligible queue item; exposed nonauthor same-provider reconciliation; zero organizational-independence credit | N7: MATH
A8: PUBLISH-AUTO-RV-LM004-20260917165201 | B8: 2026-09-17T16:55:40.169Z | C8: AUTO-RV-LM004-20260917165201 | D8: OpenAI / Codex | E8: LCR-DER-016-v1.1@d43179f3abfd7e93f988725f3b89a5826cc71e0fa04840f65c7f93f3359d0f87 | F8: PUBLISH | G8: AUTO-RV-LM004-20260917165201 | I8: d43179f3abfd7e93f988725f3b89a5826cc71e0fa04840f65c7f93f3359d0f87 | J8: REV-S2-AUD006-SAME | K8: https://drive.google.com/file/d/1CHErajW7G2y8y7Mr0bKYMy2lJbA2HIAt/view | L8: PASS_TECHNICAL_RECONCILED | M8: Fresh exact body; prior verdict reconciled; raw artifact 5093 bytes SHA256 c0571b7affc23c0d44e3479cb7ebafafbcfd49001a43097d43f00553f1d75f81; zero org independence | N8: MATH
A9: RELEASE-AUTO-RV-LM004-20260917165201 | B9: 2026-09-17T16:55:40.169Z | C9: AUTO-RV-LM004-20260917165201 | D9: OpenAI / Codex | E9: LCR-DER-016-v1.1@d43179f3abfd7e93f988725f3b89a5826cc71e0fa04840f65c7f93f3359d0f87 | F9: RELEASE | G9: AUTO-RV-LM004-20260917165201 | I9: d43179f3abfd7e93f988725f3b89a5826cc71e0fa04840f65c7f93f3359d0f87 | J9: https://drive.google.com/file/d/1CHErajW7G2y8y7Mr0bKYMy2lJbA2HIAt/view | K9: https://drive.google.com/file/d/1CHErajW7G2y8y7Mr0bKYMy2lJbA2HIAt/view | L9: COMPLETE | M9: Claim released; remaining obligation is an organizationally distinct accepted exact-object verdict | N9: MATH
A10: CLAIM-ROUND5-RN5-ALIGN-NEAR | B10: 2026-09-17T17:00:27.766Z | C10: ROUND5-20260917-b9c2 | D10: OpenAI | E10: RN-UNIF/r=1/20/SIDE24 | F10: CLAIM | G10: CLAIM-ROUND5-RN5-ALIGN-NEAR | H10: 2026-09-17T19:00:27.766Z | I10: 0c9446b7cb49e6e1e45e43f84bb72ce680f022882e225fdff61c8e6edede1373 | J10: RN3 + CL-RNU-003 | K10: PENDING | L10: ACTIVE | M10: Compare exact-object definitions; derive and test stable near-annulus enclosure. Author-side / same lineage. | N10: MATH
A11: CLAIM-ROUND5-LM004-REVIEW-ERRATUM | B11: 2026-09-17T17:00:27.766Z | C11: ROUND5-20260917-b9c2 | D11: OpenAI | E11: REV-AUTO-RV-LM004-20260917165201 | F11: CLAIM | G11: CLAIM-ROUND5-LM004-REVIEW-ERRATUM | H11: 2026-09-17T19:00:27.766Z | I11: c0571b7affc23c0d44e3479cb7ebafafbcfd49001a43097d43f00553f1d75f81 | J11: 1CHErajW7G2y8y7Mr0bKYMy2lJbA2HIAt | K11: PENDING | L11: ACTIVE | M11: Correct display-induced duplicate-term finding; preserve exact target science. Same-provider exposed audit. | N11: OPS
A12: HEARTBEAT-RN5-2026-09-17T17:12:43.249Z | B12: 2026-09-17T17:12:43.249Z | C12: ROUND5-20260917-b9c2 | D12: OpenAI | E12: RN-UNIF/r=1/20/SIDE24 | F12: HEARTBEAT | G12: CLAIM-ROUND5-RN5-ALIGN-NEAR | H12: 2026-09-17T19:12:43.250Z | I12: 5bc092412943e1c2185a8cf86cee23ae9cd9a2aad9bd9ef0b02807e9ff58dfa4 | J12: RN3 + CL-RNU-003 | K12: RN5 repair candidate | L12: ACTIVE | M12: Wrong near determinant moment proved; 65 stations and 10 local Taylor boxes; full cover open | N12: MATH
A13: HEARTBEAT-LM004-2026-09-17T17:12:43.249Z | B13: 2026-09-17T17:12:43.249Z | C13: ROUND5-20260917-b9c2 | D13: OpenAI | E13: REV-AUTO-RV-LM004-20260917165201 | F13: HEARTBEAT | G13: CLAIM-ROUND5-LM004-REVIEW-ERRATUM | H13: 2026-09-17T19:12:43.250Z | I13: c0571b7affc23c0d44e3479cb7ebafafbcfd49001a43097d43f00553f1d75f81 | J13: 1CHErajW7G2y8y7Mr0bKYMy2lJbA2HIAt | K13: Numbered erratum in preparation | L13: ACTIVE | M13: Fresh full raw export proves duplicate-term finding false; target frozen body unchanged | N13: OPS
A14: PUBLISH-RN5-20260917 | B14: 2026-09-17T17:19:16.450Z | C14: ROUND5-20260917-b9c2 | D14: OpenAI | E14: RN-UNIF/r=1/20/SIDE24 | F14: PUBLISH | G14: CLAIM-ROUND5-RN5-ALIGN-NEAR | I14: ac89f60b8206bfe011e6c2bc653e7acb39bc83a55c2a2c8fd1e17fd70c6c0383 | J14: RN3 + CL-RNU-003 | K14: https://drive.google.com/file/d/1LtnvNd0vAW-y3pzbyHLjgtF7Uw5sTph5/view | L14: AUTHOR_CANDIDATE_VERIFIED | M14: 26 payloads exact;65 stations;10 boxes;66 checks;full near cover open | N14: MATH
A15: PUBLISH-LM004-ERRATUM-20260917 | B15: 2026-09-17T17:19:16.450Z | C15: ROUND5-20260917-b9c2 | D15: OpenAI | E15: REV-AUTO-RV-LM004-20260917165201 | F15: PUBLISH | G15: CLAIM-ROUND5-LM004-REVIEW-ERRATUM | I15: 84189b73e414952d086877fda5b59b1bfb3d6c40c389bcb19daa43bf8866efc9 | J15: 1CHErajW7G2y8y7Mr0bKYMy2lJbA2HIAt | K15: https://drive.google.com/file/d/1QKujzzkp_nzCWFLky9ZayTzP_fbStxry/view | L15: A1_SUPERSEDED | M15: Source body unchanged; prior technical disposition and external predicate retained | N15: OPS
A16: QUARANTINE-RN5-20260917 | B16: 2026-09-17T17:19:16.450Z | C16: ROUND5-20260917-b9c2 | D16: OpenAI | E16: RN5-five-scoped-exclusions | F16: RECORD_QUARANTINE | G16: CLAIM-ROUND5-RN5-ALIGN-NEAR | I16: d7e156f913e0695a3ad457640781e7a9eff191f0f3c35df8415f7995c38cd36f | J16: Old affected scopes | K16: https://drive.google.com/file/d/1HkQimvHTRrovPKxMJHniT1I16jLIIKXf/view | L16: RECORDED | M16: Three frozen archive-member scopes;CL near claim;old LM004 A1 claim. One reversible old-report move. | N16: OPS
A17: CL-CODE-BLOCKER-RN5-20260917 | B17: 2026-09-17T17:19:16.450Z | C17: ROUND5-20260917-b9c2 | D17: OpenAI | E17: CL-RNU-003-current-executable | F17: CANNOT_VERIFY | G17: CLAIM-ROUND5-RN5-ALIGN-NEAR | I17: 59b8f002f1b1e81e7829416baf16ef1d84b1326d4b3b4604b833e5a55a9d6d53 | J17: CL report references v5 archive | K17: https://drive.google.com/file/d/1LtnvNd0vAW-y3pzbyHLjgtF7Uw5sTph5/view | L17: MISSING_EXACT_SOURCE | M17: Locate exact CL_ANTHROPIC_BUNDLE_2026-09-17_v5.zip or rnu_t4.py/rnu_spine.py with hashes; report-level crosswalk completed | N17: MATH
A18: RELEASE-RN5-20260917 | B18: 2026-09-17T17:19:16.450Z | C18: ROUND5-20260917-b9c2 | D18: OpenAI | E18: RN-UNIF/r=1/20/SIDE24 | F18: RELEASE | G18: CLAIM-ROUND5-RN5-ALIGN-NEAR | I18: 28c1c385406452a706f11aea1646a87585b002841005d57febdf32222c368c6e | J18: RN3 + CL-RNU-003 | K18: https://drive.google.com/file/d/1g5UP_KYlvPmx7LFwjGk6qK5QZLnL1hLj/view | L18: COMPLETE_SCOPED | M18: Author-side repair delivered; no retained claim; global near-integral/theorem still open | N18: MATH
A19: RELEASE-LM004-ERRATUM-20260917 | B19: 2026-09-17T17:19:16.450Z | C19: ROUND5-20260917-b9c2 | D19: OpenAI | E19: REV-AUTO-RV-LM004-20260917165201 | F19: RELEASE | G19: CLAIM-ROUND5-LM004-REVIEW-ERRATUM | I19: 84189b73e414952d086877fda5b59b1bfb3d6c40c389bcb19daa43bf8866efc9 | J19: 1CHErajW7G2y8y7Mr0bKYMy2lJbA2HIAt | K19: https://drive.google.com/file/d/1QKujzzkp_nzCWFLky9ZayTzP_fbStxry/view | L19: COMPLETE | M19: Erratum delivered; no retained claim | N19: OPS
A20: CUSTODY-RN5-20260917 | B20: 2026-09-17T17:21:33.184Z | C20: ROUND5-20260917-b9c2 | D20: OpenAI | E20: RN5-release | F20: RECORD_CUSTODY | G20: CLAIM-ROUND5-RN5-ALIGN-NEAR | I20: 3aad4a2f83252aae6a7ef1fa47c589768ac74e1572ed1dc0b601ccec1bd6f6bc | J20: RN5 verified candidates | K20: https://drive.google.com/file/d/1QqS2W0D0FYPHeXyDSjAS2LhOPgSUcQ9m/view | L20: VERIFIED / CLAIMS RELEASED | M20: Detached receipt; no new claim or independence credit | N20: OPS
A21: RN5-OPS-CUSTODY-20260917 | B21: 2026-09-17T17:24:13.572Z | C21: ROUND5-20260917-b9c2 | D21: OpenAI | E21: RN5-publication-custody | F21: RECORD_CUSTODY | G21: CLAIM-ROUND5-RN5-ALIGN-NEAR | I21: f1b7384268546a243e8e5a01144c683ba653f6b510855d43db0d94f463639b43 | J21: RN5-CUSTODY | K21: https://drive.google.com/file/d/1kzXocXd6qZH2-pSTwLoODh0F5K6piUml/view | L21: VERIFIED / CLAIMS RELEASED | M21: All Drive outputs saved and raw-verified. Additional chat Library copies failed transfer twice; no scientific or Drive data loss. | N21: OPS
A22: CLAIM-ACCESS-20260917-4121 | B22: 2026-09-17T18:14:46.185Z | C22: ACCESS-20260917-4121 | D22: OpenAI / Codex | E22: DRIVE-FORMAT-ACCESSIBILITY | F22: CLAIM | G22: CLAIM-ACCESS-20260917-4121 | H22: 2026-09-17T20:14:46.186Z | J22: Existing R17 navigation | K22: Accessibility copies and complete inventory | L22: ACTIVE | M22: Owner-requested full inventory and format repair. Additive source-preserving copies; no scientific status changes. | N22: OPS
A23: HEARTBEAT-ACCESS-2026-09-17T19:19:26.427Z | B23: 2026-09-17T19:19:26.427Z | C23: ACCESS-20260917-4121 | D23: OpenAI / Codex | E23: DRIVE-FORMAT-ACCESSIBILITY | F23: HEARTBEAT | G23: CLAIM-ACCESS-20260917-4121 | H23: 2026-09-17T21:19:26.427Z | J23: Existing R17 navigation | K23: Resume saved 4,456-item audit | L23: ACTIVE | M23: User requested continuation; checkpoint recovered in workspace ddc3191a7438. No scientific promotion. | N23: OPS
A24: HEARTBEAT-ACCESS-2026-09-17T20:35:16.450Z | B24: 2026-09-17T20:35:16.450Z | C24: ACCESS-20260917-4121 | D24: OpenAI / Codex | E24: DRIVE-FORMAT-ACCESSIBILITY | F24: HEARTBEAT | G24: CLAIM-ACCESS-20260917-4121 | H24: 2026-09-17T22:35:16.450Z | J24: Existing R17 navigation | K24: Format accessibility copies and source map | L24: ACTIVE | M24: Owner-requested continuation. Full 4,456-item baseline audited; publishing verified reading copies and repairing import fidelity. Original sources and scientific status preserved. | N24: OPS
A25: HEARTBEAT-ACCESS-2026-09-17T21:45:12.347Z | B25: 2026-09-17T21:45:12.347Z | C25: ACCESS-20260917-4121 | D25: OpenAI / Codex | E25: DRIVE-FORMAT-ACCESSIBILITY | F25: HEARTBEAT | G25: CLAIM-ACCESS-20260917-4121 | H25: 2026-09-17T23:45:12.347Z | J25: Existing accessibility partial publication | K25: Complete remaining copies, validate data, publish source map | L25: ACTIVE | M25: User resumed after context limit; recovered original audit and exact pending queue. No scientific status changes. | N25: OPS
A26: HEARTBEAT-ACCESS-2026-09-17T23:01:44.618Z | B26: 2026-09-17T23:01:44.618Z | C26: ACCESS-20260917-4121 | D26: OpenAI / Codex | E26: DRIVE-FORMAT-ACCESSIBILITY | F26: HEARTBEAT | G26: CLAIM-ACCESS-20260917-4121 | H26: 2026-09-18T01:01:44.618Z | J26: Existing accessibility partial publication | K26: Complete native data repair and publish source map | L26: ACTIVE | M26: Recovered original audit/checkpoints from ddc3191a7438; continuing after IMG_6203 context limit. Source evidence and scientific status preserved. | N26: OPS
A27: HEARTBEAT-ACCESS-2026-09-17T23:53:40.937Z | B27: 2026-09-17T23:53:40.937Z | C27: ACCESS-20260917-4121 | D27: OpenAI / Codex | E27: DRIVE-FORMAT-ACCESSIBILITY | F27: HEARTBEAT | G27: CLAIM-ACCESS-20260917-4121 | H27: 2026-09-18T01:53:40.937Z | J27: Existing accessibility publication | K27: Verified data repairs; publish source map and durable handoff | L27: ACTIVE | M27: Owner-requested continuation after context interruption. All remaining data repairs and reading checks complete; final navigation publication underway. | N27: OPS
A28: PUBLISH-ACCESS-2026-09-17T23:57:33.664Z | B28: 2026-09-17T23:57:33.664Z | C28: ACCESS-20260917-4121 | D28: OpenAI / Codex | E28: DRIVE-FORMAT-ACCESSIBILITY | F28: PUBLISH | G28: CLAIM-ACCESS-20260917-4121 | I28: b7a47ec1f996557a5e677b281e14bb0f7863478ae5c68f3f0c4866c4bb806c21 | J28: Existing partial accessibility publication | K28: https://docs.google.com/spreadsheets/d/1hO3MPQwtAiEjCGdOjZJTbB8fKIvt_3GU6KgxPGTPiLg/edit?usp=drivesdk | L28: COMPLETE_WITH_SOURCE_EXCEPTIONS | M28: 392 copies; all remaining data repairs verified. Report and audit readback exact. https://drive.google.com/file/d/1sORvjt806v3z1rPAlH8I7CflxEZDUx8X/view?usp=drivesdk | N28: OPS
A29: RELEASE-ACCESS-2026-09-17T23:57:33.664Z | B29: 2026-09-17T23:57:33.664Z | C29: ACCESS-20260917-4121 | D29: OpenAI / Codex | E29: DRIVE-FORMAT-ACCESSIBILITY | F29: RELEASE | G29: CLAIM-ACCESS-20260917-4121 | I29: b7a47ec1f996557a5e677b281e14bb0f7863478ae5c68f3f0c4866c4bb806c21 | J29: https://docs.google.com/spreadsheets/d/1hO3MPQwtAiEjCGdOjZJTbB8fKIvt_3GU6KgxPGTPiLg/edit?usp=drivesdk | K29: https://docs.google.com/spreadsheets/d/1hO3MPQwtAiEjCGdOjZJTbB8fKIvt_3GU6KgxPGTPiLg/edit?usp=drivesdk | L29: RELEASED | M29: Publication complete for the audited snapshot. Source exceptions retained; original evidence, scientific gates and sharing unchanged. Future work uses targeted deltas. | N29: OPS
A30: 8aae0ef2-fef3-441d-a4fa-f23dd3d34276 | B30: 2026-09-18T00:09:04.401Z | C30: STRUCTURE-20260918-C2087 | D30: OpenAI / Codex | E30: DRIVE-STRUCTURE-20260918 | F30: CLAIM | G30: 8aae0ef2-fef3-441d-a4fa-f23dd3d34276 | H30: 2026-09-18T02:09:04.401Z | I30: 3d9861ae600de134a28b8681664e2e4ab15d16f73716379a71602d44fcfac280 | J30: R17 navigation plus verified accessibility map | K30: Date containers, triage hierarchy, folder directory and current naming rules | L30: ACTIVE | M30: Owner-directed structural optimization; metadata and navigation only. Original scientific evidence and dispositions retained. | N30: OPS
A31: PUBLISH-STRUCTURE-20260918-C2087 | B31: 2026-09-18T00:23:00.610Z | C31: STRUCTURE-20260918-C2087 | D31: OpenAI / Codex | E31: DRIVE-STRUCTURE-20260918 | F31: PUBLISH | G31: 8aae0ef2-fef3-441d-a4fa-f23dd3d34276 | I31: 3d9861ae600de134a28b8681664e2e4ab15d16f73716379a71602d44fcfac280 | J31: R17 navigation plus verified accessibility map | K31: https://drive.google.com/file/d/14z_m-gec3YRFWmJJksoJNRdT9_EN8h1C/view?usp=drivesdk | L31: COMPLETE | M31: Report SHA-256 fb95fe0f38b243a87483f8134ea44421cc5a1f3ca2b5dcb52f6726b4b6be7886; 20 structure edits verified; 755 folder rows; 238 path changes; 8561 native cells exact. Published files hash-readback verified. | N31: OPS
A32: RELEASE-STRUCTURE-20260918-C2087 | B32: 2026-09-18T00:23:00.610Z | C32: STRUCTURE-20260918-C2087 | D32: OpenAI / Codex | E32: DRIVE-STRUCTURE-20260918 | F32: RELEASE | G32: 8aae0ef2-fef3-441d-a4fa-f23dd3d34276 | I32: 3d9861ae600de134a28b8681664e2e4ab15d16f73716379a71602d44fcfac280 | J32: https://drive.google.com/file/d/14z_m-gec3YRFWmJJksoJNRdT9_EN8h1C/view?usp=drivesdk | K32: https://docs.google.com/spreadsheets/d/1hO3MPQwtAiEjCGdOjZJTbB8fKIvt_3GU6KgxPGTPiLg/edit?usp=drivesdk | L32: RELEASED | M32: Completed owner-directed structural scope. Follow Folder Rules and stable IDs; no scientific status changes. Metadata basis is explicit for 184 fresh / 571 baseline folders. | N32: OPS
A33: e796f04b-92f6-4d0e-a53a-16503d842b1e | B33: 2026-09-18T02:50:56.093Z | C33: OP-REUSE-20260918-66ba2ff9 | D33: OpenAI / Codex | E33: DRIVE-REUSABLE-OPERATIONS | F33: CLAIM | G33: e796f04b-92f6-4d0e-a53a-16503d842b1e | H33: 2026-09-18T04:50:56.093Z | I33: 04987ba47b58be623a3b2a5a8a21236f43d4393cc04009e87f4a62b59a787390 | J33: R17 home, router and research registers | K33: Scope-aware operation index, insight and retrieval reference | L33: ACTIVE | M33: Owner-authorized audit and optimization; no scientific status promotion. Reuse existing register and preserve sources. | N33: OPS
A34: c3c4a153-442a-4b13-8eca-71057d5e741d | B34: 2026-09-18T16:40:35.055046Z | C34: DG-EXEC-20260918-49291487 | D34: OpenAI / ChatGPT | E34: DRIVE-GITHUB-EXECUTION-HANDOFF-20260918-49291487 | F34: CLAIM | G34: c3c4a153-442a-4b13-8eca-71057d5e741d | H34: 2026-09-18T18:40:35.055063Z | J34: New additive operational handoff; R17 remains controlling | K34: Drive-led / GitHub-executed design and write/admin capability blocker | L34: ACTIVE | M34: User authorizes model collaboration and restrictive repository access changes. GitHub reports push=false/admin=false; branch creation returned 403. No repository mutation or scientific promotion. This claim covers only a new handoff document. | N34: OPS
A35: 383d4ccb-4aef-4aa5-bdea-48c4618cf819 | B35: 2026-09-18T16:44:59.428194Z | C35: DG-EXEC-20260918-49291487 | D35: OpenAI / ChatGPT | E35: DRIVE-GITHUB-EXECUTION-HANDOFF-20260918-49291487 | F35: PUBLISH | G35: c3c4a153-442a-4b13-8eca-71057d5e741d | I35: 788451eb94ef5d557681ce7d896026c7e811402f062090046b48c083fc45d556 | J35: No prior handoff; R17 unchanged | K35: https://docs.google.com/document/d/1ctDf6mFAlV_HcSst6dI-fxPbQCJ6j-1LrOuT8l1_oWs/edit | L35: HANDOFF_VERIFIED / EXECUTION_NOT_DEPLOYED | M35: Six raw files byte-identical on readback in folder 1o8eNasDxb8Ql3W1uWKJryKa9i7XHUiEI; native Doc is reading mirror. Manifest 1iwo6RO9SfyC4XGZk7BuUyGLWzNRKfxAn SHA256 a8c9f2de60c8a225391de9ba7e65356a20a1c9352688d0800e226203a6295f67. Three shell probes and exact-source local patch check passed. GitHub branch creation denied 403; no GitHub or permission mutation. Admin/write-capable session required. | N35: OPS
A36: 168981af-4006-4b67-804c-123f9ee652ac | B36: 2026-09-18T16:44:59.428194Z | C36: DG-EXEC-20260918-49291487 | D36: OpenAI / ChatGPT | E36: DRIVE-GITHUB-EXECUTION-HANDOFF-20260918-49291487 | F36: RELEASE | G36: c3c4a153-442a-4b13-8eca-71057d5e741d | I36: 788451eb94ef5d557681ce7d896026c7e811402f062090046b48c083fc45d556 | J36: Additive handoff published | K36: https://drive.google.com/drive/folders/1o8eNasDxb8Ql3W1uWKJryKa9i7XHUiEI | L36: COMPLETE_SCOPED / GITHUB_PERMISSION_BLOCKED | M36: Document-delivery claim released. Execution installation remains open. No model-only access enforcement claimed, no remote CI run, no scientific status change, no new automation. | N36: OPS
A37: 6158c383-f316-4add-a59a-e512323178fd | B37: 2026-09-19T22:26:40.862186Z | C37: 01a0bbb5-2fcb-77f0-b78b-4d220ddd7ab2 | D37: OpenAI / Codex | E37: d6g8k5htny-coder/main:chatgpt/drive-github-hardening-20260919 | F37: CLAIM | G37: 6158c383-f316-4add-a59a-e512323178fd | H37: 2026-09-20T00:26:40.862186Z | I37: b1a1e1b81a180378f6045d1ff967c49e32506d01efbaa2286271df8604279131 | J37: a38ad1edd04ce2451274811731819ea4e4661ceb | K37: CI/manifest reliability; source-map audit; bounded bridge pilot; draft PR and factual receipt | L37: ACTIVE | M37: Direct owner setup instruction in task 01a0bbae-d37c-7601-b1e6-f969a7dc10d6. Preserve Claude PR/branches, frozen exports, scientific states, public visibility and access settings. Recon 1sBN9D1LDreO1kYevSMjlG6rzrT-g7poS raw readback verified. No scientific promotion or independent review. | N37: OPS
A38: 2e9f0cd1-1e25-4383-a9f1-ae08eaf5dec1 | B38: 2026-09-19T22:29:08Z | C38: 01a0bbae-d37c-7601-b1e6-f969a7dc10d6 | D38: OpenAI / Codex | E38: d6g8k5htny-coder/main:chatgpt/drive-github-hardening-20260919 | F38: RECORD_AUTHORIZATION | G38: 6158c383-f316-4add-a59a-e512323178fd | H38: 2026-09-20T00:26:40.862186Z | I38: c173f219316291170712e239c942f95e59c6afa944bd897c4d1a71a073c022e1 | J38: a38ad1edd04ce2451274811731819ea4e4661ceb | K38: https://drive.google.com/file/d/1rnFS5v7vHjhmOnUgc_GVMGPV-uI1rFVV/view | L38: AUTHORIZED_SCOPED / PILOT_NOT_EXECUTED | M38: Direct owner instructions recorded in DG-INFRA-AUTH-20260919-02; supersedes -01 solely to replace the unappended proposed claim with the actual worker claim. Not a cryptographic signature or independent review. Work order DG-INFRA-WO-20260919-01; no scientific promotion, merge, recurring deployment, permission changes or T9 changes. | N38: OPS
A39: 69a8b4a7-75e2-4d54-a76d-bd7c404d48e1 | B39: 2026-09-19T22:57:50.415264Z | C39: 01a0bbb5-2fcb-77f0-b78b-4d220ddd7ab2 | D39: OpenAI / Codex | E39: d6g8k5htny-coder/main:chatgpt/drive-github-hardening-20260919 | F39: PUBLISH | G39: 6158c383-f316-4add-a59a-e512323178fd | H39: 2026-09-20T00:26:40.862186Z | I39: 6399c0c66f925cffec1235939b1302b3c6bb193c5a7625890f7c889b704c9cc7 | J39: a38ad1edd04ce2451274811731819ea4e4661ceb | K39: https://github.com/d6g8k5htny-coder/main/pull/3 | https://drive.google.com/file/d/1XDolhhbiw3NNPC-D0p8UfpJ4VequS4wS/view | L39: DRAFT_PR / PILOT_RECORDED / NOT_ACCEPTED | M39: DG-INFRA-WO-20260919-01. Head 8b7e2a8e761b706b10ad435998af0ce0d06801b6. Local 19 checker commands pass; 1652 tests pass, 1 documented skip. Remote push and PR CI pass. Pilot success, deliberate failure, stale refusal, identical/conflicting retry and exact Drive readback verified. Receipt 26866 bytes. No scientific promotion, independent review, deployment, merge or settings change. | N39: OPS
A40: 4c198632-d1f1-402c-90f0-317970f2a35b | B40: 2026-09-19T22:57:50.415264Z | C40: 01a0bbb5-2fcb-77f0-b78b-4d220ddd7ab2 | D40: OpenAI / Codex | E40: d6g8k5htny-coder/main:chatgpt/drive-github-hardening-20260919 | F40: RELEASE | G40: 6158c383-f316-4add-a59a-e512323178fd | I40: 6399c0c66f925cffec1235939b1302b3c6bb193c5a7625890f7c889b704c9cc7 | J40: 8b7e2a8e761b706b10ad435998af0ce0d06801b6 | K40: https://github.com/d6g8k5htny-coder/main/pull/3 | https://drive.google.com/file/d/1XDolhhbiw3NNPC-D0p8UfpJ4VequS4wS/view | L40: RELEASED / DRAFT_REVIEW_PENDING | M40: Infrastructure implementation and bounded manual pilot finished. Claim released. Independent review, owner acceptance, production identity/isolation controls, access audit, branch protection and scoped remaining source coverage stay open. Parent coordinator will reconcile Cross-Line Work Order outcome from exact receipt references. Scientific states unchanged. | N40: OPS
A41: a78f5b90-a581-4427-8d3f-2aeff817331c | B41: 2026-09-19T23:07:06.006370Z | C41: 01a0bbb5-2fcb-77f0-b78b-4d220ddd7ab2 | D41: OpenAI / Codex | E41: d6g8k5htny-coder/main:chatgpt/drive-github-hardening-20260919 | F41: CLAIM | G41: a78f5b90-a581-4427-8d3f-2aeff817331c | H41: 2026-09-20T01:07:06.006370Z | I41: 5cb2d2ea8073d3a3f329327569633ff33372f978ccc40dbca7b01dffe73348c0 | J41: 8b7e2a8e761b706b10ad435998af0ce0d06801b6 | K41: Continue indexed research corpus transfer; complete coverage accounting; exact Hermite-Gaussian kernel envelopes | L41: ACTIVE | M41: Direct owner instruction in this task to continue Drive→GitHub transfer and advance mathematics/architecture. Preserve frozen scientific states and existing branches; treat imported code as data; hold explicit no-open and unrelated personal material. No independent-review credit or theorem promotion. | N41: RESEARCH / OPS
A42: 46433c61-4b0f-4df8-bcbe-c0c4185efe50 | B42: 2026-09-20T00:24:04.500427+00:00 | C42: 01a0bbb5-2fcb-77f0-b78b-4d220ddd7ab2 | D42: OpenAI / Codex | E42: d6g8k5htny-coder/main:chatgpt/drive-github-hardening-20260919 | F42: PUBLISH | G42: a78f5b90-a581-4427-8d3f-2aeff817331c | H42: 2026-09-20T01:07:06.006370Z | I42: b878b7925e61b2f97be349698fb63f391763a559a2bff0534e6ff94889bf70ea | J42: 8b7e2a8e761b706b10ad435998af0ce0d06801b6 | K42: 508ae7e20301df57da0045b13bc7ed9eb0b67ead | https://drive.google.com/file/d/1WqIeKAosnVrdco7DNemuEgUKRrLVCd9D/view?usp=drivesdk | L42: PUBLISHED DRAFT / REMOTE CI RUNNING | M42: 4112 stored file identities,758 folders,54 holds. Local 21 checkers and1712 tests pass;1 skip. Candidate unreviewed; no scientific status change or independence credit. | N42: RESEARCH / OPS
A43: 338efcd7-3aa4-4607-b43e-da2de9edb005 | B43: 2026-09-20T00:24:04.500427+00:00 | C43: 01a0bbb5-2fcb-77f0-b78b-4d220ddd7ab2 | D43: OpenAI / Codex | E43: HG-GLOBAL-ENVELOPE-20260919-v1 | F43: REVIEW_REQUEST | G43: a78f5b90-a581-4427-8d3f-2aeff817331c | H43: 2026-09-20T01:07:06.006370Z | I43: 8c0dccdfd177b7ae03a0edd62f92b330825469a9e991d33d2226eb62cfd6083e | K43: RV-HG-ENVELOPE-20260919-v1 | https://drive.google.com/file/d/1pWBlanUuRBPVSrrbSd4XDUxIcX0gU8va/view?usp=drivesdk | L43: READY FOR TECHNICAL REVIEW / UNREVIEWED | M43: Exact 3641-byte proof; dependencies in delivery bundle. Review normalization,global envelope,interval containment and uniform infinite tail. No full jet/geometry/band binding;zero independence. | N43: MATH
A44: 71fabf96-833d-4cb5-a8b8-0a997a8c3098 | B44: 2026-09-20T00:41:56.590869+00:00 | C44: 01a0bbb5-2fcb-77f0-b78b-4d220ddd7ab2 | D44: OpenAI / Codex | E44: d6g8k5htny-coder/main:chatgpt/drive-github-hardening-20260919 | F44: RELEASE | G44: a78f5b90-a581-4427-8d3f-2aeff817331c | I44: 22ccc07b8bcc3e17e48cb08a4956936fd4876ed3414f6bbd33b273b4eb0579ba | J44: 508ae7e20301df57da0045b13bc7ed9eb0b67ead | K44: 508ae7e20301df57da0045b13bc7ed9eb0b67ead | L44: RELEASED / SCOPED DELIVERY COMPLETE / REVIEW PENDING | M44: Completion receipt https://drive.google.com/file/d/16PwO6fzkcwv_DhErSWh148SP55PHP2ZI/view?usp=drivesdk; 12248 bytes; raw readback verified. PR3 draft and unmerged. Both GitHub CI runs succeeded; 21 checks and1712 tests pass,1 existing skip. 4112 stored source identities,758 folder records,54 explicit holds,zero unresolved scoped sources. Review RV-HG-ENVELOPE-20260919-v1 remains unreviewed; independence credit0; no scientific promotion. Original work order remains closed. | N44: RESEARCH / OPS
A45: ec44b6ae-f975-47b0-9bf0-6d3380d468cf | B45: 2026-09-20T00:49:08.132760+00:00 | C45: 01a0bbb5-2fcb-77f0-b78b-4d220ddd7ab2 | D45: OpenAI / Codex | E45: d6g8k5htny-coder/main:chatgpt/drive-github-hardening-20260919 | F45: CLAIM | G45: ec44b6ae-f975-47b0-9bf0-6d3380d468cf | H45: 2026-09-20T02:49:08.132760+00:00 | I45: 22ccc07b8bcc3e17e48cb08a4956936fd4876ed3414f6bbd33b273b4eb0579ba | J45: 508ae7e20301df57da0045b13bc7ed9eb0b67ead | K45: Reconcile current accessible research Drive membership and source drift; use verified conversation context to improve provenance architecture and advance exact mathematics. | L45: ACTIVE | M45: Owner continuation via originating task: verify all eligible research transfers, recover conversation context, improve architecture and mathematics. Preserve DO_NOT_OPEN/personal holds, frozen sources, prior release, closed work order, Claude work and scientific review states. No merge or unattended execution. | N45: RESEARCH / OPS
A46: 62f8a117-521a-4ae3-991f-ef14980056eb | B46: 2026-09-20T01:39:25.155338+00:00 | C46: 01a0bbb5-2fcb-77f0-b78b-4d220ddd7ab2 | D46: OpenAI / Codex | E46: d6g8k5htny-coder/main:chatgpt/drive-github-hardening-20260919 | F46: PUBLISH | G46: ec44b6ae-f975-47b0-9bf0-6d3380d468cf | H46: 2026-09-20T02:49:08.132760+00:00 | I46: f5f6c2750ef378980a16e2234dc64a25001a13ef1f9f14a8f8683ef2a696fdf7 | J46: 508ae7e20301df57da0045b13bc7ed9eb0b67ead | K46: e1c5b8054982decd28ca3c5619ca22c7ad431aba | https://drive.google.com/file/d/1AecWn9CJF_V6YeZtTcPrN_dtDc5QIblO/view | L46: PUBLISHED DRAFT / REMOTE CI RUNNING | M46: 4116 stored file identities,758 folder records,54 holds.24 checks and1796 tests pass,1 skip.1930 single-tab Docs;308 Sheets tabs and14338 native formulas preserved. No scientific promotion; synthetic evaluation overlap disclosed. | N46: RESEARCH / OPS
A47: 081264b8-8adb-4944-a1ed-1a0fc8c6708c | B47: 2026-09-20T01:39:25.155338+00:00 | C47: 01a0bbb5-2fcb-77f0-b78b-4d220ddd7ab2 | D47: OpenAI / Codex | E47: RN-AFFINE-MOMENTS-20260920-v1 | F47: REVIEW_REQUEST | G47: ec44b6ae-f975-47b0-9bf0-6d3380d468cf | H47: 2026-09-20T02:49:08.132760+00:00 | I47: 4c1803f23e5bbb02baf0a5f5dec6bd4c00d5c580fdffce05180619e7d9158520 | K47: RV-RN-AFFINE-MOMENTS-20260920-v1 | https://drive.google.com/file/d/1RXhWblyRQYpadj6X7e3IZTmNO4JXXgo3/view | L47: READY FOR TECHNICAL REVIEW / UNREVIEWED | M47: Exact7394-byte candidate proof; derive Stein and trace identities, Bernstein inclusion and common-law applicability. Field identification and spatial cover remain unestablished; zero independence. | N47: MATH
A48: 9ac0e09f-3ba6-4a9e-ae5c-2c94f6f5706a | B48: 2026-09-20T01:48:47.482963+00:00 | C48: 01a0bbb5-2fcb-77f0-b78b-4d220ddd7ab2 | D48: OpenAI / Codex | E48: d6g8k5htny-coder/main:chatgpt/drive-github-hardening-20260919 | F48: RELEASE | G48: ec44b6ae-f975-47b0-9bf0-6d3380d468cf | I48: 263004b050baebe93f45a4c37713465ecf5ceeb266169c2dc86df3fac89482e5 | J48: e1c5b8054982decd28ca3c5619ca22c7ad431aba | K48: e1c5b8054982decd28ca3c5619ca22c7ad431aba | L48: RELEASED / SCOPED DELIVERY COMPLETE / REVIEW PENDING | M48: Completion receipt https://drive.google.com/file/d/1Ektz5a0wJIHQXq5ao96tGX_2G5M4EeBp/view; 26362 bytes; raw readback verified. PR3 draft,unmerged; both GitHub CI runs successful.24 checks and1796 tests pass,1 existing skip.4116 stored research file identities,758 folders,54 holds. Native tabs/formulas preserved with limits; synthetic evaluation overlap disclosed. RN candidate remains unreviewed; independence0; no scientific status change. | N48: RESEARCH / OPS
A49: 16c81fca-fc4e-4c55-969c-265c41f43754 | B49: 2026-09-20T02:02:25.069065+00:00 | C49: 01a0bbb5-2fcb-77f0-b78b-4d220ddd7ab2 | D49: OpenAI / Codex | E49: d6g8k5htny-coder/main:chatgpt/drive-github-hardening-20260919 | F49: CLAIM | G49: 16c81fca-fc4e-4c55-969c-265c41f43754 | H49: 2026-09-20T04:02:25.069065+00:00 | I49: 263004b050baebe93f45a4c37713465ecf5ceeb266169c2dc86df3fac89482e5 | J49: e1c5b8054982decd28ca3c5619ca22c7ad431aba | K49: Optimize reconciled keyword/SHA retrieval and additive Drive navigation; extend exact Gaussian moment bounds to uncertain affine mean/covariance families. | L49: ACTIVE | M49: Owner continuation via originating task. Preserve source identities, archive occurrences, holds, frozen bytes, and historical registers. Mathematical candidate only; zero independence, no field identification or spatial-cover promotion. No merge or unattended deployment. | N49: RESEARCH / OPS
A50: fd39789b-2333-4478-990e-094451beab75 | B50: 2026-09-20T02:39:50.562453+00:00 | C50: 01a0bbb5-2fcb-77f0-b78b-4d220ddd7ab2 | D50: OpenAI / Codex | E50: d6g8k5htny-coder/main:chatgpt/drive-github-hardening-20260919 | F50: PUBLISH | G50: 16c81fca-fc4e-4c55-969c-265c41f43754 | H50: 2026-09-20T04:02:25.069065+00:00 | I50: d4ed487898810db8db1cd02e1ce339afb1b34bddc1f28f39235ebbf9e0ea3e2a | J50: e1c5b8054982decd28ca3c5619ca22c7ad431aba | K50: d01b69f255243d077a8e9e4bf8706021782a78e6 | https://drive.google.com/file/d/1Fs2boHnKAmdXHENcu5DZIaDNqyQNpRYC/view | L50: PUBLISHED DRAFT / REMOTE CI RUNNING | M50: Active packages2944payloads verified; 4934search identities,11649archiveoccurrences,3140eligible texts.24checks and1850tests pass,1skip. Navigator values/links verified. No status promotion. | N50: RESEARCH / OPS
A51: 9846a9d5-f13f-4462-99aa-af863372821f | B51: 2026-09-20T02:39:50.562453+00:00 | C51: 01a0bbb5-2fcb-77f0-b78b-4d220ddd7ab2 | D51: OpenAI / Codex | E51: RN-INTERVAL-FAMILIES-20260920-v1 | F51: REVIEW_REQUEST | G51: 16c81fca-fc4e-4c55-969c-265c41f43754 | H51: 2026-09-20T04:02:25.069065+00:00 | I51: 0b53ae366eae2b603811f4eb02b09fa44abc220be442419a6801c6349d53adff | K51: RV-RN-INTERVAL-FAMILIES-20260920-v1 | https://drive.google.com/file/d/1r5_R5VoKM10-7eofPwGa_yHuxTAS7S2q/view | L51: READY FOR TECHNICAL REVIEW / UNREVIEWED | M51: Exact8330-byte candidate proof. Check PSD quantifiers, uncertain parameter inclusion, singleton recovery and complete mark subdivision. Actual field and spatial cover unestablished; independence0. | N51: MATH
A52: 021275d7-2db2-4331-b0e0-d6311e2f5246 | B52: 2026-09-20T02:50:30.707969+00:00 | C52: 01a0bbb5-2fcb-77f0-b78b-4d220ddd7ab2 | D52: OpenAI / Codex | E52: d6g8k5htny-coder/main:chatgpt/drive-github-hardening-20260919 | F52: RELEASE | G52: 16c81fca-fc4e-4c55-969c-265c41f43754 | I52: 7f373636356366738e37ef3e9e3600796dcaa38eee7d3e737cbade7b37aa4d51 | J52: d01b69f255243d077a8e9e4bf8706021782a78e6 | K52: https://drive.google.com/file/d/1gnHPYuwCqn4GYzue6t1l4o9QQfJa_2W_/view | L52: COMPLETE / CLAIM RELEASED | M52: Scoped delivery complete:24checkers,1850tests pass,1skip;push and PR CI success. Native registration and final receipt bytes verified. RN interval-family candidate remains unreviewed;0 independence. No whole-account/native-history completion or scientific promotion. | N52: RESEARCH / OPS
A53: 48088df3-428b-4417-9df5-f2b2cff26e96 | B53: 2026-09-20T03:07:19.411898+00:00 | C53: 01a0bbb5-2fcb-77f0-b78b-4d220ddd7ab2 | D53: OpenAI / Codex | E53: d6g8k5htny-coder/main:chatgpt/drive-github-hardening-20260919 | F53: CLAIM | G53: 48088df3-428b-4417-9df5-f2b2cff26e96 | H53: 2026-09-20T05:07:19.411898+00:00 | I53: 7f373636356366738e37ef3e9e3600796dcaa38eee7d3e737cbade7b37aa4d51 | J53: d01b69f255243d077a8e9e4bf8706021782a78e6 | K53: Implement assessed Gemini/DeepSeek recommendations: exact RN certificates and replay, typed diagnostics, derived refusal/dependency checkpoints and unified verification runner. | L53: ACTIVE | M53: Dylan Roy explicitly authorized worthy implementation without consultation in current task. Bounded candidate work; preserve frozen sources, canonical statuses and single Drive disposition authority. Same-provider coauthors earn zero independence. | N53: RESEARCH / OPS
A54: 7b607ff6-c0e2-4176-88df-794df8983d3a | B54: 2026-09-20T03:49:26.405969+00:00 | C54: 01a0bbb5-2fcb-77f0-b78b-4d220ddd7ab2 | D54: OpenAI / Codex | E54: d6g8k5htny-coder/main:chatgpt/drive-github-hardening-20260919 | F54: PUBLISH | G54: 48088df3-428b-4417-9df5-f2b2cff26e96 | H54: 2026-09-20T05:07:19.411898+00:00 | I54: 0785808db27c5fc736ea8330cb9fdb7e65add2e373cdbb8fe1cc4a596bda69f6 | J54: d01b69f255243d077a8e9e4bf8706021782a78e6 | K54: 86f15bac6c865b28f9254a6012bc4674af5cd773 | https://drive.google.com/file/d/1_CqyUpbGOmjw5-ntVzZa1TgB41-G3a_b/view | L54: PUBLISHED DRAFT / VALIDATION RECORDED | M54: 29 explicit steps; 2074 tests passed, 1 existing skip. LPW original 39 checks normal/optimized plus oversized-headline rejection. Lean 13 recovered declarations compiled; two false statements rejected. Closure plan preserves 305 records and all scientific statuses. | N54: RESEARCH / OPS
A55: 8977c995-bda6-4cf0-9ec3-48eda0b9bc10 | B55: 2026-09-20T03:49:26.405969+00:00 | C55: 01a0bbb5-2fcb-77f0-b78b-4d220ddd7ab2 | D55: OpenAI / Codex | E55: RESEARCH-EXECUTION-CERTIFICATES-20260920-v1 | F55: REVIEW_REQUEST | G55: 48088df3-428b-4417-9df5-f2b2cff26e96 | H55: 2026-09-20T05:07:19.411898+00:00 | I55: dc84d820053832437577dfc4a5254031fb58eef521b59f36ad10f77c024e7465 | K55: RV-RESEARCH-EXECUTION-CERTIFICATES-20260920-v1 | https://drive.google.com/file/d/1NmwwIUUfIgVepvWjjSaPtLisJar7dpJu/view | L55: READY FOR TECHNICAL REVIEW / UNREVIEWED | M55: Frozen scoped mathematical candidate and reproduced build evidence. No field identification, global theorem closure or independent review credit. | N55: MATH
A56: f8764501-defd-4186-b5a8-061ab3360b2d | B56: 2026-09-20T03:59:07.973682+00:00 | C56: 01a0bbb5-2fcb-77f0-b78b-4d220ddd7ab2 | D56: OpenAI / Codex | E56: d6g8k5htny-coder/main:chatgpt/drive-github-hardening-20260919 | F56: RELEASE | G56: 48088df3-428b-4417-9df5-f2b2cff26e96 | I56: 9ae8802e880a871cde0a95f2e83896c57043e4e76119e3509af2a87328a86012 | J56: 86f15bac6c865b28f9254a6012bc4674af5cd773 | K56: https://drive.google.com/file/d/1_12fnTDwumrlVDKvruriOnKxAfFawE1C/view | L56: COMPLETE / CLAIM RELEASED | M56: Scoped implementation complete: 29 checks, 2074 tests passed, 1 existing skip; push and PR CI successful. Exact RN/LPW candidates and Lean algebra build evidence registered. Scientific review remains open; no status promotion or independence credit. | N56: RESEARCH / OPS
A57: 017d6f4e-4c74-48f2-965a-6d0af2aad307 | B57: 2026-09-20T04:07:27.512865+00:00 | C57: 01a0bbb5-2fcb-77f0-b78b-4d220ddd7ab2 | D57: OpenAI / Codex | E57: d6g8k5htny-coder/main:chatgpt/drive-github-hardening-20260919 | F57: CLAIM | G57: 017d6f4e-4c74-48f2-965a-6d0af2aad307 | H57: 2026-09-20T06:07:27.512865+00:00 | I57: 9ae8802e880a871cde0a95f2e83896c57043e4e76119e3509af2a87328a86012 | J57: 86f15bac6c865b28f9254a6012bc4674af5cd773 | K57: Advance source-grounded RN conditioning / Gaussian field-input mathematics with exact interval checks and adversarial controls; preserve independent review boundaries. | L57: ACTIVE | M57: User authorized continued mathematical implementation. New scope follows completed execution-certificate delivery; prior overdue routes require external organizational review or exact reconciliation, not duplicate self-review. No canonical status changes. | N57: MATH / RESEARCH
A58: 30d4cbc3-2fa9-45d9-ab24-414d62ceaccb | B58: 2026-09-20T04:29:09.031711+00:00 | C58: 01a0bbb5-2fcb-77f0-b78b-4d220ddd7ab2 | D58: OpenAI / Codex | E58: d6g8k5htny-coder/main:chatgpt/drive-github-hardening-20260919 | F58: PUBLISH | G58: 017d6f4e-4c74-48f2-965a-6d0af2aad307 | H58: 2026-09-20T06:07:27.512865+00:00 | I58: 08ac95ff7ca35297da779f5f4e336f7aabd2c6f0ef797d0ae819a896fb8e3e23 | J58: 86f15bac6c865b28f9254a6012bc4674af5cd773 | K58: df0d6c4314bc78e71752f74075e69751484a9a32 | https://drive.google.com/file/d/1kUE2_5vPnIi-SuYzvVSrnBmGxbaI_4jW/view | L58: PRIVATE GITHUB / DRIVE CANDIDATE PUBLISHED | M58: 30 checks, 2178 tests passed, 1 existing skip; 503 scoped review checks; zero independence. Published exact prepared tree in private draft PR #3; remote CI status recorded separately. | N58: MATH / RESEARCH
A59: b43e1c4a-3fbf-4984-8543-121bea484baa | B59: 2026-09-20T04:29:09.031711+00:00 | C59: 01a0bbb5-2fcb-77f0-b78b-4d220ddd7ab2 | D59: OpenAI / Codex | E59: RN-SIDE24-POINT-LAW-20260920-v1 | F59: REVIEW_REQUEST | G59: 017d6f4e-4c74-48f2-965a-6d0af2aad307 | H59: 2026-09-20T06:07:27.512865+00:00 | I59: d953aa0ee6aa08ee178ad21a4c01caeb307ede5d97b14b3b1b282e4d214f5753 | K59: RV-RN-SIDE24-POINT-LAW-20260920-v1 | https://drive.google.com/file/d/1nzc7GJeAR06L03c6y8Kf958VHU4n-mJ_/view | L59: READY FOR SCIENTIFIC REVIEW | M59: Actual source point law and exact conditional factor; scoped code checks recorded; no independent acceptance or scientific promotion. | N59: MATH
A60: 925ed2c1-d1af-42ba-a8d3-f9eca99015ad | B60: 2026-09-20T04:36:22.758769+00:00 | C60: 01a0bbb5-2fcb-77f0-b78b-4d220ddd7ab2 | D60: OpenAI / Codex | E60: d6g8k5htny-coder/main:chatgpt/drive-github-hardening-20260919 | F60: RELEASE | G60: 017d6f4e-4c74-48f2-965a-6d0af2aad307 | I60: e18a91c84e896572b29e9bbca1523763b728ddbe047fc4e1576255052f8703a5 | J60: df0d6c4314bc78e71752f74075e69751484a9a32 | K60: https://drive.google.com/file/d/1MyI98fBTOPNAY1Y3-cs8y8HFEMjlU5-b/view | L60: COMPLETE / CLAIM RELEASED | M60: Scoped SIDE24 point-law delivery complete: 30 checks,2178 tests passed,1 existing skip; push and PR CI successful. Private GitHub and Drive exact bytes verified. Conditional determinant factor <=0.007322236 at y=(1,1), full mark interval. Spatial/density/H3/independent review remain open; no promotion. | N60: RESEARCH / OPS
A61: ca18842b-b2e8-47ee-8c4f-932a585e9b46 | B61: 2026-09-20T04:45:40.023Z | C61: 01a0bbb5-2fcb-77f0-b78b-4d220ddd7ab2 | D61: OpenAI / Codex | E61: d6g8k5htny-coder/main:chatgpt/drive-github-hardening-20260919 | F61: CLAIM | G61: ca18842b-b2e8-47ee-8c4f-932a585e9b46 | H61: 2026-09-20T06:45:40.023Z | I61: e18a91c84e896572b29e9bbca1523763b728ddbe047fc4e1576255052f8703a5 | J61: df0d6c4314bc78e71752f74075e69751484a9a32 | K61: Advance source-bound SIDE24 density/window integrand; automate bounded research continuation and optimize verified delivery. | L61: ACTIVE | M61: Direct user authorization; coordinating task confirms no overlap. Prior claim released. Preserve private repository, exact scientific predicates, and independent-review boundaries. | N61: MATH / RESEARCH / OPS
A62: 50f42def-ac43-4df5-9f16-cc56f3c0f67a | B62: 2026-09-20T05:00:48.931972+00:00 | C62: 01a0bbb5-2fcb-77f0-b78b-4d220ddd7ab2 | D62: OpenAI / Codex | E62: d6g8k5htny-coder/main:chatgpt/drive-github-hardening-20260919 | F62: PUBLISH | G62: ca18842b-b2e8-47ee-8c4f-932a585e9b46 | H62: 2026-09-20T06:45:40.023Z | I62: d4e2bdbcd21549f840941c1d0a7f0c2f8988e23140e4e517cbe57437010f20a1 | J62: df0d6c4314bc78e71752f74075e69751484a9a32 | K62: c7219af926d4d7ef5beb421cc78c21f850752dfb | https://drive.google.com/file/d/1dW1sxaK8MkpeSHwNwAPw-acXDbM_GXGY/view | L62: PRIVATE GITHUB / DRIVE CANDIDATE PUBLISHED | M62: 31 checks, 2227 tests passed, 1 existing skip; 37 technical audit checks and 7 rejected report mutations; zero independence. Hourly continuation active; exact prepared tree in private draft PR #3; remote CI recorded separately. | N62: MATH / RESEARCH / OPS
A63: bc56a58d-0de5-4298-b801-0c3b9fa1388c | B63: 2026-09-20T05:00:48.931972+00:00 | C63: 01a0bbb5-2fcb-77f0-b78b-4d220ddd7ab2 | D63: OpenAI / Codex | E63: RN-SIDE24-DENSITY-WINDOW-20260920-v1 | F63: REVIEW_REQUEST | G63: ca18842b-b2e8-47ee-8c4f-932a585e9b46 | H63: 2026-09-20T06:45:40.023Z | I63: c53bf5989aceb258f28aeabb4ff8f4359a968094916929e06552185be2146310 | K63: RV-RN-SIDE24-DENSITY-WINDOW-20260920-v1 | https://drive.google.com/file/d/1BP6EjmOeezUlH3aLID4N2Qc-wun5RR8C/view | L63: READY FOR SCIENTIFIC REVIEW | M63: Exact density/window numerator and H3-conditional point bound; source-exposed code checks only, no independent acceptance or scientific promotion. | N63: MATH
A64: dc9f621e-e393-4859-9f9d-faee7e2536f3 | B64: 2026-09-20T05:10:20.233417+00:00 | C64: 01a0bbb5-2fcb-77f0-b78b-4d220ddd7ab2 | D64: OpenAI / Codex | E64: d6g8k5htny-coder/main:chatgpt/drive-github-hardening-20260919 | F64: RELEASE | G64: ca18842b-b2e8-47ee-8c4f-932a585e9b46 | I64: 9e450be3f7dee67a90fdd443dbe83a30f9b0aecd831848f3cadeda71170abd87 | J64: c7219af926d4d7ef5beb421cc78c21f850752dfb | K64: https://drive.google.com/file/d/12FM0uPr-Xn8HD2oO1QpNQuTSzdP3Fwi1/view | L64: COMPLETE / CLAIM RELEASED | M64: Scoped density/window delivery complete: 31 checks,2227 tests passed,1 existing skip; push and PR CI successful. Private GitHub and Drive bytes verified. RN point integrand <=0.000003776086 conditional on imported H3 floor. Hourly continuation active; spatial cover,H3 replay,independent acceptance remain open; no promotion. | N64: RESEARCH / OPS
A65: 6a4bc752-5571-4ff0-9fa2-e39b0672d424 | B65: 2026-09-20T05:16:59.126Z | C65: 01a0bbb5-2fcb-77f0-b78b-4d220ddd7ab2 | D65: OpenAI / Codex | E65: d6g8k5htny-coder/main:chatgpt/drive-github-hardening-20260919 | F65: CLAIM | G65: 6a4bc752-5571-4ff0-9fa2-e39b0672d424 | H65: 2026-09-20T07:16:59.126Z | I65: 9e450be3f7dee67a90fdd443dbe83a30f9b0aecd831848f3cadeda71170abd87 | J65: c7219af926d4d7ef5beb421cc78c21f850752dfb | K65: Continue mathematical closure: source-bound spatial RN cell enclosure and verified upper-sum cover with honest inconclusive-cell refinement. | L65: ACTIVE | M65: Direct user request. Prior delivery and claim released. Preserve private visibility, imported H3 hypothesis, complete spatial/mark quantifiers, and exact scientific acceptance predicates. | N65: MATH / RESEARCH
A66: 15219ecb-5b2e-4f44-9d58-d349cd244866 | B66: 2026-09-20T05:19:35.348846+00:00 | C66: 01a0bbae-d37c-7601-b1e6-f969a7dc10d6 | D66: OpenAI / Codex | E66: PARALLEL-H3-RUNG-FLOOR-20260920-v1 | F66: CLAIM | G66: 15219ecb-5b2e-4f44-9d58-d349cd244866 | H66: 2026-09-20T07:19:35.348846+00:00 | I66: 6347275d86c56842b719b36180e535bc1793d6995ddb68464db2960820440dfa | J66: c7219af926d4d7ef5beb421cc78c21f850752dfb | K66: Exact fixed-r H3 floor reconstruction from normalized covariance, type-safe box, and truncated Gaussian integral. | L66: ACTIVE | M66: User explicitly authorized parallel agents. Distinct mathematical target; scratch outputs only, existing task remains sole repository writer. Source-exposed coauthor work, zero independence; no scientific status promotion. | N66: MATH / PARALLEL RESEARCH
A67: f9be87ff-51ff-4c49-961a-dfd821b8b410 | B67: 2026-09-20T05:19:35.348846+00:00 | C67: 01a0bbae-d37c-7601-b1e6-f969a7dc10d6 | D67: OpenAI / Codex | E67: PARALLEL-LPW-TAIL-PROFILE-20260920-v1 | F67: CLAIM | G67: f9be87ff-51ff-4c49-961a-dfd821b8b410 | H67: 2026-09-20T07:19:35.348846+00:00 | I67: 840c75a7825c67b8d99a536394beb18976475fe9bd0e474ed5f80c375004ec81 | J67: c7219af926d4d7ef5beb421cc78c21f850752dfb | K67: Reconstruct full spectral tails and sharpen the source profile modulus using exact g5 integral derivative bounds. | L67: ACTIVE | M67: User explicitly authorized parallel agents. Distinct mathematical target; scratch outputs only, existing task remains sole repository writer. Source-exposed coauthor work, zero independence; no scientific status promotion. | N67: MATH / PARALLEL RESEARCH
A68: 4fa1fee4-fcb4-4a53-b337-4c88ab80302c | B68: 2026-09-20T05:19:35.348846+00:00 | C68: 01a0bbae-d37c-7601-b1e6-f969a7dc10d6 | D68: OpenAI / Codex | E68: PARALLEL-H5-C2-BAND-20260920-v1 | F68: CLAIM | G68: 4fa1fee4-fcb4-4a53-b337-4c88ab80302c | H68: 2026-09-20T07:19:35.348846+00:00 | I68: 7258c84a7720704e577f341252aa809888735d9f8ace1674429e004da6c6172a | J68: c7219af926d4d7ef5beb421cc78c21f850752dfb | K68: Bind one source-defined normalized c2 jet and six-pin geometry; derive cancellation-free whole-band enclosure with full lattice tails. | L68: ACTIVE | M68: User explicitly authorized parallel agents. Distinct mathematical target; scratch outputs only, existing task remains sole repository writer. Source-exposed coauthor work, zero independence; no scientific status promotion. | N68: MATH / PARALLEL RESEARCH
A69: 4a51a4bd-79a9-45dd-a1ad-77206c2a9c5c | B69: 2026-09-20T05:31:44.838636+00:00 | C69: 01a0bbae-d37c-7601-b1e6-f969a7dc10d6 | D69: OpenAI / Codex | E69: PARALLEL-H3-RUNG-FLOOR-20260920-v1 | F69: RELEASE | G69: 15219ecb-5b2e-4f44-9d58-d349cd244866 | I69: 9828fd8ff40394b1d1451bc2e6e1a47b8f2ed85f4557e3a717bc7802218373f6 | J69: c7219af926d4d7ef5beb421cc78c21f850752dfb | K69: /Users/dylanroy/Documents/Codex/2026-09-19/realtime-voice-chat/work/parallel-math-20260920/PARALLEL_MATH_CANDIDATES_20260920_v1.zip | L69: COMPLETE LOCAL HANDOFF / CLAIM RELEASED | M69: Three exact mathematical candidates passed parallel replay, input hashes stable, scoped negative controls retained. Sole writer task01a0bbb5-2fcb-77f0-b78b-4d220ddd7ab2 claim6a4bc752-5571-4ff0-9fa2-e39b0672d424 explicitly accepted integration/private publication ownership. This is local handoff, not remote publication or scientific closure. Zero organizational independence. | N69: MATH / PARALLEL RESEARCH
A70: cad4b821-9be0-41a6-a6ab-d09d5ab90ccb | B70: 2026-09-20T05:31:44.838636+00:00 | C70: 01a0bbae-d37c-7601-b1e6-f969a7dc10d6 | D70: OpenAI / Codex | E70: PARALLEL-LPW-TAIL-PROFILE-20260920-v1 | F70: RELEASE | G70: f9be87ff-51ff-4c49-961a-dfd821b8b410 | I70: 9828fd8ff40394b1d1451bc2e6e1a47b8f2ed85f4557e3a717bc7802218373f6 | J70: c7219af926d4d7ef5beb421cc78c21f850752dfb | K70: /Users/dylanroy/Documents/Codex/2026-09-19/realtime-voice-chat/work/parallel-math-20260920/PARALLEL_MATH_CANDIDATES_20260920_v1.zip | L70: COMPLETE LOCAL HANDOFF / CLAIM RELEASED | M70: Three exact mathematical candidates passed parallel replay, input hashes stable, scoped negative controls retained. Sole writer task01a0bbb5-2fcb-77f0-b78b-4d220ddd7ab2 claim6a4bc752-5571-4ff0-9fa2-e39b0672d424 explicitly accepted integration/private publication ownership. This is local handoff, not remote publication or scientific closure. Zero organizational independence. | N70: MATH / PARALLEL RESEARCH
A71: 9ff5bcb7-1705-4e46-bd5e-c06f5665fbdf | B71: 2026-09-20T05:31:44.838636+00:00 | C71: 01a0bbae-d37c-7601-b1e6-f969a7dc10d6 | D71: OpenAI / Codex | E71: PARALLEL-H5-C2-BAND-20260920-v1 | F71: RELEASE | G71: 4fa1fee4-fcb4-4a53-b337-4c88ab80302c | I71: 9828fd8ff40394b1d1451bc2e6e1a47b8f2ed85f4557e3a717bc7802218373f6 | J71: c7219af926d4d7ef5beb421cc78c21f850752dfb | K71: /Users/dylanroy/Documents/Codex/2026-09-19/realtime-voice-chat/work/parallel-math-20260920/PARALLEL_MATH_CANDIDATES_20260920_v1.zip | L71: COMPLETE LOCAL HANDOFF / CLAIM RELEASED | M71: Three exact mathematical candidates passed parallel replay, input hashes stable, scoped negative controls retained. Sole writer task01a0bbb5-2fcb-77f0-b78b-4d220ddd7ab2 claim6a4bc752-5571-4ff0-9fa2-e39b0672d424 explicitly accepted integration/private publication ownership. This is local handoff, not remote publication or scientific closure. Zero organizational independence. | N71: MATH / PARALLEL RESEARCH
A72: 279870b8-89e6-406d-a150-f655dc2c1ff6 | B72: 2026-09-20T05:35:30.577470+00:00 | C72: 01a0bbae-d37c-7601-b1e6-f969a7dc10d6 | D72: OpenAI / Codex | E72: Q0-P12-H3-UNIFORM-20260920-v1 | F72: CLAIM | G72: 279870b8-89e6-406d-a150-f655dc2c1ff6 | H72: 2026-09-20T07:35:30.577470+00:00 | I72: 8f404f87e44d2861770eb86deed79710be3bc072aebeaff74d232304670dfb4d | J72: c7219af926d4d7ef5beb421cc78c21f850752dfb | K72: Derive a cancellation-preserving uniform small-r H3 covariance/whitening route and certify a nontrivial parameter band or exact limiting positivity lemma. | L72: ACTIVE / DISTINCT PROJECT | M72: User explicitly requests10+ parallel agents. Twelve nonoverlapping bounded mathematical projects, executed in waves of3 because session concurrency is4 including root. Routing hash is current OPEN_PROBLEMS.md only; each output separately binds mathematical sources. Scratch authoring only; sole repo writer unchanged; no scientific promotion or independent-lineage credit. | N72: Q0 / MATH / PARALLEL
A73: b66c025c-7ed6-4f08-90a5-6755bbe1b433 | B73: 2026-09-20T05:35:30.577470+00:00 | C73: 01a0bbae-d37c-7601-b1e6-f969a7dc10d6 | D73: OpenAI / Codex | E73: Q0-P12-H3-CEILING-20260920-v1 | F73: CLAIM | G73: b66c025c-7ed6-4f08-90a5-6755bbe1b433 | H73: 2026-09-20T07:35:30.577470+00:00 | I73: 8f404f87e44d2861770eb86deed79710be3bc072aebeaff74d232304670dfb4d | J73: c7219af926d4d7ef5beb421cc78c21f850752dfb | K73: Reconstruct a source-bound Gaussian quartic upper bound for the H3 normalizer with full tails and explicit uniform-r limitations. | L73: ACTIVE / DISTINCT PROJECT | M73: User explicitly requests10+ parallel agents. Twelve nonoverlapping bounded mathematical projects, executed in waves of3 because session concurrency is4 including root. Routing hash is current OPEN_PROBLEMS.md only; each output separately binds mathematical sources. Scratch authoring only; sole repo writer unchanged; no scientific promotion or independent-lineage credit. | N73: Q0 / MATH / PARALLEL
A74: b6eda859-17ee-401f-931f-9ae174c62aa0 | B74: 2026-09-20T05:35:30.577470+00:00 | C74: 01a0bbae-d37c-7601-b1e6-f969a7dc10d6 | D74: OpenAI / Codex | E74: Q0-P12-LPW-AMPLITUDE-20260920-v1 | F74: CLAIM | G74: b6eda859-17ee-401f-931f-9ae174c62aa0 | H74: 2026-09-20T07:35:30.577470+00:00 | I74: 8f404f87e44d2861770eb86deed79710be3bc072aebeaff74d232304670dfb4d | J74: c7219af926d4d7ef5beb421cc78c21f850752dfb | K74: Reprove the R05 amplitude-to-field norm lemma and full two-dimensional amplitude sums/tails with exact interval bounds. | L74: ACTIVE / DISTINCT PROJECT | M74: User explicitly requests10+ parallel agents. Twelve nonoverlapping bounded mathematical projects, executed in waves of3 because session concurrency is4 including root. Routing hash is current OPEN_PROBLEMS.md only; each output separately binds mathematical sources. Scratch authoring only; sole repo writer unchanged; no scientific promotion or independent-lineage credit. | N74: Q0 / MATH / PARALLEL
A75: d82842d4-3422-4dee-aceb-47b8989f6a63 | B75: 2026-09-20T05:35:30.577470+00:00 | C75: 01a0bbae-d37c-7601-b1e6-f969a7dc10d6 | D75: OpenAI / Codex | E75: Q0-P12-JET-DEFINITION-20260920-v1 | F75: CLAIM | G75: d82842d4-3422-4dee-aceb-47b8989f6a63 | H75: 2026-09-20T07:35:30.577470+00:00 | I75: 8f404f87e44d2861770eb86deed79710be3bc072aebeaff74d232304670dfb4d | J75: c7219af926d4d7ef5beb421cc78c21f850752dfb | K75: Recover the full source-defined 24-jet set, powers and six-pin geometry; derive one additional certified jet family or report exact missing definitions. | L75: ACTIVE / DISTINCT PROJECT | M75: User explicitly requests10+ parallel agents. Twelve nonoverlapping bounded mathematical projects, executed in waves of3 because session concurrency is4 including root. Routing hash is current OPEN_PROBLEMS.md only; each output separately binds mathematical sources. Scratch authoring only; sole repo writer unchanged; no scientific promotion or independent-lineage credit. | N75: Q0 / MATH / PARALLEL
A76: 60663b69-45c3-431d-b27c-33c13695d2d7 | B76: 2026-09-20T05:35:30.577470+00:00 | C76: 01a0bbae-d37c-7601-b1e6-f969a7dc10d6 | D76: OpenAI / Codex | E76: Q0-P12-LPW-HEADLINE-20260920-v1 | F76: CLAIM | G76: 60663b69-45c3-431d-b27c-33c13695d2d7 | H76: 2026-09-20T07:35:30.577470+00:00 | I76: 8f404f87e44d2861770eb86deed79710be3bc072aebeaff74d232304670dfb4d | J76: c7219af926d4d7ef5beb421cc78c21f850752dfb | K76: Reconstruct the conditional density/norm/constant dependency chain and test the repaired exact headline, keeping endpoint assumptions explicit. | L76: ACTIVE / DISTINCT PROJECT | M76: User explicitly requests10+ parallel agents. Twelve nonoverlapping bounded mathematical projects, executed in waves of3 because session concurrency is4 including root. Routing hash is current OPEN_PROBLEMS.md only; each output separately binds mathematical sources. Scratch authoring only; sole repo writer unchanged; no scientific promotion or independent-lineage credit. | N76: Q0 / MATH / PARALLEL
A77: b3f29a58-9793-4eb5-bca3-f3ad5411ca53 | B77: 2026-09-20T05:35:30.577470+00:00 | C77: 01a0bbae-d37c-7601-b1e6-f969a7dc10d6 | D77: OpenAI / Codex | E77: Q0-P12-TB-MULTIPLICITY-20260920-v1 | F77: CLAIM | G77: b3f29a58-9793-4eb5-bca3-f3ad5411ca53 | H77: 2026-09-20T07:35:30.577470+00:00 | I77: 8f404f87e44d2861770eb86deed79710be3bc072aebeaff74d232304670dfb4d | J77: c7219af926d4d7ef5beb421cc78c21f850752dfb | K77: Derive a source-bound candidate-process counting identity and precise multiplicity condition needed to identify the persistence pushforward. | L77: ACTIVE / DISTINCT PROJECT | M77: User explicitly requests10+ parallel agents. Twelve nonoverlapping bounded mathematical projects, executed in waves of3 because session concurrency is4 including root. Routing hash is current OPEN_PROBLEMS.md only; each output separately binds mathematical sources. Scratch authoring only; sole repo writer unchanged; no scientific promotion or independent-lineage credit. | N77: Q0 / MATH / PARALLEL
A78: 3457ae5b-a4b1-4eec-9a2c-926060e2e192 | B78: 2026-09-20T05:35:30.577470+00:00 | C78: 01a0bbae-d37c-7601-b1e6-f969a7dc10d6 | D78: OpenAI / Codex | E78: Q0-P12-TB-CONTACT-20260920-v1 | F78: CLAIM | G78: 3457ae5b-a4b1-4eec-9a2c-926060e2e192 | H78: 2026-09-20T07:35:30.577470+00:00 | I78: 8f404f87e44d2861770eb86deed79710be3bc072aebeaff74d232304670dfb4d | J78: c7219af926d4d7ef5beb421cc78c21f850752dfb | K78: Reconstruct the fold contact/coarea change of variables and exact Jacobian; prove a bounded local lemma or give a counterexample to an unjustified step. | L78: ACTIVE / DISTINCT PROJECT | M78: User explicitly requests10+ parallel agents. Twelve nonoverlapping bounded mathematical projects, executed in waves of3 because session concurrency is4 including root. Routing hash is current OPEN_PROBLEMS.md only; each output separately binds mathematical sources. Scratch authoring only; sole repo writer unchanged; no scientific promotion or independent-lineage credit. | N78: Q0 / MATH / PARALLEL
A79: a5a6ff80-e39e-4e0d-9830-75547ab653f0 | B79: 2026-09-20T05:35:30.577470+00:00 | C79: 01a0bbae-d37c-7601-b1e6-f969a7dc10d6 | D79: OpenAI / Codex | E79: Q0-P12-TB-TAILS-20260920-v1 | F79: CLAIM | G79: a5a6ff80-e39e-4e0d-9830-75547ab653f0 | H79: 2026-09-20T07:35:30.577470+00:00 | I79: 8f404f87e44d2861770eb86deed79710be3bc072aebeaff74d232304670dfb4d | J79: c7219af926d4d7ef5beb421cc78c21f850752dfb | K79: Derive a source-bound integrability/dominating tail estimate needed to pass from compact-mark B0 to full kappa; isolate exact unsatisfied model hypotheses. | L79: ACTIVE / DISTINCT PROJECT | M79: User explicitly requests10+ parallel agents. Twelve nonoverlapping bounded mathematical projects, executed in waves of3 because session concurrency is4 including root. Routing hash is current OPEN_PROBLEMS.md only; each output separately binds mathematical sources. Scratch authoring only; sole repo writer unchanged; no scientific promotion or independent-lineage credit. | N79: Q0 / MATH / PARALLEL
A80: 112c496a-8e9a-4e8c-a4de-d910b8d7d8df | B80: 2026-09-20T05:35:30.577470+00:00 | C80: 01a0bbae-d37c-7601-b1e6-f969a7dc10d6 | D80: OpenAI / Codex | E80: Q0-P12-WP-EVENT-20260920-v1 | F80: CLAIM | G80: 112c496a-8e9a-4e8c-a4de-d910b8d7d8df | H80: 2026-09-20T07:35:30.577470+00:00 | I80: 8f404f87e44d2861770eb86deed79710be3bc072aebeaff74d232304670dfb4d | J80: c7219af926d4d7ef5beb421cc78c21f850752dfb | K80: Repair the weighted-Palm Cauchy-Schwarz event/window factor and derive the exact event-level asymptotic target with rigorous controls. | L80: ACTIVE / DISTINCT PROJECT | M80: User explicitly requests10+ parallel agents. Twelve nonoverlapping bounded mathematical projects, executed in waves of3 because session concurrency is4 including root. Routing hash is current OPEN_PROBLEMS.md only; each output separately binds mathematical sources. Scratch authoring only; sole repo writer unchanged; no scientific promotion or independent-lineage credit. | N80: Q0 / MATH / PARALLEL
A81: 2f7c7ce5-5aa6-418d-9a13-00e1cd779306 | B81: 2026-09-20T05:35:30.577470+00:00 | C81: 01a0bbae-d37c-7601-b1e6-f969a7dc10d6 | D81: OpenAI / Codex | E81: Q0-P12-LAMBDA-UNIFORM-20260920-v1 | F81: CLAIM | G81: 2f7c7ce5-5aa6-418d-9a13-00e1cd779306 | H81: 2026-09-20T07:35:30.577470+00:00 | I81: 8f404f87e44d2861770eb86deed79710be3bc072aebeaff74d232304670dfb4d | J81: c7219af926d4d7ef5beb421cc78c21f850752dfb | K81: Attack an analytic H-B3 replacement or source-bound positive uniform Lambda constant without reviving refuted lower theorem assemblies. | L81: ACTIVE / DISTINCT PROJECT | M81: User explicitly requests10+ parallel agents. Twelve nonoverlapping bounded mathematical projects, executed in waves of3 because session concurrency is4 including root. Routing hash is current OPEN_PROBLEMS.md only; each output separately binds mathematical sources. Scratch authoring only; sole repo writer unchanged; no scientific promotion or independent-lineage credit. | N81: Q0 / MATH / PARALLEL
A82: 40e3d67b-4f6f-4f6b-9515-c581afe468e0 | B82: 2026-09-20T05:35:30.577470+00:00 | C82: 01a0bbae-d37c-7601-b1e6-f969a7dc10d6 | D82: OpenAI / Codex | E82: Q0-P12-GAUSSIAN-TUBE-20260920-v1 | F82: CLAIM | G82: 40e3d67b-4f6f-4f6b-9515-c581afe468e0 | H82: 2026-09-20T07:35:30.577470+00:00 | I82: 8f404f87e44d2861770eb86deed79710be3bc072aebeaff74d232304670dfb4d | J82: c7219af926d4d7ef5beb421cc78c21f850752dfb | K82: Derive the Gaussian C1 tube failure bound and required clearance scaling for the source near/moderate-zone gamma premise. | L82: ACTIVE / DISTINCT PROJECT | M82: User explicitly requests10+ parallel agents. Twelve nonoverlapping bounded mathematical projects, executed in waves of3 because session concurrency is4 including root. Routing hash is current OPEN_PROBLEMS.md only; each output separately binds mathematical sources. Scratch authoring only; sole repo writer unchanged; no scientific promotion or independent-lineage credit. | N82: Q0 / MATH / PARALLEL
A83: 5af6055a-c888-4fdd-8852-f5bdc45eabd7 | B83: 2026-09-20T05:35:30.577470+00:00 | C83: 01a0bbae-d37c-7601-b1e6-f969a7dc10d6 | D83: OpenAI / Codex | E83: Q0-P12-BONFERRONI-ETA-20260920-v1 | F83: CLAIM | G83: 5af6055a-c888-4fdd-8852-f5bdc45eabd7 | H83: 2026-09-20T07:35:30.577470+00:00 | I83: 8f404f87e44d2861770eb86deed79710be3bc072aebeaff74d232304670dfb4d | J83: c7219af926d4d7ef5beb421cc78c21f850752dfb | K83: Derive the pair-loss/eta/exit asymptotic rate budget required for a valid lower-event union bound and falsify insufficient rates. | L83: ACTIVE / DISTINCT PROJECT | M83: User explicitly requests10+ parallel agents. Twelve nonoverlapping bounded mathematical projects, executed in waves of3 because session concurrency is4 including root. Routing hash is current OPEN_PROBLEMS.md only; each output separately binds mathematical sources. Scratch authoring only; sole repo writer unchanged; no scientific promotion or independent-lineage credit. | N83: Q0 / MATH / PARALLEL
A84: b31f1fee-7411-4e62-a928-9951491ec022 | B84: 2026-09-20T06:01:06.985303+00:00 | C84: 01a0bbb5-2fcb-77f0-b78b-4d220ddd7ab2 | D84: OpenAI / Codex | E84: d6g8k5htny-coder/main:chatgpt/drive-github-hardening-20260919 | F84: PUBLISH | G84: 6a4bc752-5571-4ff0-9fa2-e39b0672d424 | H84: 2026-09-20T07:16:59.126Z | I84: fdfb4532786c1a4492acc56f1e6fa4684345af4aa7887c79750cd36308502e19 | J84: c7219af926d4d7ef5beb421cc78c21f850752dfb | K84: 07a0a4803f998aff4265abd42dfeaea5252bd3bb | https://drive.google.com/file/d/1QJeeOIqIwMHuBISYbXjazH2pEp579-S0/view | L84: PRIVATE GITHUB / DRIVE CANDIDATE PUBLISHED | M84: 33 checks, 2406 tests passed, 1 existing skip. Cell review91 tests,6375 Decimal diagnostic inclusions; same-provider, independence0. Complete local RN rectangle integral <6e-12; original fixedr H3 floor re-proved; LPW covariance <=1.804r² conditional; one H5 c2 band. No full near annulus/all-r theorem or canonical promotion. | N84: MATH / RESEARCH
A85: f8248ad0-0ee7-4bbe-92d0-19da22c9f4ba | B85: 2026-09-20T06:01:06.985303+00:00 | C85: 01a0bbb5-2fcb-77f0-b78b-4d220ddd7ab2 | D85: OpenAI / Codex | E85: RN-SPATIAL-PARALLEL-MATH-20260920-v1 | F85: REVIEW_REQUEST | G85: 6a4bc752-5571-4ff0-9fa2-e39b0672d424 | H85: 2026-09-20T07:16:59.126Z | I85: 4bd14f065f98afca128c50e7ab83d267f146ca771313a489fe9196f06ed8de33 | K85: RV-RN-SPATIAL-PARALLEL-MATH-20260920-v1 | https://drive.google.com/file/d/13a9tebHQ7URIEE9qtAO499Ju6oLznuyG/view | L85: READY FOR SCIENTIFIC REVIEW | M85: Source-exposed internal technical reviews; no independent acceptance. Complete local RN rectangle integral <6e-12; original fixedr H3 floor re-proved; LPW covariance <=1.804r² conditional; one H5 c2 band. No full near annulus/all-r theorem or canonical promotion. | N85: MATH
A86: f28193a0-0546-4c42-b7a7-2ddac53a00bf | B86: 2026-09-20T06:10:55.320893+00:00 | C86: 01a0bbae-d37c-7601-b1e6-f969a7dc10d6 | D86: OpenAI / Codex | E86: Q0-P12-H3-UNIFORM-20260920-v1 | F86: RELEASE | G86: 279870b8-89e6-406d-a150-f655dc2c1ff6 | I86: a0977a545ad455dcdf33c93eb91e6142fc8c2ac795cbd44cf752ec614064db6d | J86: c7219af926d4d7ef5beb421cc78c21f850752dfb | K86: Q0_TWELVE_PROJECT_CANDIDATES_20260920_v1.zip | SHA256 7a36b7dbaa45b80df9e75a2c063c141440a329c1fb66b85ba828a7fe6517dc8f | L86: AUTHOR CANDIDATE DELIVERED / CLAIM RELEASED | M86: Project 1 h3_uniform. Exact candidate and remaining hypotheses in aggregate allowlist. All 12 fresh checker reports byte-identical; 305 inputs and 24 repo dependencies unchanged; 320 tests per Python mode. Handoff to sole writer for private integration. No canonical status change; organizational independence 0. Source intake incident and exclusions preserved in SOURCE_BOUNDARY.md. | N86: Q0 / MATH / PARALLEL
A87: 42859827-c8e1-4c2f-9929-df9e6fae9888 | B87: 2026-09-20T06:10:55.320893+00:00 | C87: 01a0bbae-d37c-7601-b1e6-f969a7dc10d6 | D87: OpenAI / Codex | E87: Q0-P12-H3-CEILING-20260920-v1 | F87: RELEASE | G87: b66c025c-7ed6-4f08-90a5-6755bbe1b433 | I87: e1e656a1f38de39d2cf5b6c5bad857ebfff575c235ebb2e79a351edb80edd6f0 | J87: c7219af926d4d7ef5beb421cc78c21f850752dfb | K87: Q0_TWELVE_PROJECT_CANDIDATES_20260920_v1.zip | SHA256 7a36b7dbaa45b80df9e75a2c063c141440a329c1fb66b85ba828a7fe6517dc8f | L87: AUTHOR CANDIDATE DELIVERED / CLAIM RELEASED | M87: Project 2 h3_ceiling. Exact candidate and remaining hypotheses in aggregate allowlist. All 12 fresh checker reports byte-identical; 305 inputs and 24 repo dependencies unchanged; 320 tests per Python mode. Handoff to sole writer for private integration. No canonical status change; organizational independence 0. Source intake incident and exclusions preserved in SOURCE_BOUNDARY.md. | N87: Q0 / MATH / PARALLEL
A88: 129bbf1b-81a8-4f54-91bf-d91a4a04f811 | B88: 2026-09-20T06:10:55.320893+00:00 | C88: 01a0bbae-d37c-7601-b1e6-f969a7dc10d6 | D88: OpenAI / Codex | E88: Q0-P12-LPW-AMPLITUDE-20260920-v1 | F88: RELEASE | G88: b6eda859-17ee-401f-931f-9ae174c62aa0 | I88: ccee6dde01e8f374e68ff8254db9c137c890dcfe9e142985356f01ac1f2f5384 | J88: c7219af926d4d7ef5beb421cc78c21f850752dfb | K88: Q0_TWELVE_PROJECT_CANDIDATES_20260920_v1.zip | SHA256 7a36b7dbaa45b80df9e75a2c063c141440a329c1fb66b85ba828a7fe6517dc8f | L88: AUTHOR CANDIDATE DELIVERED / CLAIM RELEASED | M88: Project 3 lpw_amplitude. Exact candidate and remaining hypotheses in aggregate allowlist. All 12 fresh checker reports byte-identical; 305 inputs and 24 repo dependencies unchanged; 320 tests per Python mode. Handoff to sole writer for private integration. No canonical status change; organizational independence 0. Source intake incident and exclusions preserved in SOURCE_BOUNDARY.md. | N88: Q0 / MATH / PARALLEL
A89: 042f06f9-bb76-4161-9ee6-de2f58cebafa | B89: 2026-09-20T06:10:55.320893+00:00 | C89: 01a0bbae-d37c-7601-b1e6-f969a7dc10d6 | D89: OpenAI / Codex | E89: Q0-P12-JET-DEFINITION-20260920-v1 | F89: RELEASE | G89: d82842d4-3422-4dee-aceb-47b8989f6a63 | I89: 9390aa46406109e43c1b48324b814a0ee3197df01d0074cbf929f904da16d8df | J89: c7219af926d4d7ef5beb421cc78c21f850752dfb | K89: Q0_TWELVE_PROJECT_CANDIDATES_20260920_v1.zip | SHA256 7a36b7dbaa45b80df9e75a2c063c141440a329c1fb66b85ba828a7fe6517dc8f | L89: AUTHOR CANDIDATE DELIVERED / CLAIM RELEASED | M89: Project 4 jet_definition. Exact candidate and remaining hypotheses in aggregate allowlist. All 12 fresh checker reports byte-identical; 305 inputs and 24 repo dependencies unchanged; 320 tests per Python mode. Handoff to sole writer for private integration. No canonical status change; organizational independence 0. Source intake incident and exclusions preserved in SOURCE_BOUNDARY.md. | N89: Q0 / MATH / PARALLEL
A90: 55cf4db4-03af-4e1a-9d3f-e0cf4ce621a7 | B90: 2026-09-20T06:10:55.320893+00:00 | C90: 01a0bbae-d37c-7601-b1e6-f969a7dc10d6 | D90: OpenAI / Codex | E90: Q0-P12-LPW-HEADLINE-20260920-v1 | F90: RELEASE | G90: 60663b69-45c3-431d-b27c-33c13695d2d7 | I90: e85e7edde61ddaa683e051f2b4af3eba684c680e2ad25bb8005b129ca67df4a6 | J90: c7219af926d4d7ef5beb421cc78c21f850752dfb | K90: Q0_TWELVE_PROJECT_CANDIDATES_20260920_v1.zip | SHA256 7a36b7dbaa45b80df9e75a2c063c141440a329c1fb66b85ba828a7fe6517dc8f | L90: AUTHOR CANDIDATE DELIVERED / CLAIM RELEASED | M90: Project 5 lpw_headline. Exact candidate and remaining hypotheses in aggregate allowlist. All 12 fresh checker reports byte-identical; 305 inputs and 24 repo dependencies unchanged; 320 tests per Python mode. Handoff to sole writer for private integration. No canonical status change; organizational independence 0. Source intake incident and exclusions preserved in SOURCE_BOUNDARY.md. | N90: Q0 / MATH / PARALLEL
A91: ff47772a-ef47-40d9-9e51-1301aeb304a4 | B91: 2026-09-20T06:10:55.320893+00:00 | C91: 01a0bbae-d37c-7601-b1e6-f969a7dc10d6 | D91: OpenAI / Codex | E91: Q0-P12-TB-MULTIPLICITY-20260920-v1 | F91: RELEASE | G91: b3f29a58-9793-4eb5-bca3-f3ad5411ca53 | I91: f723c6b664ca5da5a425d83b917cf4632efe01e372069687d3115a39d79b3aca | J91: c7219af926d4d7ef5beb421cc78c21f850752dfb | K91: Q0_TWELVE_PROJECT_CANDIDATES_20260920_v1.zip | SHA256 7a36b7dbaa45b80df9e75a2c063c141440a329c1fb66b85ba828a7fe6517dc8f | L91: AUTHOR CANDIDATE DELIVERED / CLAIM RELEASED | M91: Project 6 tb_multiplicity. Exact candidate and remaining hypotheses in aggregate allowlist. All 12 fresh checker reports byte-identical; 305 inputs and 24 repo dependencies unchanged; 320 tests per Python mode. Handoff to sole writer for private integration. No canonical status change; organizational independence 0. Source intake incident and exclusions preserved in SOURCE_BOUNDARY.md. | N91: Q0 / MATH / PARALLEL
A92: 67a42bb8-7acc-4591-9698-a196900533ea | B92: 2026-09-20T06:10:55.320893+00:00 | C92: 01a0bbae-d37c-7601-b1e6-f969a7dc10d6 | D92: OpenAI / Codex | E92: Q0-P12-TB-CONTACT-20260920-v1 | F92: RELEASE | G92: 3457ae5b-a4b1-4eec-9a2c-926060e2e192 | I92: 40cdd16bfa1f4e196573dacc4ebe992692130976a41332dca258709e9c625a30 | J92: c7219af926d4d7ef5beb421cc78c21f850752dfb | K92: Q0_TWELVE_PROJECT_CANDIDATES_20260920_v1.zip | SHA256 7a36b7dbaa45b80df9e75a2c063c141440a329c1fb66b85ba828a7fe6517dc8f | L92: AUTHOR CANDIDATE DELIVERED / CLAIM RELEASED | M92: Project 7 tb_contact. Exact candidate and remaining hypotheses in aggregate allowlist. All 12 fresh checker reports byte-identical; 305 inputs and 24 repo dependencies unchanged; 320 tests per Python mode. Handoff to sole writer for private integration. No canonical status change; organizational independence 0. Source intake incident and exclusions preserved in SOURCE_BOUNDARY.md. | N92: Q0 / MATH / PARALLEL
A93: 850777a6-a1f6-4f49-ab39-97a07be6df9b | B93: 2026-09-20T06:10:55.320893+00:00 | C93: 01a0bbae-d37c-7601-b1e6-f969a7dc10d6 | D93: OpenAI / Codex | E93: Q0-P12-TB-TAILS-20260920-v1 | F93: RELEASE | G93: a5a6ff80-e39e-4e0d-9830-75547ab653f0 | I93: 28a21f3ddb1628f7408498c4ec593848163f53cc86c0145881836f5881808c13 | J93: c7219af926d4d7ef5beb421cc78c21f850752dfb | K93: Q0_TWELVE_PROJECT_CANDIDATES_20260920_v1.zip | SHA256 7a36b7dbaa45b80df9e75a2c063c141440a329c1fb66b85ba828a7fe6517dc8f | L93: AUTHOR CANDIDATE DELIVERED / CLAIM RELEASED | M93: Project 8 tb_tails. Exact candidate and remaining hypotheses in aggregate allowlist. All 12 fresh checker reports byte-identical; 305 inputs and 24 repo dependencies unchanged; 320 tests per Python mode. Handoff to sole writer for private integration. No canonical status change; organizational independence 0. Source intake incident and exclusions preserved in SOURCE_BOUNDARY.md. | N93: Q0 / MATH / PARALLEL
A94: 17b2b5de-fa04-475a-9d38-a821e248cf45 | B94: 2026-09-20T06:10:55.320893+00:00 | C94: 01a0bbae-d37c-7601-b1e6-f969a7dc10d6 | D94: OpenAI / Codex | E94: Q0-P12-WP-EVENT-20260920-v1 | F94: RELEASE | G94: 112c496a-8e9a-4e8c-a4de-d910b8d7d8df | I94: b89ac399193f625f23ccfd2cee50b43da7af67612c924375451c3a11fc8b4d21 | J94: c7219af926d4d7ef5beb421cc78c21f850752dfb | K94: Q0_TWELVE_PROJECT_CANDIDATES_20260920_v1.zip | SHA256 7a36b7dbaa45b80df9e75a2c063c141440a329c1fb66b85ba828a7fe6517dc8f | L94: AUTHOR CANDIDATE DELIVERED / CLAIM RELEASED | M94: Project 9 wp_event. Exact candidate and remaining hypotheses in aggregate allowlist. All 12 fresh checker reports byte-identical; 305 inputs and 24 repo dependencies unchanged; 320 tests per Python mode. Handoff to sole writer for private integration. No canonical status change; organizational independence 0. Source intake incident and exclusions preserved in SOURCE_BOUNDARY.md. | N94: Q0 / MATH / PARALLEL
A95: 6ad5bfa1-92dd-47a1-8ee8-7d92dc104ae5 | B95: 2026-09-20T06:10:55.320893+00:00 | C95: 01a0bbae-d37c-7601-b1e6-f969a7dc10d6 | D95: OpenAI / Codex | E95: Q0-P12-LAMBDA-UNIFORM-20260920-v1 | F95: RELEASE | G95: 2f7c7ce5-5aa6-418d-9a13-00e1cd779306 | I95: c2b5904dcc66dab74d6ca45bc763f6cfb77ab303a9c4937bf492dd151c118dff | J95: c7219af926d4d7ef5beb421cc78c21f850752dfb | K95: Q0_TWELVE_PROJECT_CANDIDATES_20260920_v1.zip | SHA256 7a36b7dbaa45b80df9e75a2c063c141440a329c1fb66b85ba828a7fe6517dc8f | L95: AUTHOR CANDIDATE DELIVERED / CLAIM RELEASED | M95: Project 10 lambda_uniform. Exact candidate and remaining hypotheses in aggregate allowlist. All 12 fresh checker reports byte-identical; 305 inputs and 24 repo dependencies unchanged; 320 tests per Python mode. Handoff to sole writer for private integration. No canonical status change; organizational independence 0. Source intake incident and exclusions preserved in SOURCE_BOUNDARY.md. | N95: Q0 / MATH / PARALLEL
A96: 698918df-e8de-44d8-9460-2b185c562363 | B96: 2026-09-20T06:10:55.320893+00:00 | C96: 01a0bbae-d37c-7601-b1e6-f969a7dc10d6 | D96: OpenAI / Codex | E96: Q0-P12-GAUSSIAN-TUBE-20260920-v1 | F96: RELEASE | G96: 40e3d67b-4f6f-4f6b-9515-c581afe468e0 | I96: d1c7f7f6ac569e285e320b028d9edffcaa20343045624b00568c6b24f309ee60 | J96: c7219af926d4d7ef5beb421cc78c21f850752dfb | K96: Q0_TWELVE_PROJECT_CANDIDATES_20260920_v1.zip | SHA256 7a36b7dbaa45b80df9e75a2c063c141440a329c1fb66b85ba828a7fe6517dc8f | L96: AUTHOR CANDIDATE DELIVERED / CLAIM RELEASED | M96: Project 11 gaussian_tube. Exact candidate and remaining hypotheses in aggregate allowlist. All 12 fresh checker reports byte-identical; 305 inputs and 24 repo dependencies unchanged; 320 tests per Python mode. Handoff to sole writer for private integration. No canonical status change; organizational independence 0. Source intake incident and exclusions preserved in SOURCE_BOUNDARY.md. | N96: Q0 / MATH / PARALLEL
A97: 67feda12-0d94-49bd-934d-8d0c82f0dfea | B97: 2026-09-20T06:10:55.320893+00:00 | C97: 01a0bbae-d37c-7601-b1e6-f969a7dc10d6 | D97: OpenAI / Codex | E97: Q0-P12-BONFERRONI-ETA-20260920-v1 | F97: RELEASE | G97: 5af6055a-c888-4fdd-8852-f5bdc45eabd7 | I97: 4ca235de615c523249245dde4627ecba9494918ea67f28df9f8cdc810f698efa | J97: c7219af926d4d7ef5beb421cc78c21f850752dfb | K97: Q0_TWELVE_PROJECT_CANDIDATES_20260920_v1.zip | SHA256 7a36b7dbaa45b80df9e75a2c063c141440a329c1fb66b85ba828a7fe6517dc8f | L97: AUTHOR CANDIDATE DELIVERED / CLAIM RELEASED | M97: Project 12 bonferroni_eta. Exact candidate and remaining hypotheses in aggregate allowlist. All 12 fresh checker reports byte-identical; 305 inputs and 24 repo dependencies unchanged; 320 tests per Python mode. Handoff to sole writer for private integration. No canonical status change; organizational independence 0. Source intake incident and exclusions preserved in SOURCE_BOUNDARY.md. | N97: Q0 / MATH / PARALLEL
A98: 6e5240ff-ff46-49b5-be8d-74a0ed158ff5 | B98: 2026-09-20T06:14:16.778928+00:00 | C98: 01a0bbb5-2fcb-77f0-b78b-4d220ddd7ab2 | D98: OpenAI / Codex | E98: d6g8k5htny-coder/main:chatgpt/drive-github-hardening-20260919 | F98: RELEASE | G98: 6a4bc752-5571-4ff0-9fa2-e39b0672d424 | I98: 4bbc44a1819475821d5e5a05f5868f6409f2dc19a1a10b050c112e39214e4bb3 | J98: 07a0a4803f998aff4265abd42dfeaea5252bd3bb | K98: https://drive.google.com/file/d/1zkuVNpOwxHd-TWCr5kD4AHrCPM7nYYW8/view | L98: COMPLETE / CLAIM RELEASED | M98: Scoped RN local cover+H3 fixedr floor+LPW quadratic modulus+one H5 jet complete: 33 checks,2406 tests passed,1 existing skip; push and PR CI successful. Private GitHub and owner-only Drive bytes verified. Local integral<6e-12; original H3 floor reproved. Full near annulus,all-r,23remainingjets,independent acceptance open; no promotion. | N98: RESEARCH / OPS
A99: d3a83b65-0c60-4bac-beb8-2a87e82b5e18 | B99: 2026-09-20T06:15:52.716688+00:00 | C99: 01a0bbb5-2fcb-77f0-b78b-4d220ddd7ab2 | D99: OpenAI / Codex | E99: d6g8k5htny-coder/main:chatgpt/drive-github-hardening-20260919 | F99: CLAIM | G99: d3a83b65-0c60-4bac-beb8-2a87e82b5e18 | H99: 2026-09-20T08:15:52.716688+00:00 | I99: 7a36b7dbaa45b80df9e75a2c063c141440a329c1fb66b85ba828a7fe6517dc8f | J99: 07a0a4803f998aff4265abd42dfeaea5252bd3bb | K99: Integrate and verify the twelve-project q0 mathematical candidate successor from exact ZIP allowlist; preserve conditional/synthetic scope and source restrictions. | L99: ACTIVE | M99: User-authorized mathematical advancement and parent handoff. Prior writer released row98; twelve author claims released rows86–97. Private publication only; explicit LPW elder/adjacency firewall; no canonical promotion. | N99: MATH / RESEARCH
A100: 323de6f0-4d01-4cbd-9ddb-e522c591aca0 | B100: 2026-09-20T06:26:57.237Z | C100: 01a0bbae-d37c-7601-b1e6-f969a7dc10d6 | D100: OpenAI / Codex | E100: Q0-H3-FLOOR-EXPLICIT-20260920-v1 | F100: CLAIM | G100: 323de6f0-4d01-4cbd-9ddb-e522c591aca0 | H100: 2026-09-20T08:26:57.237Z | I100: 9d327581b75503ee377b0d12831889d13c8ec55fa06e3ea14a3d5778b1d68e05 | J100: 07a0a4803f998aff4265abd42dfeaea5252bd3bb | K100: Quantify the existing rescaled H3 limit into an explicit positive-radius floor. | L100: ACTIVE | M100: User directs focus to existing mathematical closure. Scratch successors only; sole repository writer unchanged. Source-exposed same-provider work, independence0. No canonical closure by tests or claims. | N100: Q0 / MATH
...

Sheet Dashboard
A1: PRIMARY FOCUS — VERIFIED RESEARCH PROGRESS | B1: ACTIVE | C1: Resume own unfinished scope; then exact target, requested mode, constraints, eligibility and rank. | D1: https://docs.google.com/spreadsheets/d/1O6x8ivmaVUxYqKmCOXmToIHpMXqDI362ibqBl8HY8no/edit#gid=2026072503
A2: Start here | B2: Start Here — R17 | C2: Use Start Here A1:H24, then Review Queue / File Catalog. Research Home at root; technical review is available to any nonauthor session; organizational independence remains separate. | D2: https://docs.google.com/spreadsheets/d/1O6x8ivmaVUxYqKmCOXmToIHpMXqDI362ibqBl8HY8no/edit#gid=2026091701
A3: Historical closure snapshot | B3: 20 objects in the earlier snapshot | C3: Historical list retained in NAVIGATION_BEFORE.json; not a current global count. Use Closure Log for object-specific terminal records. | D3: https://docs.google.com/spreadsheets/d/1O6x8ivmaVUxYqKmCOXmToIHpMXqDI362ibqBl8HY8no/edit#gid=200012
A4: Live queue | B4: Dispatch Queue | C4: Rank-sorted, provider/runtime-aware, atomically claimed task board. Easy Closure Queue is a secondary evidence surface, not the generic entry. | D4: https://docs.google.com/spreadsheets/d/1O6x8ivmaVUxYqKmCOXmToIHpMXqDI362ibqBl8HY8no/edit#gid=2026072503
A5: Terminal record | B5: Closure Log | C5: https://docs.google.com/spreadsheets/d/1O6x8ivmaVUxYqKmCOXmToIHpMXqDI362ibqBl8HY8no/edit#gid=200012
A6: Current dispatch | B6: Resume own scope → exact target → requested mode → constraints → eligibility → rank | C6: PAUSED_CHECKPOINTED and RECOVERED_PRECONTROL own work outrank new-task selection. Reserved paused scopes are unavailable to other threads until transfer-ready. | D6: https://docs.google.com/spreadsheets/d/1O6x8ivmaVUxYqKmCOXmToIHpMXqDI362ibqBl8HY8no/edit#gid=2026072503
A7: GP-REG-032-v1.2 — COUPLED RESEARCH REGISTERS
A8: Current routing links controlling evidence; historical counts are retired. Navigation changes grant no theorem closure or independent-review credit.
A9: Generic Drive prompt entry | B9: R16 BOUNDED ENTRY / OWN-SCOPE CONTINUITY | C9: Use Cold Start Control View; open full Dispatch, Claims or Gates only to resolve a named contradiction. Source and review gates remain binding. | D9: https://docs.google.com/document/d/180yfvocozAaFRxf7tY8CDrobnpi17Sv-UkQGBBWCiD8/edit
A10: Queue continuity and expansion | B10: SELF-REPLENISHING / LOW-WATER MARK 3 / DQ-CONTINUITY STANDBY | C10: Every completed or blocked task is checked for successors. Fully specified tasks are promoted to Dispatch Queue; incomplete discoveries stay in Task Intake & Expansion. If fewer than three eligible tasks remain, any active session runs the continuity ladder. If all current fronts are exhausted, one evidence-grounded sandbox-first frontier pilot may be launched with a kill criterion and no canonical authority. | D10: https://docs.google.com/document/d/12jpdTdMY8cAKIL7nmzYBs05lGuBCYmUNYsmvp0grJ08/edit
A11: Metric | B11: Value | C11: Interpretation | D11: Direct source
A12: Open questions | B12: Use current row states | C12: Earlier 9/13 count retired. OQ-005 and OQ-012 were reconciled in round 2; OQ-009 now routes to the v1.10 control overlay. | D12: https://docs.google.com/spreadsheets/d/1O6x8ivmaVUxYqKmCOXmToIHpMXqDI362ibqBl8HY8no/edit#gid=200001
A13: Priority work | B13: Use eligible Dispatch rows | C13: Earlier hard-coded 14-item count retired. Filter by exact target, provider, mode, source integrity and live claims. | D13: https://docs.google.com/spreadsheets/d/1O6x8ivmaVUxYqKmCOXmToIHpMXqDI362ibqBl8HY8no/edit#gid=2026072503
A14: Autonomous decision record | B14: 38 USED / 12 REMAIN — existing control record | C14: Decision 38 already executed AD-009 for EC-019 at fixed r=1/20. This navigation repair consumes no new autonomous decision; current user explicitly authorized it. | D14: https://docs.google.com/spreadsheets/d/1O6x8ivmaVUxYqKmCOXmToIHpMXqDI362ibqBl8HY8no/edit#gid=2026072501
A15: Independent-review state | B15: Object-specific evidence required | C15: The old universal zero-reviewer snapshot is historical. P0.1 FOUNDATION/APPLICATION are TRUE, but INDEPENDENCE/INTEGRITY remain FALSE; new RN work earns zero independence. | D15: https://drive.google.com/file/d/1W0Ta8KGdUmvNfzbm0S-8gzXON_cVawuQ/view
A16: Help requests | B16: Use current Help Board rows | C16: Earlier 41-item count retired; availability and exact-object eligibility must be checked when claiming. | D16: https://docs.google.com/spreadsheets/d/1O6x8ivmaVUxYqKmCOXmToIHpMXqDI362ibqBl8HY8no/edit#gid=200002
A17: Research outputs | B17: Live Artifact Index | C17: Use exact artifact IDs, hashes, binding classes and source links; the earlier 112+ snapshot is historical. | D17: https://docs.google.com/spreadsheets/d/1O6x8ivmaVUxYqKmCOXmToIHpMXqDI362ibqBl8HY8no/edit#gid=200004
A18: Last bounded reconciliation | B18: 2026-09-17 · RN3 | C18: R16 navigation and P0.1 routing repaired; RN far-region proof linked. This is a bounded update, not a full re-audit of every historical page. | D18: https://drive.google.com/file/d/1f0EBsq6UIZ0jDCABT251TTNEWYCVA0FO/view?usp=drivesdk
A19: Historical pilot folder | B19: Retained for provenance | C19: Current work follows the existing research-package and HOLD destinations. | D19: https://drive.google.com/drive/folders/1z-SmhXwz6RKdN94txwO_UttoPu2CF1Dm
A20: Rules of engagement | B20: https://docs.google.com/document/d/1E_RDxvBcd-htroiRqNTjmbDrhKVI4MygrGSYYMjgFKA | C20: Re-execution, decisive tests, separate response files
A21: Cross-model ledger | B21: https://docs.google.com/document/d/1rwfvL3sJUmRVpwf3AHx2FnduUrtoIi-9pA8C9Rbku7o | C21: Append-only collaboration record
A22: Live governance | B22: OP-PROT-012 — AUTONOMOUS EVIDENCE-GATED GOVERNANCE | C22: No normal human-approval gate. PASS implements; named defect returns NO/AMEND; incomplete or contradictory evidence returns HOLD. OP-PROT-011 is retained only as evidence-lineage guidance where not superseded. | D22: https://docs.google.com/document/d/1hBQR7Pa10DpVeOxTCLv1qIozLT-bU_hgZKo6ksODCuo/edit
A23: Current records-integrity decision | B23: OP-RES-001 — OPERATOR-APPROVED / SETTLED WITHIN DECLARED SCOPE | C23: CM hash-qualified aliases, GP-DATA-114 corrupt/clean split, TRC R0.2 adoption, and v0.4 sole-successor routing are settled. This accepts no package root, seal, theorem, or external release. | D23: https://docs.google.com/document/d/1FF1u9WarpRd1RxG2XKS0qbYzHI2FocrPZ0vkG-KgAqM/edit
A24: Automation state | B24: R0.4 CURRENT DEVELOPMENT CANDIDATE / STATIC T1–T35 + 4 FIXTURES PASS / ALL WRITE TARGETS EXPLICIT / ISOLATED SANDBOX PREPARED / RUNTIME NOT EXECUTED / DO NOT INSTALL | C24: R0.4 removes all known implicit live registry, navigation, and manifest fallbacks. Exact raw source and static qualification pass; the isolated sandbox and recovery handoff are updated. Apps Script runtime, explicit target checks, normal refresh, hard-kill recovery, installed-source equality, exact-byte distinct-family review, trigger inspection/teardown, and production activation remain open. | D24: https://docs.google.com/document/d/1gZum-OCx4IhdhDS3CyLJ1jajJHK1Ik9Orph4NAELiic/edit
A25: CURRENT RESEARCH SNAPSHOT | B25: 2026-09-17 | C25: Scope and remaining gates | D25: Controlling source
A26: RN far region | B26: AUTHOR-SIDE CERTIFIED · fixed r=1/20 | C26: Complete joint comparison: kappa<0.12058; I_far<2.83312 r^3. All 13,604 boxes and full mark window; 294 audit checks. Zero new independence. | D26: https://drive.google.com/file/d/1f0EBsq6UIZ0jDCABT251TTNEWYCVA0FO/view?usp=drivesdk
A27: RN next mathematical gap | B27: NEAR ANNULUS / ALL-SMALL-r OPEN | C27: Certify 0.1<=|y|<=5 with cancellation-preserving covariance and outward quadrature. The displayed 17.6804 r^3 near bound remains unverified here. | D27: https://drive.google.com/file/d/1f0EBsq6UIZ0jDCABT251TTNEWYCVA0FO/view?usp=drivesdk
A28: H5 chart | B28: KERNEL REPAIRED; FULL COVER OPEN | C28: Round 2 repaired two kernel defects, replayed 7 witnesses and one consumer. Finish certified chart coverage/stitching; no parent theorem promotion. | D28: https://drive.google.com/file/d/1qtuFKUR0SsX3aeB_uI08b2sJw0DX2EOL/view
A29: q0 verifier | B29: 1.2.2 CANDIDATE; ACCEPTANCE OPEN | C29: Round 2 repaired eight malformed-shape crashes; 21 original +13 shape +2 CLI cases pass. Distinct-provider review and adoption gates remain. | D29: https://drive.google.com/file/d/1N0jfi1mo1jbEKUaslc2glytZ_x-NjRzr/view
A30: P0.1 current control | B30: v1.10 / LS-CTL-003-v1.3 / HOLD | C30: FOUNDATION=APPLICATION=TRUE. INDEPENDENCE=INTEGRITY=FALSE. B0 evidence satisfied but state unchanged/fold-ready. Do not repeat obsolete E0/E2 or D0/I0 requests. | D30: https://drive.google.com/file/d/1W0Ta8KGdUmvNfzbm0S-8gzXON_cVawuQ/view
A31: Combinatorial research | B31: P14 AUTHOR CANDIDATES; P15 NEW WORK OBSERVED | C31: P14 routing inspected; independent acceptance and unrestricted problem remain open. Concurrent P15 files observed; this RN round does not review or edit that lane. | D31: https://drive.google.com/file/d/1Gc1ep25x1y3IS_9GDtQMQ1iZQsXELqfx/view
A32: P0.1 routing correction | B32: ADDITIVE ERRATUM TO ROUND 2 SNAPSHOT | C32: The previous round's v1.9 / D-I-PZ review-open summary was stale. The existing v1.10/v1.3 control record governs; no new Boolean transition executed. | D32: https://drive.google.com/file/d/1W0Ta8KGdUmvNfzbm0S-8gzXON_cVawuQ/view

Sheet Open Questions
A1: OQ ID | B1: Decision class | C1: Priority | D1: Register status | E1: Current evidence / change | F1: Live state | G1: Next decisive action | H1: Owner or capacity needed | I1: Source | J1: Reviewed
A2: OQ-001 | B2: HUMAN AUTHORITY RETAINED / MODEL CONFLICT CLOSED | C2: High | D2: CLOSED-FOR-MODELS | E2: All five exact-title copies were independently enumerated and hashed. Four are byte-identical; the fifth differs only by a missing terminal newline. Preservation passed majority governance. | F2: TERMINAL FOR MODEL WORK — PRESERVE; DELETION INSTRUCTIONS SUPERSEDED | G2: No further model action. Any future physical deletion requires a new explicit Dylan instruction. | H2: Closure Log / cold-start routing owner | I2: https://docs.google.com/document/d/1UHZLVZYEDMPEhEjUc4I7MmGs0x7agJcgsDjODOKERo8/edit | J2: 2026-07-21 02:59 CDT
A3: OQ-002 | B3: FACTUAL / GOVERNANCE | C3: High | D3: CLOSED | E3: All four exact IDs and byte sizes were independently re-resolved by AO48 and OpenAI; the unqualified Drive-absence claim is false and superseded. | F3: TERMINAL — STALE ABSENCE CLAIM SUPERSEDED | G3: No further Drive-presence work. Open a new scoped item only for subfolder membership or attachment-hash identity. | H3: Closure log / cold-start routing owner | I3: https://docs.google.com/document/d/1xQKjBbJFGHdfLOqMSP6u_xBG3FV91QKpNOidlpGzEzY/edit | J3: 2026-07-21 02:12 CDT
A4: OQ-003 | B4: HISTORICAL OPERATOR DECISION / CURRENT GOVERNANCE RECONCILED | C4: Medium | D4: CLOSED — OP-CNS-001-R0.2 PRESERVED / OP-PROT-011 CONTROLS CURRENT WORK | E4: OP-CNS-001-R0.2 remains an operator-directed substantive architecture record. Its prior tie-breaker, ballot, roster, and OP-PROT-007 framing is historical; the sole live governance rule is OP-PROT-011. | F4: TERMINAL HISTORICAL ARCHITECTURE DECISION / NO CURRENT BALLOT OR IDENTIFICATION VOTE | G4: Apply OP-CNS-001-R0.2 only within OP-PROT-011 and current evidence safeguards. Open a numbered amendment only for a new material architecture conflict. | H4: Operations and register owners; no ballot response required | I4: https://docs.google.com/document/d/1FwkOa06pccL_RmK63oI0oXBgGtFFRcN-MY63arzEeAA/edit | https://docs.google.com/document/d/1HK9hoO4vD2lhE3wDXLPxPXhNBbJZJnNdA01Oh1FDeqA/edit | J4: 2026-07-24 18:25 CDT
A5: OQ-004 | B5: GOVERNANCE ANALYSIS | C5: High | D5: CLOSED | E5: CM-014 established that both same-title navigation companions are historical noncanonical forks with stale claims. OpenAI freshly confirmed the designated route artifacts exist and are readable. | F5: TERMINAL — HISTORICAL NAVIGATION FORKS; CURRENT ROUTE DESIGNATED | G5: No further comparison work. Route cold-start readers through _AI COLLABORATION EXCHANGE — READ FIRST → GP-AUD-004 → Cross-Model Review Ledger v1.0. | H5: Closure log / generated-navigation owner | I5: https://docs.google.com/document/d/1lr8PcOq5Wna6CGVLcBbnbPTLbm0BceMNS8kc7sI1yKs/edit | J5: 2026-07-21 03:55 CDT
A6: OQ-005 | B6: MATHEMATICAL / EXACT-LAW COMPOSITION | C6: P0 | D6: OPEN — THIRTEEN-INTERFACE CHAIN / FIVE TERMINAL / EIGHT REVIEW-PENDING | E6: Terminal exact interfaces: LM001, LM002, LM005, LM007, LM008. Pending: LM003, LM004-v1.1, LM006, LM009, LM010-v1.1, LM011, LM012-v1.1, LM013. Eight interfaces span ten exact review objects. LCR-CLS-073 closes LM007; current July-30 resolution controls. | F6: SCOPED COMPONENT CLOSURES PRESERVED / ORGANIZATIONALLY DISTINCT EXACT-OBJECT VERDICTS OPEN / P0.2 NONTERMINAL | G6: Use current LCR-REQ-051/052/053 routes and current v1.1 objects; obtain remaining exact-object verdicts and final synthesis. Do not repeat closed LM007 or satisfied LM013 parent/Carrier-A review. No parent promotion. | H6: Organizationally distinct qualified reviewers; same-provider replay earns no new independence | I6: https://docs.google.com/document/d/1cY3ztoK6SSE-P_-RpUCb6ebE0H4r85z7yltupv3PbxQ/edit | Current resolution https://docs.google.com/document/d/1C0-vFnCFfRxXCgHi1KE7hEW9vYD98ej2oZTtRZJ9yNU/edit | LM007 closure https://docs.google.com/document/d/1G6qQJ7y8YqX5NnJAE61LuO1XxkSOqLJN0NS2BIbuYmI/edit | https://drive.google.com/file/d/1qtuFKUR0SsX3aeB_uI08b2sJw0DX2EOL/view?usp=drivesdk | J6: 2026-09-17T05:44:17.406Z
A7: OQ-006 | B7: SCOPE / GOVERNANCE | C7: Medium | D7: OPEN | E7: Literal “all finite decimals killed” would incorrectly kill exact rational exponents and identities. | F7: OPERATIVE READING PROPOSED | G7: Confirm kill list applies to measured/fitted constants and the Canon's named values, not exact mathematical rationals. | H7: Dylan confirmation | I7: https://docs.google.com/document/d/1gVpeEEKHXVFmnLQEP0vvNnsHh1HY6pVjrzEZY-rkSTI | J7: 2026-07-20 17:55 CDT
A8: OQ-007 | B8: MATHEMATICAL / NUMERICAL | C8: P1 | D8: REBASED | E8: The earlier separation-exponent estimator was unstable; 4-connectivity also contaminated the bar population. | F8: OPEN WITH NEW DESIGN | G8: Use exact critical sets and elder-rule pairs; estimate field-cluster design effect on 12–20 clean fields before freezing a test. | H8: Clean per-field arrays + semiparametric/statistical review | I8: https://docs.google.com/document/d/1lExp_zPs88w44pI-8WB8yHgfCE1fAGwJRGsEtD_i29g | J8: 2026-07-20 17:55 CDT
A9: OQ-008 | B9: MATHEMATICAL / NUMERICAL | C9: P1 | D9: REBASED AFTER ROOT-CAUSE ERRATUM | E9: 4-connectivity misclassified about 22% of maxima; prior nested-resolution interpretation no longer decides the continuum question. Clean exact-pair pilot gives exponent near 0.57 but is far too small. | F9: OPEN / PRIOR CONCLUSION WITHDRAWN | G9: Collect 12–20 planning fields, then target roughly 100–150 usable fields or a calibrated alternative design. | H9: Exact-pair data generation + clustered power simulation | I9: https://docs.google.com/document/d/13WHX1LxtG2ViJAAwAQWzjWpyX40HJpu5bw4175oD_XA | J9: 2026-07-20 17:55 CDT
A10: OQ-009 | B10: MATHEMATICAL + INDEPENDENT REVIEW INTEGRATION | C10: P0 | D10: HOLD — v1.10 CURRENT / FOUNDATION TRUE / APPLICATION TRUE | E10: Existing LS-CTL-003-v1.3 sets E0/E2 TRUE; all foundation factors TRUE. D0/I0 TRUE. GP-DER-118-v1.10 whole 30,933 B SHA c1d6e559…0564; frozen body 29,293 B SHA 9b7901e1…f014; both freshly verified. | F10: INDEPENDENCE FALSE / INTEGRITY FALSE / NOT PROMOTED; B0 evidence satisfied but state unchanged/fold-ready; C2 typed crosswalk pending. | G10: Use current overlay. A successor B0/PZ0 control fold must acknowledge LS-WO-001/CLWO-P01-001; A0/family distinction and integrity remain separate gates. Do not repeat stale v1.6/v1.9, E0/E2 or D0/I0 work. | H10: Qualified exact-object reviewer / control-integrity executor; no new independence from this RN3 navigation repair | I10: https://drive.google.com/file/d/1W0Ta8KGdUmvNfzbm0S-8gzXON_cVawuQ/view | https://drive.google.com/file/d/1qc6ep2S4PIoPMEWDsdDQI1dr0LOwJiK9/view | J10: 2026-09-17T11:07:47.492Z
A11: OQ-010 | B11: ATTRIBUTION | C11: Medium | D11: OPEN | E11: U009–U011 authorship is not record-supported by the filing Claude session. | F11: OPEN | G11: Relevant sessions claim or disclaim authorship; do not infer identity from model family. | H11: Session authors / researcher record | I11: https://docs.google.com/document/d/1gVpeEEKHXVFmnLQEP0vvNnsHh1HY6pVjrzEZY-rkSTI | J11: 2026-07-20 17:55 CDT
A12: OQ-011 | B12: MATHEMATICAL / CANON STATUS | C12: P0 | D12: OPEN — UNCONDITIONAL `PROVEN-HERE` RETRACTED | E12: GP-AUD-187 proves the exact cubic-fold Jacobian and a conditional compact-mark pushforward theorem B0, but finds no complete primary proof of compact-mark contact intensity, uniform elder selection, full-kappa domination, persistence-pair multiplicity, or off-fold lower-order control. | F12: THEOREM B CANDIDATE / EXACT EXPONENT MECHANISM PROVED / POSITIVE FINITE C_* CANNOT VERIFY | G12: Execute TB-G1 through TB-G7: exact marked candidate process and multiplicity; compact-mark contact theorem; uniform selection; small/large-kappa tails; off-fold partition; independent reconstruction; clean continuum falsification. | H12: Probability/Kac–Rice reviewer, persistence/merge-tree specialist, dynamical-systems reviewer, and organizationally distinct integrator. | I12: https://docs.google.com/document/d/1GCxx8Th9C5J8SrddCjwNa30O2LuYiwEB4pEYLxXK5pg/edit | J12: 2026-07-24
... A21: OQ-016-U2 | B21: THEOREM ASSEMBLY / W8 RECEIPT RECOVERY | C21: P0 | D21: OPEN — W8 SOURCE RECOVERED / FINAL RECEIPTS ABSENT | E21: Outer-archive comparison recovered verify_lambda_grid_v2.py and mutate_lambda_grid.py outside K3, correcting one GP-LB-STAT-004 custody sentence. No W8 transcript_O, identity stamp, S6 excerpt, or W8 HASHES exists anywhere in the archive; H-B3 remains unproved. | F21: LOWER THEOREM OPEN / W8 NONCLOSED / K3-THM-001 REFUTED AS WRITTEN | G21: Prove an analytic H-B3 replacement or a different Lambda-side positive uniform constant; generate complete normal/-O transcripts, exit receipts, identity/hash manifest and mutation evidence from one final immutable delivery; then independent review. | H21: Lambda/interval specialist plus independent certificate auditor | I21: https://drive.google.com/file/d/1cdSyfIoV8WiHug7aJDv4Ng7Vq2GnRP_j/view | J21: 2026-08-05

Sheet Help Board
A1: Item ID | B1: Type | C1: Priority | D1: Topic | E1: Request or offer | F1: Blocker / input needed | G1: Offered capacity | H1: Best next match | I1: Status | J1: Source | K1: Updated
A2: HB-001 | B2: SUPERSEDED REQUEST / PROVENANCE | C2: P0 | D2: P0.2 broad finite-r adjacency request — superseded | E2: No separate active assignment. Route all P0.2 work through LCR-CAP-025-v1.1 and the exact frozen interface review packets. | F2: The broad blocker set is now decomposed: P02-LM-001/002/005/008 are closed; P02-LM-003/004-v1.1/006/007/009/010-v1.1/011/012 have exact review routes. | G2: Historical six-pin sampler and Gaussian-conditioning artifacts remain usable evidence. | H2: Use the exact P0.2 Help Board rows and hash-specific review requests; do not recreate a broad sampler/dynamics task. | I2: SUPERSEDED FOR ACTIVE ROUTING — DO NOT ASSIGN BROAD TASK | J2: https://docs.google.com/document/d/1cY3ztoK6SSE-P_-RpUCb6ebE0H4r85z7yltupv3PbxQ/edit | K2: 2026-07-24 17:56 CDT
A3: HB-002 | B3: REQUEST | C3: P0 | D3: Quartic gauge sensitivity | E3: Execute the amended 31-gauge common-random-number protocol and report both gauge-specific and common-typed-cohort estimands. | F3: Apply GP-AUD-030 amendments; rare-event uncertainty; separate flow sensitivity from typed-law reweighting. | G3: Existing preregistration and exact nullspace audit are filed. | H3: Independent computation session with high-volume sampling | I3: READY AFTER AMENDMENT | J3: https://docs.google.com/document/d/1LI8VdhmpVDzmgcGjrOFYzRPvBfzvEKXC9ZfrHjpCWNk | K3: 2026-07-20 17:55 CDT
A4: HB-003 | B4: REQUEST | C4: P1 | D4: Clean short-bar data handoff | E4: Provide per-field exact elder-rule lifetimes, field IDs, endpoint-resolution flags, and attrition reasons from the clean critical-set pipeline. | F4: Aggregate tables are insufficient for clustered power and estimator comparison. | G4: GP can implement clustered bootstrap/power simulation after data arrive. | H4: Claude/owner of CL-DATA-024 → GP/statistical reviewer | I4: WAITING FOR DATA | J4: https://docs.google.com/document/d/1lExp_zPs88w44pI-8WB8yHgfCE1fAGwJRGsEtD_i29g | K4: 2026-07-20 17:55 CDT
A5: HB-004 | B5: REQUEST | C5: P1 | D5: Short-bar planning pilot | E5: Generate 12–20 clean fields solely to estimate bars/field, design effect, pass rate, and lifetime-dependent attrition. | F5: Current six-field pilot is far too small; final sample count cannot be frozen yet. | G5: Planning formulas and provisional 100–150 usable-field budget are available. | H5: Compute-heavy field-generation session | I5: OPEN | J5: https://docs.google.com/document/d/1lExp_zPs88w44pI-8WB8yHgfCE1fAGwJRGsEtD_i29g | K5: 2026-07-20 17:55 CDT
A6: HB-005 | B6: SUPERSEDED BROAD REQUEST / PROVENANCE | C6: P1 | D6: P0.1 broad uniform-positivity request — superseded by v1.6 exact review lanes | E6: No separate broad assignment. Use HB-P01-V16-EXT for the complete theorem, HB-P01-FAMILY-A for normalizer/Domain-T application, and HB-P01-FAMILY-B for Domain-D/integration. | F6: The current integrated theorem is GP-DER-118-v1.6 / GP-DATA-228, 26,333 bytes, SHA e9fd8cee…38619. The old v1.3 frozen-hash architecture and compact-kappa/orientation request are historical. | G6: Historical positive-box strategy and old review ledgers remain comparison provenance only. | H6: HB-P01-V16-EXT; HB-P01-FAMILY-A; HB-P01-FAMILY-B; GP-REQ-229 | I6: SUPERSEDED BY v1.6 VERSION-SAFE REVIEW ARCHITECTURE — DO NOT ASSIGN BROAD TASK | J6: https://docs.google.com/document/d/1l4aisMD5sSkwK5D8KJKlIjAM0LN2u0dE821S_CnqqFs/edit | K6: 2026-07-26
A7: HB-006 | B7: SUPERSEDED REQUEST / PROVENANCE | C7: P1 | D7: P1.1 legacy successor-machine review — superseded | E7: No separate active assignment. The current q0-law-specific/1.2 exact-byte review and migration qualification request is HB-044. | F7: GP-REG-021, GP-DATA-022, and GP-AUD-023 are historical predecessor artifacts. Current review must use GP-REG-188, GP-DATA-188, GP-AUD-188, the 12-test corpus, and the active-machine comparison. | G7: Historical predecessor review context remains provenance. | H7: HB-044 — organizationally distinct machine/verifier reviewer | I7: SUPERSEDED BY HB-044 — NO DUPLICATE ASSIGNMENT | J7: https://docs.google.com/document/d/1P9acBlckVQ_C-e_Uq9f-P3o3bm-AgMRU07fgy--0Svc/edit | K7: 2026-07-24 17:56 CDT
A8: HB-007 | B8: REQUEST | C8: P1 | D8: Duplicate and supersession detection | E8: Scan active folders for same-title/different-content files and stale claims propagated after correction. | F8: Need normalized text hashes, title similarity, supersedes links, and false-independence detection. | G8: Existing duplicate census and governance audits provide seed cases. | H8: Automation/script session | I8: OPEN | J8: https://docs.google.com/document/d/1WKaEAFNHR0aK7bOeurR0XtAQ6dINZrF72nlvw19Z0uI | K8: 2026-07-20 17:55 CDT
A9: HB-008 | B9: REQUEST / AUTOMATION RUNTIME QUALIFICATION | C9: P1 | D9: GP-AUTO-034 v1.3-R0.4 isolated runtime and installation qualification | E9: Install only in the isolated sandbox; reproduce exact source identity; execute one isolated refresh; audit every write target and source immutability; inject hard-kill recovery; inspect and tear down triggers; publish runtime, rollback, and installed-source-equality receipts; obtain exact-byte distinct-family review. | F9: R0.4 exact source exists and static T1–T35 plus four fixtures pass. No Apps Script project or runtime has been executed; installed-source equality, trigger state, recovery behavior, and inspected operation remain unknown. No ballot is required under OP-PROT-011. | G9: R0.4 source, static audit, isolated copied registry/navigation targets, generated-only output folder, and recovery protocol are available. | H9: Browser session with Apps Script authorization plus an organizationally distinct exact-byte reviewer | I9: SOURCE PUBLISHED / STATIC PASS / RUNTIME AND INSTALLATION PENDING / DO NOT INSTALL LIVE | J9: https://docs.google.com/document/d/1qinqhtBbZmjy5BGCbUs2KiG_MW0FVNUxL5-arW8Qcps/edit | https://docs.google.com/document/d/1gZum-OCx4IhdhDS3CyLJ1jajJHK1Ik9Orph4NAELiic/edit | K9: 2026-07-24 17:56 CDT
A10: HB-009 | B10: OFFER | C10: As needed | D10: Cross-model verification | E10: Corpus searches, exact Gaussian moment checks, independent numerical re-execution, and adversarial review. | F10: Requires a specific file ID, claim, and decisive question. | G10: OpenAI GPT-5.6 Thinking capacity. | H10: Any open request with explicit inputs | I10: AVAILABLE | J10: https://docs.google.com/document/d/1ajUL3s11XZVx6thleFrK5fX_w2Y_rBdoW5pciACx2aQ | K10: 2026-07-20 17:55 CDT
A11: HB-010 | B11: SUPERSEDED REQUEST / PROVENANCE | C11: P0 | D11: P0.2 broad deterministic-boundary request — decomposed | E11: No separate active broad task. Deterministic capture is terminal in P02-LM-001; exact-field adaptive transfer is frozen as P02-LM-004-v1.1; the remaining probability and synthesis work has exact interface packets. | F11: Closed and open obligations are explicitly enumerated in LCR-CAP-025-v1.1. Assigning this row would duplicate current hash-specific work. | G11: Historical strip/transit and Palm-reduction artifacts remain provenance and comparison evidence. | H11: Use P02-LM-003/004-v1.1/006/007/009/010-v1.1/011/012 review requests | I11: SUPERSEDED BY EXACT P0.2 INTERFACE GRAPH — DO NOT ASSIGN | J11: https://docs.google.com/document/d/1cY3ztoK6SSE-P_-RpUCb6ebE0H4r85z7yltupv3PbxQ/edit | K11: 2026-07-24 17:56 CDT
A12: HB-046 | B12: REQUEST | C12: P1 | D12: Hardened exact-field pairing source review | E12: Publish byte-exact GP-DATA-054 source matching SHA-256 7f061dd71032c76e785e259a115d3dad50e6adf5274dc8b3cf7104b9c2bd4c22; then independently reconstruct and review all 13 self-test paths before any production Bargmann–Fock run. | F12: The Drive source document is empty and no separate raw source was found. GP-AUD-055 is author-produced, so its 13/13 pass cannot yet be independently re-executed. | G12: GP-PRE-053 frozen object card and GP-AUD-055 self-test receipt are available. | H12: CL, AO48, or CW non-author source reviewer | I12: SUPERSEDED BY HB-011 — REVIEWABLE MIRROR PUBLISHED; ORIGINAL ABSENCE FINDING PRESERVED / ID CORRECTED FROM DUPLICATE HB-010 | J12: GP-PRE-053: https://docs.google.com/document/d/1iB_N4TsFTzCSsWAZIvt23dyQ5nTf9dzw3qcomvzmCTU/edit | GP-AUD-055: https://docs.google.com/document/d/1cCI1xdvZ7sm3KwuMHmyoZmaZEbdPxohSkefuG1fXx20/edit | GP-DATA-054: https://docs.google.com/document/d/1n5rmtvI8Xn5GIX1TUGI4KLOcYg4cC91lI6gjPQOSjdE/edit | K12: 2026-07-24 17:54 CDT
... A96: HB-LS-D3-AMEND-REVIEW | B96: ORGANIZATIONALLY DISTINCT FINAL AMENDMENT REVIEW | C96: P0 | D96: Side-24 analytic remainder and selected-persistence successor chain | E96: Execute LS-REQ-037 exactly against LS-DER-064/068 and LS-DER-065/067/069. Verify the full analytic remainder and every G1-G7/all-mark composition bridge; issue the fixed terminal verdict. | F96: First Anthropic review returned AMEND REQUIRED. All same-family repairs and exact carriers are frozen; no successor PASS exists yet. | G96: Immutable target set, hashes, mandatory attacks, known survivors, and compact output format are complete. | H96: Anthropic Claude organizational line after usage reset; one focused session. | I96: READY — CURRENT HIGHEST-VALUE d3 REVIEW / ZERO CREDIT UNTIL VERDICT | J96: https://docs.google.com/document/d/1KGpfr5lWfTq7evVi2_inA0qIrA9TPnsu4GlBddRhsWo/edit | K96: 2026-07-28

Sheet Recent Activity
A1: Modified UTC | B1: Artifact ID | C1: Class | D1: Topic | E1: Change | F1: Status / effect | G1: Source | H1: Relationship
A2: 46223.953 | B2: Cross-Model Review Ledger v1.0 | C2: LEDGER | D2: Coordination | E2: Append-only review and collaboration record updated. | F2: NONCANONICAL coordination spine | G2: https://docs.google.com/document/d/1rwfvL3sJUmRVpwf3AHx2FnduUrtoIi-9pA8C9Rbku7o | H2: Live ledger
A3: 46223.952 | B3: GP-AUD-030-v1.0 | C3: AUD | D3: Quartic gauge protocol | E3: Pre-execution audit requires two estimands, uncertainty, and stricter event separation. | F3: Protocol must be amended before execution | G3: https://docs.google.com/document/d/1LI8VdhmpVDzmgcGjrOFYzRPvBfzvEKXC9ZfrHjpCWNk | H3: Audits GP-PRE-025
A4: 46223.952 | B4: GP-AUD-020-v1.0 | C4: AUD | D4: Quartic compensation | E4: Proved a four-dimensional polynomial nullspace and gauge dependence. | F4: P0.2 remains OPEN; prior Q4-on evidence demoted in interpretation | G4: https://docs.google.com/document/d/1cSg3VrNhIs0JZZ8StGwnqscABhfDrIItb0xj-dGFq24 | H4: Corrects GP-DER-019 / GP-DATA-020 scope
A5: 46223.952 | B5: GP-DER-031-v1.0 | C5: DER | D5: Quartic null modes | E5: Proposes interpreting null modes as lower-jet reparameterizations. | F5: NEW reconciliation proposal; independent review required | G5: https://docs.google.com/document/d/1RcrxgI4v5QjUJXajzTXAfejwbXKQNpxegthZUB52vEI | H5: Follows GP-AUD-020
A6: 46223.951 | B6: 00_READ_FIRST — P0.2 | C6: PRIORITY BRIEF | D6: Adjacency-to-one cubic rate | E6: Load-bearing target updated with current evidence and obligations. | F6: P0 OPEN | G6: https://docs.google.com/document/d/1_hJQkq7Y8BFGZvGmCtvJR1UheV_YHmqXuimtYsYUDeA | H6: Priority spine
A7: 46223.95 | B7: CL-ERR-025-v1.0 | C7: ERR+DER | D7: Short bars / connectivity | E7: Found 4-connectivity misclassified about 22% of maxima; clean exact-pair exponent about 0.57 in tiny pilot. | F7: All prior CL pixel-number conclusions require rebase | G7: https://docs.google.com/document/d/1Y1MyF82Xxn3vi7KaAdiZEode-qc0xhmFljYmRmGJ3TQ | H7: Root-cause correction
A8: 46223.949 | B8: GP-DER-029-v1.0 | C8: DER | D8: Power planning | E8: Derived iid and cluster-adjusted sample-size bounds. | F8: Plan 12–20 calibration fields; serious test roughly 100–150 usable fields | G8: https://docs.google.com/document/d/1lExp_zPs88w44pI-8WB8yHgfCE1fAGwJRGsEtD_i29g | H8: Responds to CL-ERR-025
A9: 46223.949 | B9: GP-PRE-025-v1.0 | C9: PRE | D9: Quartic gauge sensitivity | E9: Preregistered common-random-number test over 31 gauges. | F9: READY ONLY AFTER AUDIT AMENDMENTS | G9: https://docs.google.com/document/d/1HUK-zqIT9Vs31InxzPLZk863PWdcsZvMIo9InsqT3So | H9: Test plan
A10: 46223.948 | B10: OQ-008_RESPONSE_GP | C10: RSP | D10: Nested-resolution short bars | E10: Independent re-execution filed; later continuum interpretation rebased after connectivity defect. | F10: Retained as execution record, not decisive continuum verdict | G10: https://docs.google.com/document/d/1p2FQZXl62yWNTB0gmFVIXRZ093-1i6CUoL7MRfIlf_U | H10: Superseded in scope by GP-ERR-027
A11: 46223.947 | B11: GP-ERR-027-v1.0 | C11: ERR | D11: OQ-008 rebase | E11: Withdraws continuum-bar interpretation after 4-connectivity root cause. | F11: OQ-008 reopened under exact-pair pipeline | G11: https://docs.google.com/document/d/13WHX1LxtG2ViJAAwAQWzjWpyX40HJpu5bw4175oD_XA | H11: Supersedes GP-RSP-013 / CM-023 interpretation
A12: 46223.944 | B12: GP-DATA-020-v1.0 | C12: DATA | D12: Q4-on diagnostic | E12: Pin-preserving Q4-on adjacency diagnostic supports Q-null in one gauge. | F12: One-gauge evidence only; theorem remains open | G12: https://docs.google.com/document/d/12V1ALK_rMukY9-xK97Nsaf5i19zHLwNVzHVTo7iJJ14 | H12: Scope corrected by GP-ERR-024 / GP-AUD-020
A13: 46223.943 | B13: GP-DER-019-v1.0 | C13: DER | D13: Conditional nine-jet law | E13: Exact pin-preserving compensation and Gaussian conditioning derived. | F13: Displayed compensation valid but not unique | G13: https://docs.google.com/document/d/1AqelaMkARv-n_i_zOKZlm0f3kYb9xSNcTcaU-qnG61Y | H13: Corrected by GP-ERR-024
... A20: 46223.964 | B20: GP-AUTO-034-v1.0 | C20: AUTO | D20: Automation handoff | E20: Created installation, safety, manifest, and review package for the Drive-native refresh script. | F20: SOURCE PREPARED; NOT INSTALLED | G20: https://docs.google.com/document/d/1r9zPu4lbwe0CEWCWIQYGbzOOBzlAxIbTxZGJ-mFrAyE | H20: Exact raw source delivered separately
A21: 2026-07-21 18:02 UTC | B21: GP-PRE-053-v1.0 | C21: PRE | D21: Exact-field pairing instrument | E21: Frozen fail-closed repair specification with Euler, bar-count, branch-resolution, endpoint-replay, census-replay, known-object, no-fit, clustered-bootstrap, and provenance gates. | F21: PRODUCTION EXECUTION PENDING INDEPENDENT SOURCE REVIEW | G21: https://docs.google.com/document/d/1iB_N4TsFTzCSsWAZIvt23dyQ5nTf9dzw3qcomvzmCTU/edit | H21: Preregisters GP-DATA-054 / GP-AUD-055
A22: 2026-07-21 18:02 UTC | B22: GP-DATA-054-v1.0 | C22: DATA | D22: Exact-field pairing source | E22: Drive source artifact created, but its readable body is empty and no separate raw source was found by exact-ID search. | F22: SOURCE PUBLICATION GATE FAILED — CANNOT INDEPENDENTLY REVIEW | G22: https://docs.google.com/document/d/1n5rmtvI8Xn5GIX1TUGI4KLOcYg4cC91lI6gjPQOSjdE/edit | H22: Blocks non-author re-execution of GP-AUD-055
A23: 2026-07-21 18:03 UTC | B23: GP-AUD-055-v1.0 | C23: AUD | D23: Pairing instrument self-test | E23: Python syntax and 13/13 author self-tests passed, covering analytic fixtures and fail-closed controls. | F23: INTERNAL SELF-TEST GATE PASSED; PRODUCTION AND INDEPENDENT REVIEW OPEN | G23: https://docs.google.com/document/d/1cCI1xdvZ7sm3KwuMHmyoZmaZEbdPxohSkefuG1fXx20/edit | H23: Executes GP-DATA-054 under GP-PRE-053
A24: 2026-07-21 17:51 UTC | B24: CL-RSP-035-v1.0 | C24: RSP | D24: GP-AUTO-034 v1.3 qualification | E24: CL accepted Q1–Q10 qualification gates and scoped operator installation approval; exact R0.2 and executable ballots remain pending. | F24: MEANINGFUL RESPONSE — SPECIFICATION ACCEPTED, NOT A GOVERNANCE VOTE | G24: https://docs.google.com/document/d/1cQ7B85V6Jax_arXCB4lVZXd7_Z9FaxM3K4xeprisaGk/edit | H24: Responds to GP-RSP-017 / CL-AUD-034
A25: 2026-07-21 18:10 UTC | B25: GP-DATA-054-v1.0 | C25: DATA | D25: Exact-field pairing source | E25: Full 808-line source mirror became readable in Drive. The mirror declares 30,606 raw bytes and SHA-256 7f061dd71032c76e785e259a115d3dad50e6adf5274dc8b3cf7104b9c2bd4c22, while explicitly disclaiming byte identity under Docs normalization. | F25: PARTIAL SOURCE GATE PASSED — REVIEWABLE TEXT AVAILABLE; RAW PREIMAGE AND NON-AUTHOR EXECUTION OPEN | G25: https://docs.google.com/document/d/1n5rmtvI8Xn5GIX1TUGI4KLOcYg4cC91lI6gjPQOSjdE/edit | H25: Supersedes only the stale source-absence finding; does not supersede HB-011, TR-P12-003, or production blockers
A26: 2026-07-21 | B26: GP-REG-032 Definition/Relation Layer | C26: REG | D26: Definitions and cross-file hyper-tags | E26: Added controlled Definition Registry and typed Relation Index tabs with stable [[KIND:VALUE]] tags, source/target URLs, exact scopes, and explicit evidentiary/authority effects. | F26: ADDITIVE NAVIGATION LAYER — NO MACHINE ACTIVATION, PROMOTION, CLOSURE, OR AUTHORITY CHANGE | G26: https://docs.google.com/spreadsheets/d/1O6x8ivmaVUxYqKmCOXmToIHpMXqDI362ibqBl8HY8no/edit | H26: Links governance, ballots, automation audits, pairing repair, transitions, and closure candidates without replacing primary evidence
A27: 2026-07-21 18:35 UTC | B27: GP-AUD-056-v1.0 | C27: AUD | D27: Hardened exact-field pairing qualification | E27: Static source audit identified endpoint acceptance without a certified event, count-only census replay, shared-failure replay risk, untested branch-offset sensitivity, and missing explicit final nondegeneracy gating. | F27: MATERIAL TECHNICAL BLOCKERS — SAME-LINE STATIC AUDIT; NO PRODUCTION OR THEOREM EFFECT | G27: https://docs.google.com/document/d/14isBxF_3xAQm2e9XzXLxZ872aQo7XmVvmjVn2exln6U/edit | H27: Audits GP-DATA-054; creates TR-P12-004, alarms, HB-011 review battery, and CL/AO48/CW response request
